Workbook

Sheet PARÁMETROS
A1: PARÁMETROS DEL CÁLCULO Y PRECIOS UNITARIOS (CUSCO)
A2: Celdas AMARILLAS con texto azul = datos editables. Todo el libro se recalcula al cambiarlas.
A4: 1. DATOS GENERALES
A5: Parámetro | B5: Valor | C5: Unidad | D5: Fuente / observación
A6: Fecha de inicio de obra (casco) | B6: 46300 | C6: fecha | D6: Dato de obra: editar
A7: Fecha de corte del avance | B7: 46300 | C7: fecha | D7: Actualizar cada semana (DASHBOARD)
A8: Desperdicio de concreto | B8: 0.05 | C8: % | D8: Dato del usuario (5 %)
A9: Desperdicio / rotura de casetones | B9: 0.03 | C9: % | D9: Supuesto: manipuleo de EPS
A10: N° de usos de la madera | B10: 4 | C10: usos | D10: Editable (práctica usual 3-5)
A11: N° de usos del triplay | B11: 5 | C11: usos | D11: Editable (triplay 18 mm)
A12: N° de usos de los puntales | B12: 8 | C12: usos | D12: Editable (eucalipto rollizo)
A13: Alambre N°16 por kg de acero | B13: 0.03 | C13: kg/kg | D13: APU 'Acero corrugado fy=4200' (CAPECO): 0.030 kg/kg
A14: Dados por zapata | B14: 9 | C14: und/zapata | D14: Supuesto: malla 3x3
A15: Cortes por disco de 7" | B15: 150 | C15: cortes | D15: Estimado; 1 corte por pieza
A16: Consumo de curador químico | B16: 0.2 | C16: L/m² | D16: Rendimiento típico de membranas de curado (≈5 m²/L)
A17: Consumo de desmoldante | B17: 0.08 | C17: L/m² | D17: Estimado (≈1 gal por 50 m²)
... A22: Traslape Ø3/4" (barras > 9 m) | B22: 1.15 | C22: m | D22: Lámina E-10, nota 8 (sup. clase B). Informativo: el plan de corte ya lo usa
A24: 2. LOSA ALIGERADA (casetón de poliestireno EPS; el modelo trae losa maciza de 200 mm por criterio)
A25: Parámetro | B25: Valor | C25: Unidad | D25: Fuente / observación
A26: Altura total de losa | B26: 0.2 | C26: m | D26: Láminas E-04 a E-07
A27: Espesor de losita | B27: 0.05 | C27: m | D27: Láminas E-04 a E-07
A28: Ancho de vigueta | B28: 0.1 | C28: m | D28: Láminas E-04 a E-07
A29: Ancho del casetón | B29: 0.3 | C29: m | D29: Casetón EPS 1.20 x 0.30 x 0.15
A30: Alto del casetón | B30: 0.15 | C30: m | D30: Casetón EPS 1.20 x 0.30 x 0.15
A31: Largo del casetón | B31: 1.2 | C31: m | D31: Casetón EPS 1.20 x 0.30 x 0.15
A32: Concreto por m² de aligerado | B32: =PARÁMETROS!$B$27+PARÁMETROS!$B$28*PARÁMETROS!$B$30/(PARÁMETROS!$B$28+PARÁMETROS!$B$29) -> 0.0875 | C32: m³/m² | D32: losita + vigueta x alto casetón / separación de viguetas
A33: Casetones por m² de aligerado | B33: =1/((PARÁMETROS!$B$28+PARÁMETROS!$B$29)*PARÁMETROS!$B$31) -> 2.0833333 | C33: und/m² | D33: 1 / (separación de viguetas x largo del casetón)
A35: 3. f'c POR ELEMENTO (no existe en el modelo: dato de las especificaciones, láminas E-01 a E-10)
A36: Elemento | B36: f'c (kg/cm²) | D36: Fuente / observación
A37: Zapatas | B37: 210 | D37: Especificación del proyecto (nota E-10)
A38: Vigas de conexión | B38: 210 | D38: Especificación del proyecto (nota E-10)
A39: Cimiento de escalera | B39: 210 | D39: Especificación del proyecto (nota E-10)
A40: Columnas | B40: 210 | D40: Especificación del proyecto (nota E-10)
A41: Vigas | B41: 210 | D41: Especificación del proyecto (nota E-10)
A42: Losa aligerada | B42: 210 | D42: Especificación del proyecto (nota E-10)
A43: Escalera | B43: 210 | D43: Especificación del proyecto (nota E-10)
A44: Falso piso | B44: 175 | D44: Especificación del proyecto (nota E-10)
A45: Solado | B45: 100 | D45: Especificación del proyecto (nota E-10)
A47: 4. DOSIFICACIÓN POR m³ DE CONCRETO (cemento en bolsas de 42.5 kg, piedra chancada 1/2")
A48: f'c (kg/cm²) | B48: Cemento (bls/m³) | C48: Arena gruesa (m³/m³) | D48: Piedra chancada (m³/m³) | E48: Agua (L/m³) | F48: Fuente
A49: 100 | B49: 5.2 | C49: 0.56 | D49: 0.68 | E49: 182 | F49: Estimado (solado): verificar
A50: 140 | B50: 7.01 | C50: 0.51 | D50: 0.64 | E50: 184 | F50: Tabla CAPECO, 'Costos y Presupuestos en Edificación'
A51: 175 | B51: 8.43 | C51: 0.54 | D51: 0.55 | E51: 185 | F51: Tabla CAPECO
A52: 210 | B52: 9.73 | C52: 0.52 | D52: 0.53 | E52: 186 | F52: Tabla CAPECO
A53: 245 | B53: 11.5 | C53: 0.5 | D53: 0.51 | E53: 187 | F53: Tabla CAPECO
A54: 280 | B54: 13.34 | C54: 0.45 | D54: 0.51 | E54: 189 | F54: Tabla CAPECO
A56: 5. RATIOS DE ENCOFRADO por m² de área de contacto (madera, triplay y puntales se dividen entre sus N° de usos)
A57: Tipo de encofrado | B57: Madera tornillo (p²/m²) | C57: Triplay 18 mm (m²/m²) | D57: Clavos 3" (kg/m²) | E57: Alambre N°8 (kg/m²) | F57: Puntales (und/m²) | G57: Dados (und/m²) | H57: Fuente
A58: VC costados | B58: 3.5 | C58: 0 | D58: 0.15 | E58: 0.2 | F58: 0 | G58: 2 | H58: Referencial de APU usuales (CAPECO); ajustar con el maestro de obra
A59: Cimiento escalera | B59: 3.5 | C59: 0 | D59: 0.15 | E59: 0.2 | F59: 0 | G59: 2 | H59: Referencial de APU usuales (CAPECO); ajustar con el maestro de obra
A60: Columnas | B60: 3 | C60: 1.05 | D60: 0.15 | E60: 0.25 | F60: 0 | G60: 2 | H60: Referencial de APU usuales (CAPECO); ajustar con el maestro de obra
A61: Vigas costados | B61: 3 | C61: 1.05 | D61: 0.18 | E61: 0.25 | F61: 0 | G61: 2 | H61: Referencial de APU usuales (CAPECO); ajustar con el maestro de obra
A62: Vigas fondo | B62: 4 | C62: 1.05 | D62: 0.18 | E62: 0.25 | F62: 3.5 | G62: 4 | H62: Referencial de APU usuales (CAPECO); ajustar con el maestro de obra
A63: Losa fondo | B63: 2.5 | C63: 1.05 | D63: 0.12 | E63: 0.15 | F63: 1 | G63: 2.5 | H63: Referencial de APU usuales (CAPECO); ajustar con el maestro de obra
A64: Losa bordes | B64: 3 | C64: 0 | D64: 0.15 | E64: 0.2 | F64: 0 | G64: 0 | H64: Referencial de APU usuales (CAPECO); ajustar con el maestro de obra
A65: Escalera fondo | B65: 4 | C65: 1.05 | D65: 0.2 | E65: 0.2 | F65: 1.2 | G65: 2.5 | H65: Referencial de APU usuales (CAPECO); ajustar con el maestro de obra
A66: Escalera costados | B66: 3.5 | C66: 0 | D66: 0.2 | E66: 0.2 | F66: 0 | G66: 0 | H66: Referencial de APU usuales (CAPECO); ajustar con el maestro de obra
A68: 6. PRECIOS UNITARIOS REFERENCIALES - CUSCO (incluyen IGV; confirmar precio puesto en obra, San Jerónimo)
A69: Insumo | B69: Unidad de compra | C69: Precio (S/) | D69: Fecha de cotización | E69: Proveedor / fuente | F69: Categoría | G69: Observación
A70: Cemento Portland IP 42.5 kg | B70: bolsa | C70: 27 | D70: 46293 | E70: Sodimac.pe - Cemento Yura Tipo IP | F70: Concreto | G70: En Cusco hay distribuidores desde ~S/ 23 (almacén); confirmar
A71: Arena gruesa | B71: m³ | C71: 70 | D71: 46293 | E71: Estimado: cotización 'Agregados Cusco' S/ 60 + rango 2026 S/ 55-70 (OneEstimate) | F71: Concreto | G71: Estimado: cotizar
A72: Piedra chancada 1/2" | B72: m³ | C72: 80 | D72: 46293 | E72: Estimado: 'Agregados Cusco' S/ 65 + rango 2026 S/ 75-95 (OneEstimate) | F72: Concreto | G72: Estimado: cotizar
A73: Agua | B73: m³ | C73: 7 | D73: 46293 | E73: Estimado (tarifa no doméstica SEDACUSCO) | F73: Concreto | G73: Estimado: confirmar
A74: Casetón EPS 1.20x0.30x0.15 | B74: und | C74: 12.9 | D74: 46293 | E74: Promart.pe - Etsapol (tienda Cusco) | F74: Concreto | G74: Ref. Dinova S/ 12.00
A75: Varilla Ø1/4" x 9 m | B75: und | C75: 9.5 | D75: 46293 | E75: Estimado (2.25 kg x ~S/ 4.2/kg) | F75: Acero | G75: Estimado: cotizar (Aceros Arequipa)
A76: Varilla Ø3/8" x 9 m | B76: und | C76: 20.13 | D76: 46293 | E76: Promart.pe - Aceros Arequipa A615, precio online | F76: Acero
A77: Varilla Ø1/2" x 9 m | B77: und | C77: 36.09 | D77: 46293 | E77: Promart.pe - Aceros Arequipa A615, precio online | F77: Acero
A78: Varilla Ø5/8" x 9 m | B78: und | C78: 55.82 | D78: 46293 | E78: Promart.pe - Aceros Arequipa A615, precio online | F78: Acero
A79: Varilla Ø3/4" x 9 m | B79: und | C79: 82.09 | D79: 46293 | E79: Promart.pe - Aceros Arequipa A615, precio online | F79: Acero
A80: Alambre negro N°16 | B80: kg | C80: 3.65 | D80: 46293 | E80: Promart.pe - Prodac rollo 100 kg (S/ 365) | F80: Acero
A81: Disco de corte 7" | B81: und | C81: 12 | D81: 46293 | E81: Estimado | F81: Acero | G81: Estimado: cotizar
A82: Dados de concreto | B82: und | C82: 0.5 | D82: 46293 | E82: Estimado (fabricados en obra) | F82: Acero | G82: Estimado
A83: Madera tornillo | B83: p² | C83: 5.5 | D83: 46293 | E83: Estimado: cotización madera tornillo S/ 4.90-4.95/p² (antigua) actualizada | F83: Encofrado | G83: Estimado: cotizar en madereras de San Sebastián
A84: Triplay 18 mm 1.22x2.44 | B84: plancha | C84: 115 | D84: 46293 | E84: Estimado | F84: Encofrado | G84: Estimado: cotizar
A85: Puntal eucalipto 3"-4" x 3 m | B85: und | C85: 18 | D85: 46293 | E85: Estimado (ref. rollizo 5" x 3 m S/ 49, IMA) | F85: Encofrado | G85: Estimado: cotizar
A86: Clavos 3" | B86: kg | C86: 6.5 | D86: 46293 | E86: Estimado | F86: Encofrado | G86: Estimado: cotizar
A87: Alambre negro N°8 | B87: kg | C87: 5.9 | D87: 46293 | E87: Promart.pe - Prodac rollo 10 kg (S/ 59) | F87: Encofrado
A88: Desmoldante | B88: gal | C88: 45 | D88: 46293 | E88: Estimado | F88: Encofrado | G88: Estimado: cotizar
A89: Curador químico (membrana) | B89: gal | C89: 40 | D89: 46293 | E89: Estimado | F89: Curado | G89: Estimado: cotizar
A91: 7. PESO NOMINAL DEL ACERO (NTP 341.031 / ASTM A615)
A92: Ø | B92: kg/m | C92: Insumo de compra
A93: 1/4 | B93: 0.25 | C93: Varilla Ø1/4" x 9 m
A94: 3/8 | B94: 0.56 | C94: Varilla Ø3/8" x 9 m
A95: 1/2 | B95: 0.994 | C95: Varilla Ø1/2" x 9 m
A96: 5/8 | B96: 1.552 | C96: Varilla Ø5/8" x 9 m
A97: 3/4 | B97: 2.235 | C97: Varilla Ø3/4" x 9 m
A99: Leyenda: amarillo + azul = dato editable · negro = fórmula · verde = vínculo a otra hoja.

Sheet METRADO POR NIVEL
A1: METRADO POR NIVEL - CASCO ESTRUCTURAL
A2: Cantidades del modelo IFC (hoja DATOS MODELO) + parámetros. Columnas I a W: insumos que genera cada partida.
A4: CIMENTACIÓN
A5: Nivel | B5: Partida | C5: Elemento | D5: Unidad | E5: Cantidad neta | F5: Desperdicio | G5: Cantidad total | H5: f'c / tipo | I5: Cemento (bls) | J5: Arena gruesa (m³) | K5: Piedra 1/2" (m³) | L5: Agua (m³) | M5: Casetón EPS (und) | N5: Alambre N°16 (kg) | O5: Madera tornillo (p²) | P5: Triplay (m²) | Q5: Clavos 3" (kg) | R5: Alambre N°8 (kg) | S5: Puntales (und) | T5: Desmoldante (gal) | U5: Curador (gal) | V5: Dados (und) | W5: Discos de corte (und) | X5: Nota
A6: CIMENTACIÓN | B6: Concreto | C6: Zapatas | D6: m³ | E6: =SUMIFS('DATOS MODELO'!$F$5:$F$227,'DATOS MODELO'!$B$5:$B$227,"CIMENTACIÓN",'DATOS MODELO'!$C$5:$C$227,"Zapatas") -> 23.791993 | F6: =PARÁMETROS!$B$8 -> 0.05 | G6: =E6*(1+F6) -> 24.981593 | H6: =INDEX(PARÁMETROS!$B$37:$B$45,MATCH(C6,PARÁMETROS!$A$37:$A$45,0)) -> 210 | I6: =G6*INDEX(PARÁMETROS!$B$49:$B$54,MATCH(H6,PARÁMETROS!$A$49:$A$54,0)) -> 243.0709 | J6: =G6*INDEX(PARÁMETROS!$C$49:$C$54,MATCH(H6,PARÁMETROS!$A$49:$A$54,0)) -> 12.990428 | K6: =G6*INDEX(PARÁMETROS!$D$49:$D$54,MATCH(H6,PARÁMETROS!$A$49:$A$54,0)) -> 13.240244 | L6: =G6*INDEX(PARÁMETROS!$E$49:$E$54,MATCH(H6,PARÁMETROS!$A$49:$A$54,0))/1000 -> 4.6465763 | X6: Vaciadas contra el terreno
A7: CIMENTACIÓN | B7: Concreto | C7: Vigas de conexión | D7: m³ | E7: =SUMIFS('DATOS MODELO'!$F$5:$F$227,'DATOS MODELO'!$B$5:$B$227,"CIMENTACIÓN",'DATOS MODELO'!$C$5:$C$227,"Vigas de conexión") -> 5.3450015 | F7: =PARÁMETROS!$B$8 -> 0.05 | G7: =E7*(1+F7) -> 5.6122516 | H7: =INDEX(PARÁMETROS!$B$37:$B$45,MATCH(C7,PARÁMETROS!$A$37:$A$45,0)) -> 210 | I7: =G7*INDEX(PARÁMETROS!$B$49:$B$54,MATCH(H7,PARÁMETROS!$A$49:$A$54,0)) -> 54.607208 | J7: =G7*INDEX(PARÁMETROS!$C$49:$C$54,MATCH(H7,PARÁMETROS!$A$49:$A$54,0)) -> 2.9183708 | K7: =G7*INDEX(PARÁMETROS!$D$49:$D$54,MATCH(H7,PARÁMETROS!$A$49:$A$54,0)) -> 2.9744933 | L7: =G7*INDEX(PARÁMETROS!$E$49:$E$54,MATCH(H7,PARÁMETROS!$A$49:$A$54,0))/1000 -> 1.0438788
A8: CIMENTACIÓN | B8: Concreto | C8: Cimiento de escalera | D8: m³ | E8: =SUMIFS('DATOS MODELO'!$F$5:$F$227,'DATOS MODELO'!$B$5:$B$227,"CIMENTACIÓN",'DATOS MODELO'!$C$5:$C$227,"Cimiento de escalera") -> 0.62499998 | F8: =PARÁMETROS!$B$8 -> 0.05 | G8: =E8*(1+F8) -> 0.65624998 | H8: =INDEX(PARÁMETROS!$B$37:$B$45,MATCH(C8,PARÁMETROS!$A$37:$A$45,0)) -> 210 | I8: =G8*INDEX(PARÁMETROS!$B$49:$B$54,MATCH(H8,PARÁMETROS!$A$49:$A$54,0)) -> 6.3853123 | J8: =G8*INDEX(PARÁMETROS!$C$49:$C$54,MATCH(H8,PARÁMETROS!$A$49:$A$54,0)) -> 0.34124999 | K8: =G8*INDEX(PARÁMETROS!$D$49:$D$54,MATCH(H8,PARÁMETROS!$A$49:$A$54,0)) -> 0.34781249 | L8: =G8*INDEX(PARÁMETROS!$E$49:$E$54,MATCH(H8,PARÁMETROS!$A$49:$A$54,0))/1000 -> 0.1220625
A9: CIMENTACIÓN | B9: Concreto | C9: Solado | D9: m³ | E9: =('DATOS MODELO'!$B$283+'DATOS MODELO'!$B$284)*PARÁMETROS!$B$19*PARÁMETROS!$B$18 -> 5.7507 | F9: =PARÁMETROS!$B$8 -> 0.05 | G9: =E9*(1+F9) -> 6.038235 | H9: =INDEX(PARÁMETROS!$B$37:$B$45,MATCH(C9,PARÁMETROS!$A$37:$A$45,0)) -> 100 | I9: =G9*INDEX(PARÁMETROS!$B$49:$B$54,MATCH(H9,PARÁMETROS!$A$49:$A$54,0)) -> 31.398822 | J9: =G9*INDEX(PARÁMETROS!$C$49:$C$54,MATCH(H9,PARÁMETROS!$A$49:$A$54,0)) -> 3.3814116 | K9: =G9*INDEX(PARÁMETROS!$D$49:$D$54,MATCH(H9,PARÁMETROS!$A$49:$A$54,0)) -> 4.1059998 | L9: =G9*INDEX(PARÁMETROS!$E$49:$E$54,MATCH(H9,PARÁMETROS!$A$49:$A$54,0))/1000 -> 1.0989588 | X9: Partida evitable (no modelada): área bajo zapatas y VC x espesor
A10: CIMENTACIÓN | B10: Encofrado | C10: Vigas de conexión | D10: m² | E10: =SUMIFS('DATOS MODELO'!$G$5:$G$227,'DATOS MODELO'!$B$5:$B$227,"CIMENTACIÓN",'DATOS MODELO'!$C$5:$C$227,"Vigas de conexión") -> 40.060636 | F10: 0 | G10: =E10*(1+F10) -> 40.060636 | H10: VC costados | O10: =G10*INDEX(PARÁMETROS!$B$58:$B$66,MATCH(H10,PARÁMETROS!$A$58:$A$66,0))/PARÁMETROS!$B$10 -> 35.053057 | P10: =G10*INDEX(PARÁMETROS!$C$58:$C$66,MATCH(H10,PARÁMETROS!$A$58:$A$66,0))/PARÁMETROS!$B$11 -> 0 | Q10: =G10*INDEX(PARÁMETROS!$D$58:$D$66,MATCH(H10,PARÁMETROS!$A$58:$A$66,0)) -> 6.0090954 | R10: =G10*INDEX(PARÁMETROS!$E$58:$E$66,MATCH(H10,PARÁMETROS!$A$58:$A$66,0)) -> 8.0121272 | S10: =G10*INDEX(PARÁMETROS!$F$58:$F$66,MATCH(H10,PARÁMETROS!$A$58:$A$66,0))/PARÁMETROS!$B$12 -> 0 | T10: =G10*PARÁMETROS!$B$17/3.785 -> 0.84672414 | V10: =G10*INDEX(PARÁMETROS!$G$58:$G$66,MATCH(H10,PARÁMETROS!$A$58:$A$66,0)) -> 80.121272 | X10: Fondo sobre solado/terreno
A11: CIMENTACIÓN | B11: Encofrado | C11: Cimiento de escalera | D11: m² | E11: =SUMIFS('DATOS MODELO'!$G$5:$G$227,'DATOS MODELO'!$B$5:$B$227,"CIMENTACIÓN",'DATOS MODELO'!$C$5:$C$227,"Cimiento de escalera") -> 2.9355468 | F11: 0 | G11: =E11*(1+F11) -> 2.9355468 | H11: Cimiento escalera | O11: =G11*INDEX(PARÁMETROS!$B$58:$B$66,MATCH(H11,PARÁMETROS!$A$58:$A$66,0))/PARÁMETROS!$B$10 -> 2.5686034 | P11: =G11*INDEX(PARÁMETROS!$C$58:$C$66,MATCH(H11,PARÁMETROS!$A$58:$A$66,0))/PARÁMETROS!$B$11 -> 0 | Q11: =G11*INDEX(PARÁMETROS!$D$58:$D$66,MATCH(H11,PARÁMETROS!$A$58:$A$66,0)) -> 0.44033202 | R11: =G11*INDEX(PARÁMETROS!$E$58:$E$66,MATCH(H11,PARÁMETROS!$A$58:$A$66,0)) -> 0.58710936 | S11: =G11*INDEX(PARÁMETROS!$F$58:$F$66,MATCH(H11,PARÁMETROS!$A$58:$A$66,0))/PARÁMETROS!$B$12 -> 0 | T11: =G11*PARÁMETROS!$B$17/3.785 -> 0.062045903 | V11: =G11*INDEX(PARÁMETROS!$G$58:$G$66,MATCH(H11,PARÁMETROS!$A$58:$A$66,0)) -> 5.8710936
A12: CIMENTACIÓN | B12: Acero | C12: Zapatas | D12: kg | E12: =SUMIFS('DATOS MODELO'!$E$232:$E$279,'DATOS MODELO'!$A$232:$A$279,"CIMENTACIÓN",'DATOS MODELO'!$B$232:$B$279,"Zapatas",'DATOS MODELO'!$C$232:$C$279,"1/4")*INDEX(PARÁMETROS!$B$93:$B$97,MATCH("1/4",PARÁMETROS!$A$93:$A$97,0))+SUMIFS('DATOS MODELO'!$E$232:$E$279,'DATOS MODELO'!$A$232:$A$279,"CIMENTACIÓN",'DATOS MODELO'!$B$232:$B$279,"Zapatas",'DATOS MODELO'!$C$232:$C$279,"3/8")*INDEX(PARÁMETROS!$B$93:$B$97,MATCH("3/8",PARÁMETROS!$A$93:$A$97,0))+SUMIFS('DATOS MODELO'!$E$232:$E$279,'DATOS MODELO'!$A$232:$A$279,"CIMENTACIÓN",'DATOS MODELO'!$B$232:$B$279,"Zapatas",'DATOS MODELO'!$C$232:$C$279,"1/2")*INDEX(PARÁMETROS!$B$93:$B$97,MATCH("1/2",PARÁMETROS!$A$93:$A$97,0))+SUMIFS('DATOS MODELO'!$E$232:$E$279,'DATOS MODELO'!$A$232:$A$279,"CIMENTACIÓN",'DATOS MODELO'!$B$232:$B$279,"Zapatas",'DATOS MODELO'!$C$232:$C$279,"5/8")*INDEX(PARÁMETROS!$B$93:$B$97,MATCH("5/8",PARÁMETROS!$A$93:$A$97,0))+SUMIFS('DATOS MODELO'!$E$232:$E$279,'DATOS MODELO'!$A$232:$A$279,"CIMENTACIÓN",'DATOS MODELO'!$B$232:$B$279,"Zapatas",'DATOS MODELO'!$C$232:$C$279,"3/4")*INDEX(PARÁMETROS!$B$93:$B$97,MATCH("3/4",PARÁMETROS!$A$93:$A$97,0)) -> 851.99289 | F12: 0 | G12: =E12*(1+F12) -> 851.99289 | H12: fy 4200 | N12: =G12*PARÁMETROS!$B$13 -> 25.559787 | V12: =COUNTIFS('DATOS MODELO'!$B$5:$B$227,"CIMENTACIÓN",'DATOS MODELO'!$C$5:$C$227,"Zapatas")*PARÁMETROS!$B$14 -> 126 | W12: =SUMIFS('DATOS MODELO'!$D$232:$D$279,'DATOS MODELO'!$A$232:$A$279,"CIMENTACIÓN",'DATOS MODELO'!$B$232:$B$279,"Zapatas")/PARÁMETROS!$B$15 -> 1.84 | X12: Desperdicio de corte: ver ACERO – DESPIECE (varillas de 9 m)
A13: CIMENTACIÓN | B13: Acero | C13: Vigas de conexión | D13: kg | E13: =SUMIFS('DATOS MODELO'!$E$232:$E$279,'DATOS MODELO'!$A$232:$A$279,"CIMENTACIÓN",'DATOS MODELO'!$B$232:$B$279,"Vigas de conexión",'DATOS MODELO'!$C$232:$C$279,"1/4")*INDEX(PARÁMETROS!$B$93:$B$97,MATCH("1/4",PARÁMETROS!$A$93:$A$97,0))+SUMIFS('DATOS MODELO'!$E$232:$E$279,'DATOS MODELO'!$A$232:$A$279,"CIMENTACIÓN",'DATOS MODELO'!$B$232:$B$279,"Vigas de conexión",'DATOS MODELO'!$C$232:$C$279,"3/8")*INDEX(PARÁMETROS!$B$93:$B$97,MATCH("3/8",PARÁMETROS!$A$93:$A$97,0))+SUMIFS('DATOS MODELO'!$E$232:$E$279,'DATOS MODELO'!$A$232:$A$279,"CIMENTACIÓN",'DATOS MODELO'!$B$232:$B$279,"Vigas de conexión",'DATOS MODELO'!$C$232:$C$279,"1/2")*INDEX(PARÁMETROS!$B$93:$B$97,MATCH("1/2",PARÁMETROS!$A$93:$A$97,0))+SUMIFS('DATOS MODELO'!$E$232:$E$279,'DATOS MODELO'!$A$232:$A$279,"CIMENTACIÓN",'DATOS MODELO'!$B$232:$B$279,"Vigas de conexión",'DATOS MODELO'!$C$232:$C$279,"5/8")*INDEX(PARÁMETROS!$B$93:$B$97,MATCH("5/8",PARÁMETROS!$A$93:$A$97,0))+SUMIFS('DATOS MODELO'!$E$232:$E$279,'DATOS MODELO'!$A$232:$A$279,"CIMENTACIÓN",'DATOS MODELO'!$B$232:$B$279,"Vigas de conexión",'DATOS MODELO'!$C$232:$C$279,"3/4")*INDEX(PARÁMETROS!$B$93:$B$97,MATCH("3/4",PARÁMETROS!$A$93:$A$97,0)) -> 1534.9779 | F13: 0 | G13: =E13*(1+F13) -> 1534.9779 | H13: fy 4200 | N13: =G13*PARÁMETROS!$B$13 -> 46.049337 | W13: =SUMIFS('DATOS MODELO'!$D$232:$D$279,'DATOS MODELO'!$A$232:$A$279,"CIMENTACIÓN",'DATOS MODELO'!$B$232:$B$279,"Vigas de conexión")/PARÁMETROS!$B$15 -> 3.1466667 | X13: Desperdicio de corte: ver ACERO – DESPIECE (varillas de 9 m)
A14: CIMENTACIÓN | B14: Acero | C14: Cimiento de escalera | D14: kg | E14: =SUMIFS('DATOS MODELO'!$E$232:$E$279,'DATOS MODELO'!$A$232:$A$279,"CIMENTACIÓN",'DATOS MODELO'!$B$232:$B$279,"Cimiento de escalera",'DATOS MODELO'!$C$232:$C$279,"1/4")*INDEX(PARÁMETROS!$B$93:$B$97,MATCH("1/4",PARÁMETROS!$A$93:$A$97,0))+SUMIFS('DATOS MODELO'!$E$232:$E$279,'DATOS MODELO'!$A$232:$A$279,"CIMENTACIÓN",'DATOS MODELO'!$B$232:$B$279,"Cimiento de escalera",'DATOS MODELO'!$C$232:$C$279,"3/8")*INDEX(PARÁMETROS!$B$93:$B$97,MATCH("3/8",PARÁMETROS!$A$93:$A$97,0))+SUMIFS('DATOS MODELO'!$E$232:$E$279,'DATOS MODELO'!$A$232:$A$279,"CIMENTACIÓN",'DATOS MODELO'!$B$232:$B$279,"Cimiento de escalera",'DATOS MODELO'!$C$232:$C$279,"1/2")*INDEX(PARÁMETROS!$B$93:$B$97,MATCH("1/2",PARÁMETROS!$A$93:$A$97,0))+SUMIFS('DATOS MODELO'!$E$232:$E$279,'DATOS MODELO'!$A$232:$A$279,"CIMENTACIÓN",'DATOS MODELO'!$B$232:$B$279,"Cimiento de escalera",'DATOS MODELO'!$C$232:$C$279,"5/8")*INDEX(PARÁMETROS!$B$93:$B$97,MATCH("5/8",PARÁMETROS!$A$93:$A$97,0))+SUMIFS('DATOS MODELO'!$E$232:$E$279,'DATOS MODELO'!$A$232:$A$279,"CIMENTACIÓN",'DATOS MODELO'!$B$232:$B$279,"Cimiento de escalera",'DATOS MODELO'!$C$232:$C$279,"3/4")*INDEX(PARÁMETROS!$B$93:$B$97,MATCH("3/4",PARÁMETROS!$A$93:$A$97,0)) -> 3.6568 | F14: 0 | G14: =E14*(1+F14) -> 3.6568 | H14: fy 4200 | N14: =G14*PARÁMETROS!$B$13 -> 0.109704 | W14: =SUMIFS('DATOS MODELO'!$D$232:$D$279,'DATOS MODELO'!$A$232:$A$279,"CIMENTACIÓN",'DATOS MODELO'!$B$232:$B$279,"Cimiento de escalera")/PARÁMETROS!$B$15 -> 0.033333333 | X14: Desperdicio de corte: ver ACERO – DESPIECE (varillas de 9 m)
A15: CIMENTACIÓN | B15: Curado | C15: Zapatas | D15: m² | E15: =SUMIFS('DATOS MODELO'!$I$5:$I$227,'DATOS MODELO'!$B$5:$B$227,"CIMENTACIÓN",'DATOS MODELO'!$C$5:$C$227,"Zapatas") -> 32.82054 | F15: 0 | G15: =E15*(1+F15) -> 32.82054 | H15: curador | U15: =G15*PARÁMETROS!$B$16/3.785 -> 1.7342426 | X15: Cara superior (costados contra terreno)
A16: CIMENTACIÓN | B16: Curado | C16: Vigas de conexión | D16: m² | E16: =SUMIFS('DATOS MODELO'!$I$5:$I$227,'DATOS MODELO'!$B$5:$B$227,"CIMENTACIÓN",'DATOS MODELO'!$C$5:$C$227,"Vigas de conexión")+SUMIFS('DATOS MODELO'!$J$5:$J$227,'DATOS MODELO'!$B$5:$B$227,"CIMENTACIÓN",'DATOS MODELO'!$C$5:$C$227,"Vigas de conexión") -> 52.585246 | F16: 0 | G16: =E16*(1+F16) -> 52.585246 | H16: curador | U16: =G16*PARÁMETROS!$B$16/3.785 -> 2.7786127
A17: CIMENTACIÓN | B17: Curado | C17: Cimiento de escalera | D17: m² | E17: =SUMIFS('DATOS MODELO'!$I$5:$I$227,'DATOS MODELO'!$B$5:$B$227,"CIMENTACIÓN",'DATOS MODELO'!$C$5:$C$227,"Cimiento de escalera")+SUMIFS('DATOS MODELO'!$J$5:$J$227,'DATOS MODELO'!$B$5:$B$227,"CIMENTACIÓN",'DATOS MODELO'!$C$5:$C$227,"Cimiento de escalera") -> 3.2486571 | F17: 0 | G17: =E17*(1+F17) -> 3.2486571 | H17: curador | U17: =G17*PARÁMETROS!$B$16/3.785 -> 0.17165956
A18: TOTAL CIMENTACIÓN | I18: =SUM(I6:I17) -> 335.46224 | J18: =SUM(J6:J17) -> 19.631461 | K18: =SUM(K6:K17) -> 20.66855 | L18: =SUM(L6:L17) -> 6.9114764 | M18: =SUM(M6:M17) -> 0 | N18: =SUM(N6:N17) -> 71.718828 | O18: =SUM(O6:O17) -> 37.62166 | P18: =SUM(P6:P17) -> 0 | ... W18: =SUM(W6:W17) -> 5.02
B19: Subtotal Concreto | D19: m³ | G19: =SUMIFS(G6:G17,B6:B17,"Concreto") -> 37.28833
B20: Subtotal Encofrado | D20: m² | G20: =SUMIFS(G6:G17,B6:B17,"Encofrado") -> 42.996183
B21: Subtotal Acero | D21: kg | G21: =SUMIFS(G6:G17,B6:B17,"Acero") -> 2390.6276
B22: Subtotal Curado | D22: m² | G22: =SUMIFS(G6:G17,B6:B17,"Curado") -> 88.654444
A24: NIVEL 1
A25: Nivel | B25: Partida | C25: Elemento | D25: Unidad | E25: Cantidad neta | F25: Desperdicio | G25: Cantidad total | H25: f'c / tipo | I25: Cemento (bls) | J25: Arena gruesa (m³) | K25: Piedra 1/2" (m³) | L25: Agua (m³) | M25: Casetón EPS (und) | N25: Alambre N°16 (kg) | O25: Madera tornillo (p²) | P25: Triplay (m²) | Q25: Clavos 3" (kg) | R25: Alambre N°8 (kg) | S25: Puntales (und) | T25: Desmoldante (gal) | U25: Curador (gal) | V25: Dados (und) | W25: Discos de corte (und) | X25: Nota
A26: NIVEL 1 | B26: Concreto | C26: Columnas | D26: m³ | E26: =SUMIFS('DATOS MODELO'!$F$5:$F$227,'DATOS MODELO'!$B$5:$B$227,"NIVEL 1",'DATOS MODELO'!$C$5:$C$227,"Columnas") -> 4.1939951 | F26: =PARÁMETROS!$B$8 -> 0.05 | G26: =E26*(1+F26) -> 4.4036949 | H26: =INDEX(PARÁMETROS!$B$37:$B$45,MATCH(C26,PARÁMETROS!$A$37:$A$45,0)) -> 210 | I26: =G26*INDEX(PARÁMETROS!$B$49:$B$54,MATCH(H26,PARÁMETROS!$A$49:$A$54,0)) -> 42.847951 | J26: =G26*INDEX(PARÁMETROS!$C$49:$C$54,MATCH(H26,PARÁMETROS!$A$49:$A$54,0)) -> 2.2899213 | K26: =G26*INDEX(PARÁMETROS!$D$49:$D$54,MATCH(H26,PARÁMETROS!$A$49:$A$54,0)) -> 2.3339583 | L26: =G26*INDEX(PARÁMETROS!$E$49:$E$54,MATCH(H26,PARÁMETROS!$A$49:$A$54,0))/1000 -> 0.81908724 | X26: Columnas de cimentación a N1
A27: NIVEL 1 | B27: Concreto | C27: Falso piso | D27: m³ | E27: =SUMIFS('DATOS MODELO'!$F$5:$F$227,'DATOS MODELO'!$B$5:$B$227,"NIVEL 1",'DATOS MODELO'!$C$5:$C$227,"Falso piso") -> 9.0525745 | F27: =PARÁMETROS!$B$8 -> 0.05 | G27: =E27*(1+F27) -> 9.5052032 | H27: =INDEX(PARÁMETROS!$B$37:$B$45,MATCH(C27,PARÁMETROS!$A$37:$A$45,0)) -> 175 | I27: =G27*INDEX(PARÁMETROS!$B$49:$B$54,MATCH(H27,PARÁMETROS!$A$49:$A$54,0)) -> 80.128863 | J27: =G27*INDEX(PARÁMETROS!$C$49:$C$54,MATCH(H27,PARÁMETROS!$A$49:$A$54,0)) -> 5.1328097 | K27: =G27*INDEX(PARÁMETROS!$D$49:$D$54,MATCH(H27,PARÁMETROS!$A$49:$A$54,0)) -> 5.2278618 | L27: =G27*INDEX(PARÁMETROS!$E$49:$E$54,MATCH(H27,PARÁMETROS!$A$49:$A$54,0))/1000 -> 1.7584626 | X27: e = 0.10 (modelo)
A28: NIVEL 1 | B28: Encofrado | C28: Columnas | D28: m² | E28: =SUMIFS('DATOS MODELO'!$G$5:$G$227,'DATOS MODELO'!$B$5:$B$227,"NIVEL 1",'DATOS MODELO'!$C$5:$C$227,"Columnas") -> 34.692085 | F28: 0 | G28: =E28*(1+F28) -> 34.692085 | H28: Columnas | O28: =G28*INDEX(PARÁMETROS!$B$58:$B$66,MATCH(H28,PARÁMETROS!$A$58:$A$66,0))/PARÁMETROS!$B$10 -> 26.019063 | P28: =G28*INDEX(PARÁMETROS!$C$58:$C$66,MATCH(H28,PARÁMETROS!$A$58:$A$66,0))/PARÁMETROS!$B$11 -> 7.2853378 | Q28: =G28*INDEX(PARÁMETROS!$D$58:$D$66,MATCH(H28,PARÁMETROS!$A$58:$A$66,0)) -> 5.2038127 | R28: =G28*INDEX(PARÁMETROS!$E$58:$E$66,MATCH(H28,PARÁMETROS!$A$58:$A$66,0)) -> 8.6730212 | S28: =G28*INDEX(PARÁMETROS!$F$58:$F$66,MATCH(H28,PARÁMETROS!$A$58:$A$66,0))/PARÁMETROS!$B$12 -> 0 | T28: =G28*PARÁMETROS!$B$17/3.785 -> 0.7332541 | V28: =G28*INDEX(PARÁMETROS!$G$58:$G$66,MATCH(H28,PARÁMETROS!$A$58:$A$66,0)) -> 69.384169
A29: NIVEL 1 | B29: Acero | C29: Columnas | D29: kg | E29: =SUMIFS('DATOS MODELO'!$E$232:$E$279,'DATOS MODELO'!$A$232:$A$279,"NIVEL 1",'DATOS MODELO'!$B$232:$B$279,"Columnas",'DATOS MODELO'!$C$232:$C$279,"1/4")*INDEX(PARÁMETROS!$B$93:$B$97,MATCH("1/4",PARÁMETROS!$A$93:$A$97,0))+SUMIFS('DATOS MODELO'!$E$232:$E$279,'DATOS MODELO'!$A$232:$A$279,"NIVEL 1",'DATOS MODELO'!$B$232:$B$279,"Columnas",'DATOS MODELO'!$C$232:$C$279,"3/8")*INDEX(PARÁMETROS!$B$93:$B$97,MATCH("3/8",PARÁMETROS!$A$93:$A$97,0))+SUMIFS('DATOS MODELO'!$E$232:$E$279,'DATOS MODELO'!$A$232:$A$279,"NIVEL 1",'DATOS MODELO'!$B$232:$B$279,"Columnas",'DATOS MODELO'!$C$232:$C$279,"1/2")*INDEX(PARÁMETROS!$B$93:$B$97,MATCH("1/2",PARÁMETROS!$A$93:$A$97,0))+SUMIFS('DATOS MODELO'!$E$232:$E$279,'DATOS MODELO'!$A$232:$A$279,"NIVEL 1",'DATOS MODELO'!$B$232:$B$279,"Columnas",'DATOS MODELO'!$C$232:$C$279,"5/8")*INDEX(PARÁMETROS!$B$93:$B$97,MATCH("5/8",PARÁMETROS!$A$93:$A$97,0))+SUMIFS('DATOS MODELO'!$E$232:$E$279,'DATOS MODELO'!$A$232:$A$279,"NIVEL 1",'DATOS MODELO'!$B$232:$B$279,"Columnas",'DATOS MODELO'!$C$232:$C$279,"3/4")*INDEX(PARÁMETROS!$B$93:$B$97,MATCH("3/4",PARÁMETROS!$A$93:$A$97,0)) -> 1285.4986 | F29: 0 | G29: =E29*(1+F29) -> 1285.4986 | H29: fy 4200 | N29: =G29*PARÁMETROS!$B$13 -> 38.564959 | W29: =SUMIFS('DATOS MODELO'!$D$232:$D$279,'DATOS MODELO'!$A$232:$A$279,"NIVEL 1",'DATOS MODELO'!$B$232:$B$279,"Columnas")/PARÁMETROS!$B$15 -> 6.12 | X29: Desperdicio de corte: ver ACERO – DESPIECE (varillas de 9 m)
A30: NIVEL 1 | B30: Curado | C30: Columnas | D30: m² | E30: =SUMIFS('DATOS MODELO'!$J$5:$J$227,'DATOS MODELO'!$B$5:$B$227,"NIVEL 1",'DATOS MODELO'!$C$5:$C$227,"Columnas") -> 34.692085 | F30: 0 | G30: =E30*(1+F30) -> 34.692085 | H30: curador | U30: =G30*PARÁMETROS!$B$16/3.785 -> 1.8331353
A31: NIVEL 1 | B31: Curado | C31: Falso piso | D31: m² | E31: =SUMIFS('DATOS MODELO'!$I$5:$I$227,'DATOS MODELO'!$B$5:$B$227,"NIVEL 1",'DATOS MODELO'!$C$5:$C$227,"Falso piso") -> 87.320832 | F31: 0 | G31: =E31*(1+F31) -> 87.320832 | H31: curador | U31: =G31*PARÁMETROS!$B$16/3.785 -> 4.6140466
A32: TOTAL NIVEL 1 | I32: =SUM(I26:I31) -> 122.97681 | J32: =SUM(J26:J31) -> 7.422731 | K32: =SUM(K26:K31) -> 7.56182 | L32: =SUM(L26:L31) -> 2.5775498 | M32: =SUM(M26:M31) -> 0 | N32: =SUM(N26:N31) -> 38.564959 | O32: =SUM(O26:O31) -> 26.019063 | P32: =SUM(P26:P31) -> 7.2853378 | ... W32: =SUM(W26:W31) -> 6.12
B33: Subtotal Concreto | D33: m³ | G33: =SUMIFS(G26:G31,B26:B31,"Concreto") -> 13.908898
B34: Subtotal Encofrado | D34: m² | G34: =SUMIFS(G26:G31,B26:B31,"Encofrado") -> 34.692085
B35: Subtotal Acero | D35: kg | G35: =SUMIFS(G26:G31,B26:B31,"Acero") -> 1285.4986
B36: Subtotal Curado | D36: m² | G36: =SUMIFS(G26:G31,B26:B31,"Curado") -> 122.01292
A38: NIVEL 2
A39: Nivel | B39: Partida | C39: Elemento | D39: Unidad | E39: Cantidad neta | F39: Desperdicio | G39: Cantidad total | H39: f'c / tipo | I39: Cemento (bls) | J39: Arena gruesa (m³) | K39: Piedra 1/2" (m³) | L39: Agua (m³) | M39: Casetón EPS (und) | N39: Alambre N°16 (kg) | O39: Madera tornillo (p²) | P39: Triplay (m²) | Q39: Clavos 3" (kg) | R39: Alambre N°8 (kg) | S39: Puntales (und) | T39: Desmoldante (gal) | U39: Curador (gal) | V39: Dados (und) | W39: Discos de corte (und) | X39: Nota
A40: NIVEL 2 | B40: Concreto | C40: Columnas | D40: m³ | E40: =SUMIFS('DATOS MODELO'!$F$5:$F$227,'DATOS MODELO'!$B$5:$B$227,"NIVEL 2",'DATOS MODELO'!$C$5:$C$227,"Columnas") -> 8.9459893 | F40: =PARÁMETROS!$B$8 -> 0.05 | G40: =E40*(1+F40) -> 9.3932888 | H40: =INDEX(PARÁMETROS!$B$37:$B$45,MATCH(C40,PARÁMETROS!$A$37:$A$45,0)) -> 210 | I40: =G40*INDEX(PARÁMETROS!$B$49:$B$54,MATCH(H40,PARÁMETROS!$A$49:$A$54,0)) -> 91.3967 | J40: =G40*INDEX(PARÁMETROS!$C$49:$C$54,MATCH(H40,PARÁMETROS!$A$49:$A$54,0)) -> 4.8845102 | K40: =G40*INDEX(PARÁMETROS!$D$49:$D$54,MATCH(H40,PARÁMETROS!$A$49:$A$54,0)) -> 4.9784431 | L40: =G40*INDEX(PARÁMETROS!$E$49:$E$54,MATCH(H40,PARÁMETROS!$A$49:$A$54,0))/1000 -> 1.7471517
A41: NIVEL 2 | B41: Concreto | C41: Vigas | D41: m³ | E41: =SUMIFS('DATOS MODELO'!$F$5:$F$227,'DATOS MODELO'!$B$5:$B$227,"NIVEL 2",'DATOS MODELO'!$C$5:$C$227,"Vigas") -> 6.1853209 | F41: =PARÁMETROS!$B$8 -> 0.05 | G41: =E41*(1+F41) -> 6.494587 | H41: =INDEX(PARÁMETROS!$B$37:$B$45,MATCH(C41,PARÁMETROS!$A$37:$A$45,0)) -> 210 | I41: =G41*INDEX(PARÁMETROS!$B$49:$B$54,MATCH(H41,PARÁMETROS!$A$49:$A$54,0)) -> 63.192331 | J41: =G41*INDEX(PARÁMETROS!$C$49:$C$54,MATCH(H41,PARÁMETROS!$A$49:$A$54,0)) -> 3.3771852 | K41: =G41*INDEX(PARÁMETROS!$D$49:$D$54,MATCH(H41,PARÁMETROS!$A$49:$A$54,0)) -> 3.4421311 | L41: =G41*INDEX(PARÁMETROS!$E$49:$E$54,MATCH(H41,PARÁMETROS!$A$49:$A$54,0))/1000 -> 1.2079932 | X41: Peralte bajo la losa (modelo con uniones)
A42: NIVEL 2 | B42: Concreto | C42: Losa aligerada | D42: m³ | E42: =SUMIFS('DATOS MODELO'!$L$5:$L$227,'DATOS MODELO'!$B$5:$B$227,"NIVEL 2",'DATOS MODELO'!$C$5:$C$227,"Losa aligerada")*PARÁMETROS!$B$32+(SUMIFS('DATOS MODELO'!$K$5:$K$227,'DATOS MODELO'!$B$5:$B$227,"NIVEL 2",'DATOS MODELO'!$C$5:$C$227,"Losa aligerada")-SUMIFS('DATOS MODELO'!$L$5:$L$227,'DATOS MODELO'!$B$5:$B$227,"NIVEL 2",'DATOS MODELO'!$C$5:$C$227,"Losa aligerada"))*PARÁMETROS!$B$26 -> 10.65635 | F42: =PARÁMETROS!$B$8 -> 0.05 | G42: =E42*(1+F42) -> 11.189167 | H42: =INDEX(PARÁMETROS!$B$37:$B$45,MATCH(C42,PARÁMETROS!$A$37:$A$45,0)) -> 210 | I42: =G42*INDEX(PARÁMETROS!$B$49:$B$54,MATCH(H42,PARÁMETROS!$A$49:$A$54,0)) -> 108.8706 | J42: =G42*INDEX(PARÁMETROS!$C$49:$C$54,MATCH(H42,PARÁMETROS!$A$49:$A$54,0)) -> 5.8183671 | K42: =G42*INDEX(PARÁMETROS!$D$49:$D$54,MATCH(H42,PARÁMETROS!$A$49:$A$54,0)) -> 5.9302588 | L42: =G42*INDEX(PARÁMETROS!$E$49:$E$54,MATCH(H42,PARÁMETROS!$A$49:$A$54,0))/1000 -> 2.0811852 | X42: Aligerado x concreto/m² + zonas macizas (sobre vigas y columnas, vigas chatas) x h
A43: NIVEL 2 | B43: Concreto | C43: Escalera | D43: m³ | E43: =SUMIFS('DATOS MODELO'!$F$5:$F$227,'DATOS MODELO'!$B$5:$B$227,"NIVEL 2",'DATOS MODELO'!$C$5:$C$227,"Escalera") -> 2.4227145 | F43: =PARÁMETROS!$B$8 -> 0.05 | G43: =E43*(1+F43) -> 2.5438503 | H43: =INDEX(PARÁMETROS!$B$37:$B$45,MATCH(C43,PARÁMETROS!$A$37:$A$45,0)) -> 210 | I43: =G43*INDEX(PARÁMETROS!$B$49:$B$54,MATCH(H43,PARÁMETROS!$A$49:$A$54,0)) -> 24.751663 | J43: =G43*INDEX(PARÁMETROS!$C$49:$C$54,MATCH(H43,PARÁMETROS!$A$49:$A$54,0)) -> 1.3228021 | K43: =G43*INDEX(PARÁMETROS!$D$49:$D$54,MATCH(H43,PARÁMETROS!$A$49:$A$54,0)) -> 1.3482406 | L43: =G43*INDEX(PARÁMETROS!$E$49:$E$54,MATCH(H43,PARÁMETROS!$A$49:$A$54,0))/1000 -> 0.47315615 | X43: Tramo que llega a este nivel
A44: NIVEL 2 | B44: Aligerante | C44: Losa aligerada | D44: und | E44: =SUMIFS('DATOS MODELO'!$L$5:$L$227,'DATOS MODELO'!$B$5:$B$227,"NIVEL 2",'DATOS MODELO'!$C$5:$C$227,"Losa aligerada")*PARÁMETROS!$B$33 -> 144.74167 | F44: =PARÁMETROS!$B$9 -> 0.03 | G44: =E44*(1+F44) -> 149.08392 | H44: EPS | M44: =G44 -> 149.08392 | X44: Casetones = área aligerada x und/m²
A45: NIVEL 2 | B45: Encofrado | C45: Columnas | D45: m² | E45: =SUMIFS('DATOS MODELO'!$G$5:$G$227,'DATOS MODELO'!$B$5:$B$227,"NIVEL 2",'DATOS MODELO'!$C$5:$C$227,"Columnas") -> 79.685264 | F45: 0 | G45: =E45*(1+F45) -> 79.685264 | H45: Columnas | O45: =G45*INDEX(PARÁMETROS!$B$58:$B$66,MATCH(H45,PARÁMETROS!$A$58:$A$66,0))/PARÁMETROS!$B$10 -> 59.763948 | P45: =G45*INDEX(PARÁMETROS!$C$58:$C$66,MATCH(H45,PARÁMETROS!$A$58:$A$66,0))/PARÁMETROS!$B$11 -> 16.733905 | Q45: =G45*INDEX(PARÁMETROS!$D$58:$D$66,MATCH(H45,PARÁMETROS!$A$58:$A$66,0)) -> 11.95279 | R45: =G45*INDEX(PARÁMETROS!$E$58:$E$66,MATCH(H45,PARÁMETROS!$A$58:$A$66,0)) -> 19.921316 | S45: =G45*INDEX(PARÁMETROS!$F$58:$F$66,MATCH(H45,PARÁMETROS!$A$58:$A$66,0))/PARÁMETROS!$B$12 -> 0 | T45: =G45*PARÁMETROS!$B$17/3.785 -> 1.6842328 | V45: =G45*INDEX(PARÁMETROS!$G$58:$G$66,MATCH(H45,PARÁMETROS!$A$58:$A$66,0)) -> 159.37053
A46: NIVEL 2 | B46: Encofrado | C46: Vigas | D46: m² | E46: =SUMIFS('DATOS MODELO'!$G$5:$G$227,'DATOS MODELO'!$B$5:$B$227,"NIVEL 2",'DATOS MODELO'!$C$5:$C$227,"Vigas") -> 40.748317 | F46: 0 | G46: =E46*(1+F46) -> 40.748317 | H46: Vigas costados | O46: =G46*INDEX(PARÁMETROS!$B$58:$B$66,MATCH(H46,PARÁMETROS!$A$58:$A$66,0))/PARÁMETROS!$B$10 -> 30.561238 | P46: =G46*INDEX(PARÁMETROS!$C$58:$C$66,MATCH(H46,PARÁMETROS!$A$58:$A$66,0))/PARÁMETROS!$B$11 -> 8.5571465 | Q46: =G46*INDEX(PARÁMETROS!$D$58:$D$66,MATCH(H46,PARÁMETROS!$A$58:$A$66,0)) -> 7.334697 | R46: =G46*INDEX(PARÁMETROS!$E$58:$E$66,MATCH(H46,PARÁMETROS!$A$58:$A$66,0)) -> 10.187079 | S46: =G46*INDEX(PARÁMETROS!$F$58:$F$66,MATCH(H46,PARÁMETROS!$A$58:$A$66,0))/PARÁMETROS!$B$12 -> 0 | T46: =G46*PARÁMETROS!$B$17/3.785 -> 0.86125901 | V46: =G46*INDEX(PARÁMETROS!$G$58:$G$66,MATCH(H46,PARÁMETROS!$A$58:$A$66,0)) -> 81.496634
A47: NIVEL 2 | B47: Encofrado | C47: Vigas | D47: m² | E47: =SUMIFS('DATOS MODELO'!$H$5:$H$227,'DATOS MODELO'!$B$5:$B$227,"NIVEL 2",'DATOS MODELO'!$C$5:$C$227,"Vigas") -> 18.096728 | F47: 0 | G47: =E47*(1+F47) -> 18.096728 | H47: Vigas fondo | O47: =G47*INDEX(PARÁMETROS!$B$58:$B$66,MATCH(H47,PARÁMETROS!$A$58:$A$66,0))/PARÁMETROS!$B$10 -> 18.096728 | P47: =G47*INDEX(PARÁMETROS!$C$58:$C$66,MATCH(H47,PARÁMETROS!$A$58:$A$66,0))/PARÁMETROS!$B$11 -> 3.8003129 | Q47: =G47*INDEX(PARÁMETROS!$D$58:$D$66,MATCH(H47,PARÁMETROS!$A$58:$A$66,0)) -> 3.2574111 | R47: =G47*INDEX(PARÁMETROS!$E$58:$E$66,MATCH(H47,PARÁMETROS!$A$58:$A$66,0)) -> 4.5241821 | S47: =G47*INDEX(PARÁMETROS!$F$58:$F$66,MATCH(H47,PARÁMETROS!$A$58:$A$66,0))/PARÁMETROS!$B$12 -> 7.9173186 | T47: =G47*PARÁMETROS!$B$17/3.785 -> 0.38249359 | V47: =G47*INDEX(PARÁMETROS!$G$58:$G$66,MATCH(H47,PARÁMETROS!$A$58:$A$66,0)) -> 72.386913
A48: NIVEL 2 | B48: Encofrado | C48: Losa aligerada | D48: m² | E48: =SUMIFS('DATOS MODELO'!$H$5:$H$227,'DATOS MODELO'!$B$5:$B$227,"NIVEL 2",'DATOS MODELO'!$C$5:$C$227,"Losa aligerada") -> 74.524034 | F48: 0 | G48: =E48*(1+F48) -> 74.524034 | H48: Losa fondo | O48: =G48*INDEX(PARÁMETROS!$B$58:$B$66,MATCH(H48,PARÁMETROS!$A$58:$A$66,0))/PARÁMETROS!$B$10 -> 46.577521 | P48: =G48*INDEX(PARÁMETROS!$C$58:$C$66,MATCH(H48,PARÁMETROS!$A$58:$A$66,0))/PARÁMETROS!$B$11 -> 15.650047 | Q48: =G48*INDEX(PARÁMETROS!$D$58:$D$66,MATCH(H48,PARÁMETROS!$A$58:$A$66,0)) -> 8.942884 | R48: =G48*INDEX(PARÁMETROS!$E$58:$E$66,MATCH(H48,PARÁMETROS!$A$58:$A$66,0)) -> 11.178605 | S48: =G48*INDEX(PARÁMETROS!$F$58:$F$66,MATCH(H48,PARÁMETROS!$A$58:$A$66,0))/PARÁMETROS!$B$12 -> 9.3155042 | T48: =G48*PARÁMETROS!$B$17/3.785 -> 1.5751447 | V48: =G48*INDEX(PARÁMETROS!$G$58:$G$66,MATCH(H48,PARÁMETROS!$A$58:$A$66,0)) -> 186.31008 | X48: Fondo libre (sin la huella de vigas y columnas)
A49: NIVEL 2 | B49: Encofrado | C49: Losa aligerada | D49: m² | E49: =SUMIFS('DATOS MODELO'!$G$5:$G$227,'DATOS MODELO'!$B$5:$B$227,"NIVEL 2",'DATOS MODELO'!$C$5:$C$227,"Losa aligerada") -> 6.9200284 | F49: 0 | G49: =E49*(1+F49) -> 6.9200284 | H49: Losa bordes | O49: =G49*INDEX(PARÁMETROS!$B$58:$B$66,MATCH(H49,PARÁMETROS!$A$58:$A$66,0))/PARÁMETROS!$B$10 -> 5.1900213 | P49: =G49*INDEX(PARÁMETROS!$C$58:$C$66,MATCH(H49,PARÁMETROS!$A$58:$A$66,0))/PARÁMETROS!$B$11 -> 0 | Q49: =G49*INDEX(PARÁMETROS!$D$58:$D$66,MATCH(H49,PARÁMETROS!$A$58:$A$66,0)) -> 1.0380043 | R49: =G49*INDEX(PARÁMETROS!$E$58:$E$66,MATCH(H49,PARÁMETROS!$A$58:$A$66,0)) -> 1.3840057 | S49: =G49*INDEX(PARÁMETROS!$F$58:$F$66,MATCH(H49,PARÁMETROS!$A$58:$A$66,0))/PARÁMETROS!$B$12 -> 0 | T49: =G49*PARÁMETROS!$B$17/3.785 -> 0.14626216 | V49: =G49*INDEX(PARÁMETROS!$G$58:$G$66,MATCH(H49,PARÁMETROS!$A$58:$A$66,0)) -> 0
A50: NIVEL 2 | B50: Encofrado | C50: Escalera | D50: m² | E50: =SUMIFS('DATOS MODELO'!$H$5:$H$227,'DATOS MODELO'!$B$5:$B$227,"NIVEL 2",'DATOS MODELO'!$C$5:$C$227,"Escalera") -> 10.12752 | F50: 0 | G50: =E50*(1+F50) -> 10.12752 | H50: Escalera fondo | O50: =G50*INDEX(PARÁMETROS!$B$58:$B$66,MATCH(H50,PARÁMETROS!$A$58:$A$66,0))/PARÁMETROS!$B$10 -> 10.12752 | P50: =G50*INDEX(PARÁMETROS!$C$58:$C$66,MATCH(H50,PARÁMETROS!$A$58:$A$66,0))/PARÁMETROS!$B$11 -> 2.1267792 | Q50: =G50*INDEX(PARÁMETROS!$D$58:$D$66,MATCH(H50,PARÁMETROS!$A$58:$A$66,0)) -> 2.025504 | R50: =G50*INDEX(PARÁMETROS!$E$58:$E$66,MATCH(H50,PARÁMETROS!$A$58:$A$66,0)) -> 2.025504 | S50: =G50*INDEX(PARÁMETROS!$F$58:$F$66,MATCH(H50,PARÁMETROS!$A$58:$A$66,0))/PARÁMETROS!$B$12 -> 1.519128 | T50: =G50*PARÁMETROS!$B$17/3.785 -> 0.21405591 | V50: =G50*INDEX(PARÁMETROS!$G$58:$G$66,MATCH(H50,PARÁMETROS!$A$58:$A$66,0)) -> 25.3188
A51: NIVEL 2 | B51: Encofrado | C51: Escalera | D51: m² | E51: =SUMIFS('DATOS MODELO'!$G$5:$G$227,'DATOS MODELO'!$B$5:$B$227,"NIVEL 2",'DATOS MODELO'!$C$5:$C$227,"Escalera") -> 7.2532154 | F51: 0 | G51: =E51*(1+F51) -> 7.2532154 | H51: Escalera costados | O51: =G51*INDEX(PARÁMETROS!$B$58:$B$66,MATCH(H51,PARÁMETROS!$A$58:$A$66,0))/PARÁMETROS!$B$10 -> 6.3465634 | P51: =G51*INDEX(PARÁMETROS!$C$58:$C$66,MATCH(H51,PARÁMETROS!$A$58:$A$66,0))/PARÁMETROS!$B$11 -> 0 | Q51: =G51*INDEX(PARÁMETROS!$D$58:$D$66,MATCH(H51,PARÁMETROS!$A$58:$A$66,0)) -> 1.4506431 | R51: =G51*INDEX(PARÁMETROS!$E$58:$E$66,MATCH(H51,PARÁMETROS!$A$58:$A$66,0)) -> 1.4506431 | S51: =G51*INDEX(PARÁMETROS!$F$58:$F$66,MATCH(H51,PARÁMETROS!$A$58:$A$66,0))/PARÁMETROS!$B$12 -> 0 | T51: =G51*PARÁMETROS!$B$17/3.785 -> 0.15330442 | V51: =G51*INDEX(PARÁMETROS!$G$58:$G$66,MATCH(H51,PARÁMETROS!$A$58:$A$66,0)) -> 0 | X51: Costados y contrapasos
A52: NIVEL 2 | B52: Acero | C52: Columnas | D52: kg | E52: =SUMIFS('DATOS MODELO'!$E$232:$E$279,'DATOS MODELO'!$A$232:$A$279,"NIVEL 2",'DATOS MODELO'!$B$232:$B$279,"Columnas",'DATOS MODELO'!$C$232:$C$279,"1/4")*INDEX(PARÁMETROS!$B$93:$B$97,MATCH("1/4",PARÁMETROS!$A$93:$A$97,0))+SUMIFS('DATOS MODELO'!$E$232:$E$279,'DATOS MODELO'!$A$232:$A$279,"NIVEL 2",'DATOS MODELO'!$B$232:$B$279,"Columnas",'DATOS MODELO'!$C$232:$C$279,"3/8")*INDEX(PARÁMETROS!$B$93:$B$97,MATCH("3/8",PARÁMETROS!$A$93:$A$97,0))+SUMIFS('DATOS MODELO'!$E$232:$E$279,'DATOS MODELO'!$A$232:$A$279,"NIVEL 2",'DATOS MODELO'!$B$232:$B$279,"Columnas",'DATOS MODELO'!$C$232:$C$279,"1/2")*INDEX(PARÁMETROS!$B$93:$B$97,MATCH("1/2",PARÁMETROS!$A$93:$A$97,0))+SUMIFS('DATOS MODELO'!$E$232:$E$279,'DATOS MODELO'!$A$232:$A$279,"NIVEL 2",'DATOS MODELO'!$B$232:$B$279,"Columnas",'DATOS MODELO'!$C$232:$C$279,"5/8")*INDEX(PARÁMETROS!$B$93:$B$97,MATCH("5/8",PARÁMETROS!$A$93:$A$97,0))+SUMIFS('DATOS MODELO'!$E$232:$E$279,'DATOS MODELO'!$A$232:$A$279,"NIVEL 2",'DATOS MODELO'!$B$232:$B$279,"Columnas",'DATOS MODELO'!$C$232:$C$279,"3/4")*INDEX(PARÁMETROS!$B$93:$B$97,MATCH("3/4",PARÁMETROS!$A$93:$A$97,0)) -> 1657.1508 | F52: 0 | G52: =E52*(1+F52) -> 1657.1508 | H52: fy 4200 | N52: =G52*PARÁMETROS!$B$13 -> 49.714525 | W52: =SUMIFS('DATOS MODELO'!$D$232:$D$279,'DATOS MODELO'!$A$232:$A$279,"NIVEL 2",'DATOS MODELO'!$B$232:$B$279,"Columnas")/PARÁMETROS!$B$15 -> 11.12 | X52: Desperdicio de corte: ver ACERO – DESPIECE (varillas de 9 m)
A53: NIVEL 2 | B53: Acero | C53: Vigas | D53: kg | E53: =SUMIFS('DATOS MODELO'!$E$232:$E$279,'DATOS MODELO'!$A$232:$A$279,"NIVEL 2",'DATOS MODELO'!$B$232:$B$279,"Vigas",'DATOS MODELO'!$C$232:$C$279,"1/4")*INDEX(PARÁMETROS!$B$93:$B$97,MATCH("1/4",PARÁMETROS!$A$93:$A$97,0))+SUMIFS('DATOS MODELO'!$E$232:$E$279,'DATOS MODELO'!$A$232:$A$279,"NIVEL 2",'DATOS MODELO'!$B$232:$B$279,"Vigas",'DATOS MODELO'!$C$232:$C$279,"3/8")*INDEX(PARÁMETROS!$B$93:$B$97,MATCH("3/8",PARÁMETROS!$A$93:$A$97,0))+SUMIFS('DATOS MODELO'!$E$232:$E$279,'DATOS MODELO'!$A$232:$A$279,"NIVEL 2",'DATOS MODELO'!$B$232:$B$279,"Vigas",'DATOS MODELO'!$C$232:$C$279,"1/2")*INDEX(PARÁMETROS!$B$93:$B$97,MATCH("1/2",PARÁMETROS!$A$93:$A$97,0))+SUMIFS('DATOS MODELO'!$E$232:$E$279,'DATOS MODELO'!$A$232:$A$279,"NIVEL 2",'DATOS MODELO'!$B$232:$B$279,"Vigas",'DATOS MODELO'!$C$232:$C$279,"5/8")*INDEX(PARÁMETROS!$B$93:$B$97,MATCH("5/8",PARÁMETROS!$A$93:$A$97,0))+SUMIFS('DATOS MODELO'!$E$232:$E$279,'DATOS MODELO'!$A$232:$A$279,"NIVEL 2",'DATOS MODELO'!$B$232:$B$279,"Vigas",'DATOS MODELO'!$C$232:$C$279,"3/4")*INDEX(PARÁMETROS!$B$93:$B$97,MATCH("3/4",PARÁMETROS!$A$93:$A$97,0)) -> 2014.4839 | F53: 0 | G53: =E53*(1+F53) -> 2014.4839 | H53: fy 4200 | N53: =G53*PARÁMETROS!$B$13 -> 60.434517 | W53: =SUMIFS('DATOS MODELO'!$D$232:$D$279,'DATOS MODELO'!$A$232:$A$279,"NIVEL 2",'DATOS MODELO'!$B$232:$B$279,"Vigas")/PARÁMETROS!$B$15 -> 3.9466667 | X53: Desperdicio de corte: ver ACERO – DESPIECE (varillas de 9 m)
A54: NIVEL 2 | B54: Acero | C54: Losa aligerada | D54: kg | E54: =SUMIFS('DATOS MODELO'!$E$232:$E$279,'DATOS MODELO'!$A$232:$A$279,"NIVEL 2",'DATOS MODELO'!$B$232:$B$279,"Losa aligerada",'DATOS MODELO'!$C$232:$C$279,"1/4")*INDEX(PARÁMETROS!$B$93:$B$97,MATCH("1/4",PARÁMETROS!$A$93:$A$97,0))+SUMIFS('DATOS MODELO'!$E$232:$E$279,'DATOS MODELO'!$A$232:$A$279,"NIVEL 2",'DATOS MODELO'!$B$232:$B$279,"Losa aligerada",'DATOS MODELO'!$C$232:$C$279,"3/8")*INDEX(PARÁMETROS!$B$93:$B$97,MATCH("3/8",PARÁMETROS!$A$93:$A$97,0))+SUMIFS('DATOS MODELO'!$E$232:$E$279,'DATOS MODELO'!$A$232:$A$279,"NIVEL 2",'DATOS MODELO'!$B$232:$B$279,"Losa aligerada",'DATOS MODELO'!$C$232:$C$279,"1/2")*INDEX(PARÁMETROS!$B$93:$B$97,MATCH("1/2",PARÁMETROS!$A$93:$A$97,0))+SUMIFS('DATOS MODELO'!$E$232:$E$279,'DATOS MODELO'!$A$232:$A$279,"NIVEL 2",'DATOS MODELO'!$B$232:$B$279,"Losa aligerada",'DATOS MODELO'!$C$232:$C$279,"5/8")*INDEX(PARÁMETROS!$B$93:$B$97,MATCH("5/8",PARÁMETROS!$A$93:$A$97,0))+SUMIFS('DATOS MODELO'!$E$232:$E$279,'DATOS MODELO'!$A$232:$A$279,"NIVEL 2",'DATOS MODELO'!$B$232:$B$279,"Losa aligerada",'DATOS MODELO'!$C$232:$C$279,"3/4")*INDEX(PARÁMETROS!$B$93:$B$97,MATCH("3/4",PARÁMETROS!$A$93:$A$97,0)) -> 559.61797 | F54: 0 | G54: =E54*(1+F54) -> 559.61797 | H54: fy 4200 | N54: =G54*PARÁMETROS!$B$13 -> 16.788539 | W54: =SUMIFS('DATOS MODELO'!$D$232:$D$279,'DATOS MODELO'!$A$232:$A$279,"NIVEL 2",'DATOS MODELO'!$B$232:$B$279,"Losa aligerada")/PARÁMETROS!$B$15 -> 2.4666667 | X54: Desperdicio de corte: ver ACERO – DESPIECE (varillas de 9 m)
A55: NIVEL 2 | B55: Acero | C55: Escalera | D55: kg | E55: =SUMIFS('DATOS MODELO'!$E$232:$E$279,'DATOS MODELO'!$A$232:$A$279,"NIVEL 2",'DATOS MODELO'!$B$232:$B$279,"Escalera",'DATOS MODELO'!$C$232:$C$279,"1/4")*INDEX(PARÁMETROS!$B$93:$B$97,MATCH("1/4",PARÁMETROS!$A$93:$A$97,0))+SUMIFS('DATOS MODELO'!$E$232:$E$279,'DATOS MODELO'!$A$232:$A$279,"NIVEL 2",'DATOS MODELO'!$B$232:$B$279,"Escalera",'DATOS MODELO'!$C$232:$C$279,"3/8")*INDEX(PARÁMETROS!$B$93:$B$97,MATCH("3/8",PARÁMETROS!$A$93:$A$97,0))+SUMIFS('DATOS MODELO'!$E$232:$E$279,'DATOS MODELO'!$A$232:$A$279,"NIVEL 2",'DATOS MODELO'!$B$232:$B$279,"Escalera",'DATOS MODELO'!$C$232:$C$279,"1/2")*INDEX(PARÁMETROS!$B$93:$B$97,MATCH("1/2",PARÁMETROS!$A$93:$A$97,0))+SUMIFS('DATOS MODELO'!$E$232:$E$279,'DATOS MODELO'!$A$232:$A$279,"NIVEL 2",'DATOS MODELO'!$B$232:$B$279,"Escalera",'DATOS MODELO'!$C$232:$C$279,"5/8")*INDEX(PARÁMETROS!$B$93:$B$97,MATCH("5/8",PARÁMETROS!$A$93:$A$97,0))+SUMIFS('DATOS MODELO'!$E$232:$E$279,'DATOS MODELO'!$A$232:$A$279,"NIVEL 2",'DATOS MODELO'!$B$232:$B$279,"Escalera",'DATOS MODELO'!$C$232:$C$279,"3/4")*INDEX(PARÁMETROS!$B$93:$B$97,MATCH("3/4",PARÁMETROS!$A$93:$A$97,0)) -> 88.82552 | F55: 0 | G55: =E55*(1+F55) -> 88.82552 | H55: fy 4200 | N55: =G55*PARÁMETROS!$B$13 -> 2.6647656 | W55: =SUMIFS('DATOS MODELO'!$D$232:$D$279,'DATOS MODELO'!$A$232:$A$279,"NIVEL 2",'DATOS MODELO'!$B$232:$B$279,"Escalera")/PARÁMETROS!$B$15 -> 0.53333333 | X55: Desperdicio de corte: ver ACERO – DESPIECE (varillas de 9 m)
A56: NIVEL 2 | B56: Curado | C56: Columnas | D56: m² | E56: =SUMIFS('DATOS MODELO'!$J$5:$J$227,'DATOS MODELO'!$B$5:$B$227,"NIVEL 2",'DATOS MODELO'!$C$5:$C$227,"Columnas") -> 79.685264 | F56: 0 | G56: =E56*(1+F56) -> 79.685264 | H56: curador | U56: =G56*PARÁMETROS!$B$16/3.785 -> 4.210582
A57: NIVEL 2 | B57: Curado | C57: Vigas | D57: m² | E57: =SUMIFS('DATOS MODELO'!$J$5:$J$227,'DATOS MODELO'!$B$5:$B$227,"NIVEL 2",'DATOS MODELO'!$C$5:$C$227,"Vigas") -> 40.748317 | F57: 0 | G57: =E57*(1+F57) -> 40.748317 | H57: curador | U57: =G57*PARÁMETROS!$B$16/3.785 -> 2.1531475 | X57: Costados al desencofrar
A58: NIVEL 2 | B58: Curado | C58: Losa aligerada | D58: m² | E58: =SUMIFS('DATOS MODELO'!$I$5:$I$227,'DATOS MODELO'!$B$5:$B$227,"NIVEL 2",'DATOS MODELO'!$C$5:$C$227,"Losa aligerada")+SUMIFS('DATOS MODELO'!$J$5:$J$227,'DATOS MODELO'!$B$5:$B$227,"NIVEL 2",'DATOS MODELO'!$C$5:$C$227,"Losa aligerada") -> 96.95274 | F58: 0 | G58: =E58*(1+F58) -> 96.95274 | H58: curador | U58: =G58*PARÁMETROS!$B$16/3.785 -> 5.1229982
A59: NIVEL 2 | B59: Curado | C59: Escalera | D59: m² | E59: =SUMIFS('DATOS MODELO'!$I$5:$I$227,'DATOS MODELO'!$B$5:$B$227,"NIVEL 2",'DATOS MODELO'!$C$5:$C$227,"Escalera")+SUMIFS('DATOS MODELO'!$J$5:$J$227,'DATOS MODELO'!$B$5:$B$227,"NIVEL 2",'DATOS MODELO'!$C$5:$C$227,"Escalera") -> 18.844109 | F59: 0 | G59: =E59*(1+F59) -> 18.844109 | H59: curador | U59: =G59*PARÁMETROS!$B$16/3.785 -> 0.9957257
A60: TOTAL NIVEL 2 | I60: =SUM(I40:I59) -> 288.21129 | J60: =SUM(J40:J59) -> 15.402865 | K60: =SUM(K40:K59) -> 15.699074 | L60: =SUM(L40:L59) -> 5.5094862 | M60: =SUM(M40:M59) -> 149.08392 | N60: =SUM(N40:N59) -> 129.60235 | O60: =SUM(O40:O59) -> 176.66354 | P60: =SUM(P40:P59) -> 46.868191 | ... W60: =SUM(W40:W59) -> 18.066667
B61: Subtotal Concreto | D61: m³ | G61: =SUMIFS(G40:G59,B40:B59,"Concreto") -> 29.620894
B62: Subtotal Encofrado | D62: m² | G62: =SUMIFS(G40:G59,B40:B59,"Encofrado") -> 237.35511
B63: Subtotal Acero | D63: kg | G63: =SUMIFS(G40:G59,B40:B59,"Acero") -> 4320.0782
B64: Subtotal Curado | D64: m² | G64: =SUMIFS(G40:G59,B40:B59,"Curado") -> 236.23043
A66: NIVEL 3
A67: Nivel | B67: Partida | C67: Elemento | D67: Unidad | E67: Cantidad neta | F67: Desperdicio | G67: Cantidad total | H67: f'c / tipo | I67: Cemento (bls) | J67: Arena gruesa (m³) | K67: Piedra 1/2" (m³) | L67: Agua (m³) | M67: Casetón EPS (und) | N67: Alambre N°16 (kg) | O67: Madera tornillo (p²) | P67: Triplay (m²) | Q67: Clavos 3" (kg) | R67: Alambre N°8 (kg) | S67: Puntales (und) | T67: Desmoldante (gal) | U67: Curador (gal) | V67: Dados (und) | W67: Discos de corte (und) | X67: Nota
A68: NIVEL 3 | B68: Concreto | C68: Columnas | D68: m³ | E68: =SUMIFS('DATOS MODELO'!$F$5:$F$227,'DATOS MODELO'!$B$5:$B$227,"NIVEL 3",'DATOS MODELO'!$C$5:$C$227,"Columnas") -> 7.2179914 | F68: =PARÁMETROS!$B$8 -> 0.05 | G68: =E68*(1+F68) -> 7.5788909 | H68: =INDEX(PARÁMETROS!$B$37:$B$45,MATCH(C68,PARÁMETROS!$A$37:$A$45,0)) -> 210 | I68: =G68*INDEX(PARÁMETROS!$B$49:$B$54,MATCH(H68,PARÁMETROS!$A$49:$A$54,0)) -> 73.742609 | J68: =G68*INDEX(PARÁMETROS!$C$49:$C$54,MATCH(H68,PARÁMETROS!$A$49:$A$54,0)) -> 3.9410233 | K68: =G68*INDEX(PARÁMETROS!$D$49:$D$54,MATCH(H68,PARÁMETROS!$A$49:$A$54,0)) -> 4.0168122 | L68: =G68*INDEX(PARÁMETROS!$E$49:$E$54,MATCH(H68,PARÁMETROS!$A$49:$A$54,0))/1000 -> 1.4096737
A69: NIVEL 3 | B69: Concreto | C69: Vigas | D69: m³ | E69: =SUMIFS('DATOS MODELO'!$F$5:$F$227,'DATOS MODELO'!$B$5:$B$227,"NIVEL 3",'DATOS MODELO'!$C$5:$C$227,"Vigas") -> 6.185317 | F69: =PARÁMETROS!$B$8 -> 0.05 | G69: =E69*(1+F69) -> 6.4945828 | H69: =INDEX(PARÁMETROS!$B$37:$B$45,MATCH(C69,PARÁMETROS!$A$37:$A$45,0)) -> 210 | I69: =G69*INDEX(PARÁMETROS!$B$49:$B$54,MATCH(H69,PARÁMETROS!$A$49:$A$54,0)) -> 63.192291 | J69: =G69*INDEX(PARÁMETROS!$C$49:$C$54,MATCH(H69,PARÁMETROS!$A$49:$A$54,0)) -> 3.3771831 | K69: =G69*INDEX(PARÁMETROS!$D$49:$D$54,MATCH(H69,PARÁMETROS!$A$49:$A$54,0)) -> 3.4421289 | L69: =G69*INDEX(PARÁMETROS!$E$49:$E$54,MATCH(H69,PARÁMETROS!$A$49:$A$54,0))/1000 -> 1.2079924 | X69: Peralte bajo la losa (modelo con uniones)
A70: NIVEL 3 | B70: Concreto | C70: Losa aligerada | D70: m³ | E70: =SUMIFS('DATOS MODELO'!$L$5:$L$227,'DATOS MODELO'!$B$5:$B$227,"NIVEL 3",'DATOS MODELO'!$C$5:$C$227,"Losa aligerada")*PARÁMETROS!$B$32+(SUMIFS('DATOS MODELO'!$K$5:$K$227,'DATOS MODELO'!$B$5:$B$227,"NIVEL 3",'DATOS MODELO'!$C$5:$C$227,"Losa aligerada")-SUMIFS('DATOS MODELO'!$L$5:$L$227,'DATOS MODELO'!$B$5:$B$227,"NIVEL 3",'DATOS MODELO'!$C$5:$C$227,"Losa aligerada"))*PARÁMETROS!$B$26 -> 10.65635 | F70: =PARÁMETROS!$B$8 -> 0.05 | G70: =E70*(1+F70) -> 11.189167 | H70: =INDEX(PARÁMETROS!$B$37:$B$45,MATCH(C70,PARÁMETROS!$A$37:$A$45,0)) -> 210 | I70: =G70*INDEX(PARÁMETROS!$B$49:$B$54,MATCH(H70,PARÁMETROS!$A$49:$A$54,0)) -> 108.8706 | J70: =G70*INDEX(PARÁMETROS!$C$49:$C$54,MATCH(H70,PARÁMETROS!$A$49:$A$54,0)) -> 5.8183671 | K70: =G70*INDEX(PARÁMETROS!$D$49:$D$54,MATCH(H70,PARÁMETROS!$A$49:$A$54,0)) -> 5.9302588 | L70: =G70*INDEX(PARÁMETROS!$E$49:$E$54,MATCH(H70,PARÁMETROS!$A$49:$A$54,0))/1000 -> 2.0811852 | X70: Aligerado x concreto/m² + zonas macizas (sobre vigas y columnas, vigas chatas) x h
A71: NIVEL 3 | B71: Concreto | C71: Escalera | D71: m³ | E71: =SUMIFS('DATOS MODELO'!$F$5:$F$227,'DATOS MODELO'!$B$5:$B$227,"NIVEL 3",'DATOS MODELO'!$C$5:$C$227,"Escalera") -> 2.0776282 | F71: =PARÁMETROS!$B$8 -> 0.05 | G71: =E71*(1+F71) -> 2.1815096 | H71: =INDEX(PARÁMETROS!$B$37:$B$45,MATCH(C71,PARÁMETROS!$A$37:$A$45,0)) -> 210 | I71: =G71*INDEX(PARÁMETROS!$B$49:$B$54,MATCH(H71,PARÁMETROS!$A$49:$A$54,0)) -> 21.226088 | J71: =G71*INDEX(PARÁMETROS!$C$49:$C$54,MATCH(H71,PARÁMETROS!$A$49:$A$54,0)) -> 1.134385 | K71: =G71*INDEX(PARÁMETROS!$D$49:$D$54,MATCH(H71,PARÁMETROS!$A$49:$A$54,0)) -> 1.1562001 | L71: =G71*INDEX(PARÁMETROS!$E$49:$E$54,MATCH(H71,PARÁMETROS!$A$49:$A$54,0))/1000 -> 0.40576078 | X71: Tramo que llega a este nivel
A72: NIVEL 3 | B72: Aligerante | C72: Losa aligerada | D72: und | E72: =SUMIFS('DATOS MODELO'!$L$5:$L$227,'DATOS MODELO'!$B$5:$B$227,"NIVEL 3",'DATOS MODELO'!$C$5:$C$227,"Losa aligerada")*PARÁMETROS!$B$33 -> 144.74167 | F72: =PARÁMETROS!$B$9 -> 0.03 | G72: =E72*(1+F72) -> 149.08392 | H72: EPS | M72: =G72 -> 149.08392 | X72: Casetones = área aligerada x und/m²
A73: NIVEL 3 | B73: Encofrado | C73: Columnas | D73: m² | E73: =SUMIFS('DATOS MODELO'!$G$5:$G$227,'DATOS MODELO'!$B$5:$B$227,"NIVEL 3",'DATOS MODELO'!$C$5:$C$227,"Columnas") -> 63.291537 | F73: 0 | G73: =E73*(1+F73) -> 63.291537 | H73: Columnas | O73: =G73*INDEX(PARÁMETROS!$B$58:$B$66,MATCH(H73,PARÁMETROS!$A$58:$A$66,0))/PARÁMETROS!$B$10 -> 47.468653 | P73: =G73*INDEX(PARÁMETROS!$C$58:$C$66,MATCH(H73,PARÁMETROS!$A$58:$A$66,0))/PARÁMETROS!$B$11 -> 13.291223 | Q73: =G73*INDEX(PARÁMETROS!$D$58:$D$66,MATCH(H73,PARÁMETROS!$A$58:$A$66,0)) -> 9.4937306 | R73: =G73*INDEX(PARÁMETROS!$E$58:$E$66,MATCH(H73,PARÁMETROS!$A$58:$A$66,0)) -> 15.822884 | S73: =G73*INDEX(PARÁMETROS!$F$58:$F$66,MATCH(H73,PARÁMETROS!$A$58:$A$66,0))/PARÁMETROS!$B$12 -> 0 | T73: =G73*PARÁMETROS!$B$17/3.785 -> 1.3377339 | V73: =G73*INDEX(PARÁMETROS!$G$58:$G$66,MATCH(H73,PARÁMETROS!$A$58:$A$66,0)) -> 126.58307
A74: NIVEL 3 | B74: Encofrado | C74: Vigas | D74: m² | E74: =SUMIFS('DATOS MODELO'!$G$5:$G$227,'DATOS MODELO'!$B$5:$B$227,"NIVEL 3",'DATOS MODELO'!$C$5:$C$227,"Vigas") -> 40.75534 | F74: 0 | G74: =E74*(1+F74) -> 40.75534 | H74: Vigas costados | O74: =G74*INDEX(PARÁMETROS!$B$58:$B$66,MATCH(H74,PARÁMETROS!$A$58:$A$66,0))/PARÁMETROS!$B$10 -> 30.566505 | P74: =G74*INDEX(PARÁMETROS!$C$58:$C$66,MATCH(H74,PARÁMETROS!$A$58:$A$66,0))/PARÁMETROS!$B$11 -> 8.5586214 | Q74: =G74*INDEX(PARÁMETROS!$D$58:$D$66,MATCH(H74,PARÁMETROS!$A$58:$A$66,0)) -> 7.3359612 | R74: =G74*INDEX(PARÁMETROS!$E$58:$E$66,MATCH(H74,PARÁMETROS!$A$58:$A$66,0)) -> 10.188835 | S74: =G74*INDEX(PARÁMETROS!$F$58:$F$66,MATCH(H74,PARÁMETROS!$A$58:$A$66,0))/PARÁMETROS!$B$12 -> 0 | T74: =G74*PARÁMETROS!$B$17/3.785 -> 0.86140745 | V74: =G74*INDEX(PARÁMETROS!$G$58:$G$66,MATCH(H74,PARÁMETROS!$A$58:$A$66,0)) -> 81.51068
A75: NIVEL 3 | B75: Encofrado | C75: Vigas | D75: m² | E75: =SUMIFS('DATOS MODELO'!$H$5:$H$227,'DATOS MODELO'!$B$5:$B$227,"NIVEL 3",'DATOS MODELO'!$C$5:$C$227,"Vigas") -> 18.096728 | F75: 0 | G75: =E75*(1+F75) -> 18.096728 | H75: Vigas fondo | O75: =G75*INDEX(PARÁMETROS!$B$58:$B$66,MATCH(H75,PARÁMETROS!$A$58:$A$66,0))/PARÁMETROS!$B$10 -> 18.096728 | P75: =G75*INDEX(PARÁMETROS!$C$58:$C$66,MATCH(H75,PARÁMETROS!$A$58:$A$66,0))/PARÁMETROS!$B$11 -> 3.8003129 | Q75: =G75*INDEX(PARÁMETROS!$D$58:$D$66,MATCH(H75,PARÁMETROS!$A$58:$A$66,0)) -> 3.2574111 | R75: =G75*INDEX(PARÁMETROS!$E$58:$E$66,MATCH(H75,PARÁMETROS!$A$58:$A$66,0)) -> 4.5241821 | S75: =G75*INDEX(PARÁMETROS!$F$58:$F$66,MATCH(H75,PARÁMETROS!$A$58:$A$66,0))/PARÁMETROS!$B$12 -> 7.9173186 | T75: =G75*PARÁMETROS!$B$17/3.785 -> 0.38249359 | V75: =G75*INDEX(PARÁMETROS!$G$58:$G$66,MATCH(H75,PARÁMETROS!$A$58:$A$66,0)) -> 72.386913
A76: NIVEL 3 | B76: Encofrado | C76: Losa aligerada | D76: m² | E76: =SUMIFS('DATOS MODELO'!$H$5:$H$227,'DATOS MODELO'!$B$5:$B$227,"NIVEL 3",'DATOS MODELO'!$C$5:$C$227,"Losa aligerada") -> 74.524034 | F76: 0 | G76: =E76*(1+F76) -> 74.524034 | H76: Losa fondo | O76: =G76*INDEX(PARÁMETROS!$B$58:$B$66,MATCH(H76,PARÁMETROS!$A$58:$A$66,0))/PARÁMETROS!$B$10 -> 46.577521 | P76: =G76*INDEX(PARÁMETROS!$C$58:$C$66,MATCH(H76,PARÁMETROS!$A$58:$A$66,0))/PARÁMETROS!$B$11 -> 15.650047 | Q76: =G76*INDEX(PARÁMETROS!$D$58:$D$66,MATCH(H76,PARÁMETROS!$A$58:$A$66,0)) -> 8.942884 | R76: =G76*INDEX(PARÁMETROS!$E$58:$E$66,MATCH(H76,PARÁMETROS!$A$58:$A$66,0)) -> 11.178605 | S76: =G76*INDEX(PARÁMETROS!$F$58:$F$66,MATCH(H76,PARÁMETROS!$A$58:$A$66,0))/PARÁMETROS!$B$12 -> 9.3155042 | T76: =G76*PARÁMETROS!$B$17/3.785 -> 1.5751447 | V76: =G76*INDEX(PARÁMETROS!$G$58:$G$66,MATCH(H76,PARÁMETROS!$A$58:$A$66,0)) -> 186.31008 | X76: Fondo libre (sin la huella de vigas y columnas)
A77: NIVEL 3 | B77: Encofrado | C77: Losa aligerada | D77: m² | E77: =SUMIFS('DATOS MODELO'!$G$5:$G$227,'DATOS MODELO'!$B$5:$B$227,"NIVEL 3",'DATOS MODELO'!$C$5:$C$227,"Losa aligerada") -> 6.9200367 | F77: 0 | G77: =E77*(1+F77) -> 6.9200367 | H77: Losa bordes | O77: =G77*INDEX(PARÁMETROS!$B$58:$B$66,MATCH(H77,PARÁMETROS!$A$58:$A$66,0))/PARÁMETROS!$B$10 -> 5.1900275 | P77: =G77*INDEX(PARÁMETROS!$C$58:$C$66,MATCH(H77,PARÁMETROS!$A$58:$A$66,0))/PARÁMETROS!$B$11 -> 0 | Q77: =G77*INDEX(PARÁMETROS!$D$58:$D$66,MATCH(H77,PARÁMETROS!$A$58:$A$66,0)) -> 1.0380055 | R77: =G77*INDEX(PARÁMETROS!$E$58:$E$66,MATCH(H77,PARÁMETROS!$A$58:$A$66,0)) -> 1.3840073 | S77: =G77*INDEX(PARÁMETROS!$F$58:$F$66,MATCH(H77,PARÁMETROS!$A$58:$A$66,0))/PARÁMETROS!$B$12 -> 0 | T77: =G77*PARÁMETROS!$B$17/3.785 -> 0.14626233 | V77: =G77*INDEX(PARÁMETROS!$G$58:$G$66,MATCH(H77,PARÁMETROS!$A$58:$A$66,0)) -> 0
A78: NIVEL 3 | B78: Encofrado | C78: Escalera | D78: m² | E78: =SUMIFS('DATOS MODELO'!$H$5:$H$227,'DATOS MODELO'!$B$5:$B$227,"NIVEL 3",'DATOS MODELO'!$C$5:$C$227,"Escalera") -> 9.0323961 | F78: 0 | G78: =E78*(1+F78) -> 9.0323961 | H78: Escalera fondo | O78: =G78*INDEX(PARÁMETROS!$B$58:$B$66,MATCH(H78,PARÁMETROS!$A$58:$A$66,0))/PARÁMETROS!$B$10 -> 9.0323961 | P78: =G78*INDEX(PARÁMETROS!$C$58:$C$66,MATCH(H78,PARÁMETROS!$A$58:$A$66,0))/PARÁMETROS!$B$11 -> 1.8968032 | Q78: =G78*INDEX(PARÁMETROS!$D$58:$D$66,MATCH(H78,PARÁMETROS!$A$58:$A$66,0)) -> 1.8064792 | R78: =G78*INDEX(PARÁMETROS!$E$58:$E$66,MATCH(H78,PARÁMETROS!$A$58:$A$66,0)) -> 1.8064792 | S78: =G78*INDEX(PARÁMETROS!$F$58:$F$66,MATCH(H78,PARÁMETROS!$A$58:$A$66,0))/PARÁMETROS!$B$12 -> 1.3548594 | T78: =G78*PARÁMETROS!$B$17/3.785 -> 0.1909093 | V78: =G78*INDEX(PARÁMETROS!$G$58:$G$66,MATCH(H78,PARÁMETROS!$A$58:$A$66,0)) -> 22.58099
A79: NIVEL 3 | B79: Encofrado | C79: Escalera | D79: m² | E79: =SUMIFS('DATOS MODELO'!$G$5:$G$227,'DATOS MODELO'!$B$5:$B$227,"NIVEL 3",'DATOS MODELO'!$C$5:$C$227,"Escalera") -> 6.1907953 | F79: 0 | G79: =E79*(1+F79) -> 6.1907953 | H79: Escalera costados | O79: =G79*INDEX(PARÁMETROS!$B$58:$B$66,MATCH(H79,PARÁMETROS!$A$58:$A$66,0))/PARÁMETROS!$B$10 -> 5.4169459 | P79: =G79*INDEX(PARÁMETROS!$C$58:$C$66,MATCH(H79,PARÁMETROS!$A$58:$A$66,0))/PARÁMETROS!$B$11 -> 0 | Q79: =G79*INDEX(PARÁMETROS!$D$58:$D$66,MATCH(H79,PARÁMETROS!$A$58:$A$66,0)) -> 1.2381591 | R79: =G79*INDEX(PARÁMETROS!$E$58:$E$66,MATCH(H79,PARÁMETROS!$A$58:$A$66,0)) -> 1.2381591 | S79: =G79*INDEX(PARÁMETROS!$F$58:$F$66,MATCH(H79,PARÁMETROS!$A$58:$A$66,0))/PARÁMETROS!$B$12 -> 0 | T79: =G79*PARÁMETROS!$B$17/3.785 -> 0.13084904 | V79: =G79*INDEX(PARÁMETROS!$G$58:$G$66,MATCH(H79,PARÁMETROS!$A$58:$A$66,0)) -> 0 | X79: Costados y contrapasos
A80: NIVEL 3 | B80: Acero | C80: Columnas | D80: kg | E80: =SUMIFS('DATOS MODELO'!$E$232:$E$279,'DATOS MODELO'!$A$232:$A$279,"NIVEL 3",'DATOS MODELO'!$B$232:$B$279,"Columnas",'DATOS MODELO'!$C$232:$C$279,"1/4")*INDEX(PARÁMETROS!$B$93:$B$97,MATCH("1/4",PARÁMETROS!$A$93:$A$97,0))+SUMIFS('DATOS MODELO'!$E$232:$E$279,'DATOS MODELO'!$A$232:$A$279,"NIVEL 3",'DATOS MODELO'!$B$232:$B$279,"Columnas",'DATOS MODELO'!$C$232:$C$279,"3/8")*INDEX(PARÁMETROS!$B$93:$B$97,MATCH("3/8",PARÁMETROS!$A$93:$A$97,0))+SUMIFS('DATOS MODELO'!$E$232:$E$279,'DATOS MODELO'!$A$232:$A$279,"NIVEL 3",'DATOS MODELO'!$B$232:$B$279,"Columnas",'DATOS MODELO'!$C$232:$C$279,"1/2")*INDEX(PARÁMETROS!$B$93:$B$97,MATCH("1/2",PARÁMETROS!$A$93:$A$97,0))+SUMIFS('DATOS MODELO'!$E$232:$E$279,'DATOS MODELO'!$A$232:$A$279,"NIVEL 3",'DATOS MODELO'!$B$232:$B$279,"Columnas",'DATOS MODELO'!$C$232:$C$279,"5/8")*INDEX(PARÁMETROS!$B$93:$B$97,MATCH("5/8",PARÁMETROS!$A$93:$A$97,0))+SUMIFS('DATOS MODELO'!$E$232:$E$279,'DATOS MODELO'!$A$232:$A$279,"NIVEL 3",'DATOS MODELO'!$B$232:$B$279,"Columnas",'DATOS MODELO'!$C$232:$C$279,"3/4")*INDEX(PARÁMETROS!$B$93:$B$97,MATCH("3/4",PARÁMETROS!$A$93:$A$97,0)) -> 1442.0032 | F80: 0 | G80: =E80*(1+F80) -> 1442.0032 | H80: fy 4200 | N80: =G80*PARÁMETROS!$B$13 -> 43.260095 | W80: =SUMIFS('DATOS MODELO'!$D$232:$D$279,'DATOS MODELO'!$A$232:$A$279,"NIVEL 3",'DATOS MODELO'!$B$232:$B$279,"Columnas")/PARÁMETROS!$B$15 -> 9.32 | X80: Desperdicio de corte: ver ACERO – DESPIECE (varillas de 9 m)
A81: NIVEL 3 | B81: Acero | C81: Vigas | D81: kg | E81: =SUMIFS('DATOS MODELO'!$E$232:$E$279,'DATOS MODELO'!$A$232:$A$279,"NIVEL 3",'DATOS MODELO'!$B$232:$B$279,"Vigas",'DATOS MODELO'!$C$232:$C$279,"1/4")*INDEX(PARÁMETROS!$B$93:$B$97,MATCH("1/4",PARÁMETROS!$A$93:$A$97,0))+SUMIFS('DATOS MODELO'!$E$232:$E$279,'DATOS MODELO'!$A$232:$A$279,"NIVEL 3",'DATOS MODELO'!$B$232:$B$279,"Vigas",'DATOS MODELO'!$C$232:$C$279,"3/8")*INDEX(PARÁMETROS!$B$93:$B$97,MATCH("3/8",PARÁMETROS!$A$93:$A$97,0))+SUMIFS('DATOS MODELO'!$E$232:$E$279,'DATOS MODELO'!$A$232:$A$279,"NIVEL 3",'DATOS MODELO'!$B$232:$B$279,"Vigas",'DATOS MODELO'!$C$232:$C$279,"1/2")*INDEX(PARÁMETROS!$B$93:$B$97,MATCH("1/2",PARÁMETROS!$A$93:$A$97,0))+SUMIFS('DATOS MODELO'!$E$232:$E$279,'DATOS MODELO'!$A$232:$A$279,"NIVEL 3",'DATOS MODELO'!$B$232:$B$279,"Vigas",'DATOS MODELO'!$C$232:$C$279,"5/8")*INDEX(PARÁMETROS!$B$93:$B$97,MATCH("5/8",PARÁMETROS!$A$93:$A$97,0))+SUMIFS('DATOS MODELO'!$E$232:$E$279,'DATOS MODELO'!$A$232:$A$279,"NIVEL 3",'DATOS MODELO'!$B$232:$B$279,"Vigas",'DATOS MODELO'!$C$232:$C$279,"3/4")*INDEX(PARÁMETROS!$B$93:$B$97,MATCH("3/4",PARÁMETROS!$A$93:$A$97,0)) -> 1655.6211 | F81: 0 | G81: =E81*(1+F81) -> 1655.6211 | H81: fy 4200 | N81: =G81*PARÁMETROS!$B$13 -> 49.668634 | W81: =SUMIFS('DATOS MODELO'!$D$232:$D$279,'DATOS MODELO'!$A$232:$A$279,"NIVEL 3",'DATOS MODELO'!$B$232:$B$279,"Vigas")/PARÁMETROS!$B$15 -> 3.76 | X81: Desperdicio de corte: ver ACERO – DESPIECE (varillas de 9 m)
A82: NIVEL 3 | B82: Acero | C82: Losa aligerada | D82: kg | E82: =SUMIFS('DATOS MODELO'!$E$232:$E$279,'DATOS MODELO'!$A$232:$A$279,"NIVEL 3",'DATOS MODELO'!$B$232:$B$279,"Losa aligerada",'DATOS MODELO'!$C$232:$C$279,"1/4")*INDEX(PARÁMETROS!$B$93:$B$97,MATCH("1/4",PARÁMETROS!$A$93:$A$97,0))+SUMIFS('DATOS MODELO'!$E$232:$E$279,'DATOS MODELO'!$A$232:$A$279,"NIVEL 3",'DATOS MODELO'!$B$232:$B$279,"Losa aligerada",'DATOS MODELO'!$C$232:$C$279,"3/8")*INDEX(PARÁMETROS!$B$93:$B$97,MATCH("3/8",PARÁMETROS!$A$93:$A$97,0))+SUMIFS('DATOS MODELO'!$E$232:$E$279,'DATOS MODELO'!$A$232:$A$279,"NIVEL 3",'DATOS MODELO'!$B$232:$B$279,"Losa aligerada",'DATOS MODELO'!$C$232:$C$279,"1/2")*INDEX(PARÁMETROS!$B$93:$B$97,MATCH("1/2",PARÁMETROS!$A$93:$A$97,0))+SUMIFS('DATOS MODELO'!$E$232:$E$279,'DATOS MODELO'!$A$232:$A$279,"NIVEL 3",'DATOS MODELO'!$B$232:$B$279,"Losa aligerada",'DATOS MODELO'!$C$232:$C$279,"5/8")*INDEX(PARÁMETROS!$B$93:$B$97,MATCH("5/8",PARÁMETROS!$A$93:$A$97,0))+SUMIFS('DATOS MODELO'!$E$232:$E$279,'DATOS MODELO'!$A$232:$A$279,"NIVEL 3",'DATOS MODELO'!$B$232:$B$279,"Losa aligerada",'DATOS MODELO'!$C$232:$C$279,"3/4")*INDEX(PARÁMETROS!$B$93:$B$97,MATCH("3/4",PARÁMETROS!$A$93:$A$97,0)) -> 558.66704 | F82: 0 | G82: =E82*(1+F82) -> 558.66704 | H82: fy 4200 | N82: =G82*PARÁMETROS!$B$13 -> 16.760011 | W82: =SUMIFS('DATOS MODELO'!$D$232:$D$279,'DATOS MODELO'!$A$232:$A$279,"NIVEL 3",'DATOS MODELO'!$B$232:$B$279,"Losa aligerada")/PARÁMETROS!$B$15 -> 2.4666667 | X82: Desperdicio de corte: ver ACERO – DESPIECE (varillas de 9 m)
A83: NIVEL 3 | B83: Acero | C83: Escalera | D83: kg | E83: =SUMIFS('DATOS MODELO'!$E$232:$E$279,'DATOS MODELO'!$A$232:$A$279,"NIVEL 3",'DATOS MODELO'!$B$232:$B$279,"Escalera",'DATOS MODELO'!$C$232:$C$279,"1/4")*INDEX(PARÁMETROS!$B$93:$B$97,MATCH("1/4",PARÁMETROS!$A$93:$A$97,0))+SUMIFS('DATOS MODELO'!$E$232:$E$279,'DATOS MODELO'!$A$232:$A$279,"NIVEL 3",'DATOS MODELO'!$B$232:$B$279,"Escalera",'DATOS MODELO'!$C$232:$C$279,"3/8")*INDEX(PARÁMETROS!$B$93:$B$97,MATCH("3/8",PARÁMETROS!$A$93:$A$97,0))+SUMIFS('DATOS MODELO'!$E$232:$E$279,'DATOS MODELO'!$A$232:$A$279,"NIVEL 3",'DATOS MODELO'!$B$232:$B$279,"Escalera",'DATOS MODELO'!$C$232:$C$279,"1/2")*INDEX(PARÁMETROS!$B$93:$B$97,MATCH("1/2",PARÁMETROS!$A$93:$A$97,0))+SUMIFS('DATOS MODELO'!$E$232:$E$279,'DATOS MODELO'!$A$232:$A$279,"NIVEL 3",'DATOS MODELO'!$B$232:$B$279,"Escalera",'DATOS MODELO'!$C$232:$C$279,"5/8")*INDEX(PARÁMETROS!$B$93:$B$97,MATCH("5/8",PARÁMETROS!$A$93:$A$97,0))+SUMIFS('DATOS MODELO'!$E$232:$E$279,'DATOS MODELO'!$A$232:$A$279,"NIVEL 3",'DATOS MODELO'!$B$232:$B$279,"Escalera",'DATOS MODELO'!$C$232:$C$279,"3/4")*INDEX(PARÁMETROS!$B$93:$B$97,MATCH("3/4",PARÁMETROS!$A$93:$A$97,0)) -> 81.56344 | F83: 0 | G83: =E83*(1+F83) -> 81.56344 | H83: fy 4200 | N83: =G83*PARÁMETROS!$B$13 -> 2.4469032 | W83: =SUMIFS('DATOS MODELO'!$D$232:$D$279,'DATOS MODELO'!$A$232:$A$279,"NIVEL 3",'DATOS MODELO'!$B$232:$B$279,"Escalera")/PARÁMETROS!$B$15 -> 0.50666667 | X83: Desperdicio de corte: ver ACERO – DESPIECE (varillas de 9 m)
A84: NIVEL 3 | B84: Curado | C84: Columnas | D84: m² | E84: =SUMIFS('DATOS MODELO'!$J$5:$J$227,'DATOS MODELO'!$B$5:$B$227,"NIVEL 3",'DATOS MODELO'!$C$5:$C$227,"Columnas") -> 63.291537 | F84: 0 | G84: =E84*(1+F84) -> 63.291537 | H84: curador | U84: =G84*PARÁMETROS!$B$16/3.785 -> 3.3443349
A85: NIVEL 3 | B85: Curado | C85: Vigas | D85: m² | E85: =SUMIFS('DATOS MODELO'!$J$5:$J$227,'DATOS MODELO'!$B$5:$B$227,"NIVEL 3",'DATOS MODELO'!$C$5:$C$227,"Vigas") -> 40.75534 | F85: 0 | G85: =E85*(1+F85) -> 40.75534 | H85: curador | U85: =G85*PARÁMETROS!$B$16/3.785 -> 2.1535186 | X85: Costados al desencofrar
A86: NIVEL 3 | B86: Curado | C86: Losa aligerada | D86: m² | E86: =SUMIFS('DATOS MODELO'!$I$5:$I$227,'DATOS MODELO'!$B$5:$B$227,"NIVEL 3",'DATOS MODELO'!$C$5:$C$227,"Losa aligerada")+SUMIFS('DATOS MODELO'!$J$5:$J$227,'DATOS MODELO'!$B$5:$B$227,"NIVEL 3",'DATOS MODELO'!$C$5:$C$227,"Losa aligerada") -> 96.952749 | F86: 0 | G86: =E86*(1+F86) -> 96.952749 | H86: curador | U86: =G86*PARÁMETROS!$B$16/3.785 -> 5.1229986
A87: NIVEL 3 | B87: Curado | C87: Escalera | D87: m² | E87: =SUMIFS('DATOS MODELO'!$I$5:$I$227,'DATOS MODELO'!$B$5:$B$227,"NIVEL 3",'DATOS MODELO'!$C$5:$C$227,"Escalera")+SUMIFS('DATOS MODELO'!$J$5:$J$227,'DATOS MODELO'!$B$5:$B$227,"NIVEL 3",'DATOS MODELO'!$C$5:$C$227,"Escalera") -> 16.297528 | F87: 0 | G87: =E87*(1+F87) -> 16.297528 | H87: curador | U87: =G87*PARÁMETROS!$B$16/3.785 -> 0.86116395
A88: TOTAL NIVEL 3 | I88: =SUM(I68:I87) -> 267.03159 | J88: =SUM(J68:J87) -> 14.270958 | K88: =SUM(K68:K87) -> 14.5454 | L88: =SUM(L68:L87) -> 5.1046121 | M88: =SUM(M68:M87) -> 149.08392 | N88: =SUM(N68:N87) -> 112.13564 | O88: =SUM(O68:O87) -> 162.34878 | P88: =SUM(P68:P87) -> 43.197007 | ... W88: =SUM(W68:W87) -> 16.053333
B89: Subtotal Concreto | D89: m³ | G89: =SUMIFS(G68:G87,B68:B87,"Concreto") -> 27.444151
B90: Subtotal Encofrado | D90: m² | G90: =SUMIFS(G68:G87,B68:B87,"Encofrado") -> 218.81087
B91: Subtotal Acero | D91: kg | G91: =SUMIFS(G68:G87,B68:B87,"Acero") -> 3737.8548
B92: Subtotal Curado | D92: m² | G92: =SUMIFS(G68:G87,B68:B87,"Curado") -> 217.29715
A94: NIVEL 4
A95: Nivel | B95: Partida | C95: Elemento | D95: Unidad | E95: Cantidad neta | F95: Desperdicio | G95: Cantidad total | H95: f'c / tipo | I95: Cemento (bls) | J95: Arena gruesa (m³) | K95: Piedra 1/2" (m³) | L95: Agua (m³) | M95: Casetón EPS (und) | N95: Alambre N°16 (kg) | O95: Madera tornillo (p²) | P95: Triplay (m²) | Q95: Clavos 3" (kg) | R95: Alambre N°8 (kg) | S95: Puntales (und) | T95: Desmoldante (gal) | U95: Curador (gal) | V95: Dados (und) | W95: Discos de corte (und) | X95: Nota
A96: NIVEL 4 | B96: Concreto | C96: Columnas | D96: m³ | E96: =SUMIFS('DATOS MODELO'!$F$5:$F$227,'DATOS MODELO'!$B$5:$B$227,"NIVEL 4",'DATOS MODELO'!$C$5:$C$227,"Columnas") -> 7.2179899 | F96: =PARÁMETROS!$B$8 -> 0.05 | G96: =E96*(1+F96) -> 7.5788894 | H96: =INDEX(PARÁMETROS!$B$37:$B$45,MATCH(C96,PARÁMETROS!$A$37:$A$45,0)) -> 210 | I96: =G96*INDEX(PARÁMETROS!$B$49:$B$54,MATCH(H96,PARÁMETROS!$A$49:$A$54,0)) -> 73.742594 | J96: =G96*INDEX(PARÁMETROS!$C$49:$C$54,MATCH(H96,PARÁMETROS!$A$49:$A$54,0)) -> 3.9410225 | K96: =G96*INDEX(PARÁMETROS!$D$49:$D$54,MATCH(H96,PARÁMETROS!$A$49:$A$54,0)) -> 4.0168114 | L96: =G96*INDEX(PARÁMETROS!$E$49:$E$54,MATCH(H96,PARÁMETROS!$A$49:$A$54,0))/1000 -> 1.4096734
A97: NIVEL 4 | B97: Concreto | C97: Vigas | D97: m³ | E97: =SUMIFS('DATOS MODELO'!$F$5:$F$227,'DATOS MODELO'!$B$5:$B$227,"NIVEL 4",'DATOS MODELO'!$C$5:$C$227,"Vigas") -> 6.185316 | F97: =PARÁMETROS!$B$8 -> 0.05 | G97: =E97*(1+F97) -> 6.4945818 | H97: =INDEX(PARÁMETROS!$B$37:$B$45,MATCH(C97,PARÁMETROS!$A$37:$A$45,0)) -> 210 | I97: =G97*INDEX(PARÁMETROS!$B$49:$B$54,MATCH(H97,PARÁMETROS!$A$49:$A$54,0)) -> 63.192281 | J97: =G97*INDEX(PARÁMETROS!$C$49:$C$54,MATCH(H97,PARÁMETROS!$A$49:$A$54,0)) -> 3.3771825 | K97: =G97*INDEX(PARÁMETROS!$D$49:$D$54,MATCH(H97,PARÁMETROS!$A$49:$A$54,0)) -> 3.4421284 | L97: =G97*INDEX(PARÁMETROS!$E$49:$E$54,MATCH(H97,PARÁMETROS!$A$49:$A$54,0))/1000 -> 1.2079922 | X97: Peralte bajo la losa (modelo con uniones)
A98: NIVEL 4 | B98: Concreto | C98: Losa aligerada | D98: m³ | E98: =SUMIFS('DATOS MODELO'!$L$5:$L$227,'DATOS MODELO'!$B$5:$B$227,"NIVEL 4",'DATOS MODELO'!$C$5:$C$227,"Losa aligerada")*PARÁMETROS!$B$32+(SUMIFS('DATOS MODELO'!$K$5:$K$227,'DATOS MODELO'!$B$5:$B$227,"NIVEL 4",'DATOS MODELO'!$C$5:$C$227,"Losa aligerada")-SUMIFS('DATOS MODELO'!$L$5:$L$227,'DATOS MODELO'!$B$5:$B$227,"NIVEL 4",'DATOS MODELO'!$C$5:$C$227,"Losa aligerada"))*PARÁMETROS!$B$26 -> 10.65635 | F98: =PARÁMETROS!$B$8 -> 0.05 | G98: =E98*(1+F98) -> 11.189167 | H98: =INDEX(PARÁMETROS!$B$37:$B$45,MATCH(C98,PARÁMETROS!$A$37:$A$45,0)) -> 210 | I98: =G98*INDEX(PARÁMETROS!$B$49:$B$54,MATCH(H98,PARÁMETROS!$A$49:$A$54,0)) -> 108.8706 | J98: =G98*INDEX(PARÁMETROS!$C$49:$C$54,MATCH(H98,PARÁMETROS!$A$49:$A$54,0)) -> 5.8183671 | K98: =G98*INDEX(PARÁMETROS!$D$49:$D$54,MATCH(H98,PARÁMETROS!$A$49:$A$54,0)) -> 5.9302588 | L98: =G98*INDEX(PARÁMETROS!$E$49:$E$54,MATCH(H98,PARÁMETROS!$A$49:$A$54,0))/1000 -> 2.0811852 | X98: Aligerado x concreto/m² + zonas macizas (sobre vigas y columnas, vigas chatas) x h
A99: NIVEL 4 | B99: Concreto | C99: Escalera | D99: m³ | E99: =SUMIFS('DATOS MODELO'!$F$5:$F$227,'DATOS MODELO'!$B$5:$B$227,"NIVEL 4",'DATOS MODELO'!$C$5:$C$227,"Escalera") -> 2.0776266 | F99: =PARÁMETROS!$B$8 -> 0.05 | G99: =E99*(1+F99) -> 2.1815079 | H99: =INDEX(PARÁMETROS!$B$37:$B$45,MATCH(C99,PARÁMETROS!$A$37:$A$45,0)) -> 210 | I99: =G99*INDEX(PARÁMETROS!$B$49:$B$54,MATCH(H99,PARÁMETROS!$A$49:$A$54,0)) -> 21.226072 | J99: =G99*INDEX(PARÁMETROS!$C$49:$C$54,MATCH(H99,PARÁMETROS!$A$49:$A$54,0)) -> 1.1343841 | K99: =G99*INDEX(PARÁMETROS!$D$49:$D$54,MATCH(H99,PARÁMETROS!$A$49:$A$54,0)) -> 1.1561992 | L99: =G99*INDEX(PARÁMETROS!$E$49:$E$54,MATCH(H99,PARÁMETROS!$A$49:$A$54,0))/1000 -> 0.40576047 | X99: Tramo que llega a este nivel
A100: NIVEL 4 | B100: Aligerante | C100: Losa aligerada | D100: und | E100: =SUMIFS('DATOS MODELO'!$L$5:$L$227,'DATOS MODELO'!$B$5:$B$227,"NIVEL 4",'DATOS MODELO'!$C$5:$C$227,"Losa aligerada")*PARÁMETROS!$B$33 -> 144.74167 | F100: =PARÁMETROS!$B$9 -> 0.03 | G100: =E100*(1+F100) -> 149.08392 | H100: EPS | M100: =G100 -> 149.08392 | X100: Casetones = área aligerada x und/m²
A101: NIVEL 4 | B101: Encofrado | C101: Columnas | D101: m² | E101: =SUMIFS('DATOS MODELO'!$G$5:$G$227,'DATOS MODELO'!$B$5:$B$227,"NIVEL 4",'DATOS MODELO'!$C$5:$C$227,"Columnas") -> 63.291525 | F101: 0 | G101: =E101*(1+F101) -> 63.291525 | H101: Columnas | O101: =G101*INDEX(PARÁMETROS!$B$58:$B$66,MATCH(H101,PARÁMETROS!$A$58:$A$66,0))/PARÁMETROS!$B$10 -> 47.468644 | P101: =G101*INDEX(PARÁMETROS!$C$58:$C$66,MATCH(H101,PARÁMETROS!$A$58:$A$66,0))/PARÁMETROS!$B$11 -> 13.29122 | Q101: =G101*INDEX(PARÁMETROS!$D$58:$D$66,MATCH(H101,PARÁMETROS!$A$58:$A$66,0)) -> 9.4937288 | R101: =G101*INDEX(PARÁMETROS!$E$58:$E$66,MATCH(H101,PARÁMETROS!$A$58:$A$66,0)) -> 15.822881 | S101: =G101*INDEX(PARÁMETROS!$F$58:$F$66,MATCH(H101,PARÁMETROS!$A$58:$A$66,0))/PARÁMETROS!$B$12 -> 0 | T101: =G101*PARÁMETROS!$B$17/3.785 -> 1.3377337 | V101: =G101*INDEX(PARÁMETROS!$G$58:$G$66,MATCH(H101,PARÁMETROS!$A$58:$A$66,0)) -> 126.58305
A102: NIVEL 4 | B102: Encofrado | C102: Vigas | D102: m² | E102: =SUMIFS('DATOS MODELO'!$G$5:$G$227,'DATOS MODELO'!$B$5:$B$227,"NIVEL 4",'DATOS MODELO'!$C$5:$C$227,"Vigas") -> 40.755334 | F102: 0 | G102: =E102*(1+F102) -> 40.755334 | H102: Vigas costados | O102: =G102*INDEX(PARÁMETROS!$B$58:$B$66,MATCH(H102,PARÁMETROS!$A$58:$A$66,0))/PARÁMETROS!$B$10 -> 30.566501 | P102: =G102*INDEX(PARÁMETROS!$C$58:$C$66,MATCH(H102,PARÁMETROS!$A$58:$A$66,0))/PARÁMETROS!$B$11 -> 8.5586202 | Q102: =G102*INDEX(PARÁMETROS!$D$58:$D$66,MATCH(H102,PARÁMETROS!$A$58:$A$66,0)) -> 7.3359601 | R102: =G102*INDEX(PARÁMETROS!$E$58:$E$66,MATCH(H102,PARÁMETROS!$A$58:$A$66,0)) -> 10.188834 | S102: =G102*INDEX(PARÁMETROS!$F$58:$F$66,MATCH(H102,PARÁMETROS!$A$58:$A$66,0))/PARÁMETROS!$B$12 -> 0 | T102: =G102*PARÁMETROS!$B$17/3.785 -> 0.86140733 | V102: =G102*INDEX(PARÁMETROS!$G$58:$G$66,MATCH(H102,PARÁMETROS!$A$58:$A$66,0)) -> 81.510668
A103: NIVEL 4 | B103: Encofrado | C103: Vigas | D103: m² | E103: =SUMIFS('DATOS MODELO'!$H$5:$H$227,'DATOS MODELO'!$B$5:$B$227,"NIVEL 4",'DATOS MODELO'!$C$5:$C$227,"Vigas") -> 18.096728 | F103: 0 | G103: =E103*(1+F103) -> 18.096728 | H103: Vigas fondo | O103: =G103*INDEX(PARÁMETROS!$B$58:$B$66,MATCH(H103,PARÁMETROS!$A$58:$A$66,0))/PARÁMETROS!$B$10 -> 18.096728 | P103: =G103*INDEX(PARÁMETROS!$C$58:$C$66,MATCH(H103,PARÁMETROS!$A$58:$A$66,0))/PARÁMETROS!$B$11 -> 3.8003129 | Q103: =G103*INDEX(PARÁMETROS!$D$58:$D$66,MATCH(H103,PARÁMETROS!$A$58:$A$66,0)) -> 3.2574111 | R103: =G103*INDEX(PARÁMETROS!$E$58:$E$66,MATCH(H103,PARÁMETROS!$A$58:$A$66,0)) -> 4.5241821 | S103: =G103*INDEX(PARÁMETROS!$F$58:$F$66,MATCH(H103,PARÁMETROS!$A$58:$A$66,0))/PARÁMETROS!$B$12 -> 7.9173186 | T103: =G103*PARÁMETROS!$B$17/3.785 -> 0.38249359 | V103: =G103*INDEX(PARÁMETROS!$G$58:$G$66,MATCH(H103,PARÁMETROS!$A$58:$A$66,0)) -> 72.386913
A104: NIVEL 4 | B104: Encofrado | C104: Losa aligerada | D104: m² | E104: =SUMIFS('DATOS MODELO'!$H$5:$H$227,'DATOS MODELO'!$B$5:$B$227,"NIVEL 4",'DATOS MODELO'!$C$5:$C$227,"Losa aligerada") -> 74.524034 | F104: 0 | G104: =E104*(1+F104) -> 74.524034 | H104: Losa fondo | O104: =G104*INDEX(PARÁMETROS!$B$58:$B$66,MATCH(H104,PARÁMETROS!$A$58:$A$66,0))/PARÁMETROS!$B$10 -> 46.577521 | P104: =G104*INDEX(PARÁMETROS!$C$58:$C$66,MATCH(H104,PARÁMETROS!$A$58:$A$66,0))/PARÁMETROS!$B$11 -> 15.650047 | Q104: =G104*INDEX(PARÁMETROS!$D$58:$D$66,MATCH(H104,PARÁMETROS!$A$58:$A$66,0)) -> 8.942884 | R104: =G104*INDEX(PARÁMETROS!$E$58:$E$66,MATCH(H104,PARÁMETROS!$A$58:$A$66,0)) -> 11.178605 | S104: =G104*INDEX(PARÁMETROS!$F$58:$F$66,MATCH(H104,PARÁMETROS!$A$58:$A$66,0))/PARÁMETROS!$B$12 -> 9.3155042 | T104: =G104*PARÁMETROS!$B$17/3.785 -> 1.5751447 | V104: =G104*INDEX(PARÁMETROS!$G$58:$G$66,MATCH(H104,PARÁMETROS!$A$58:$A$66,0)) -> 186.31008 | X104: Fondo libre (sin la huella de vigas y columnas)
A105: NIVEL 4 | B105: Encofrado | C105: Losa aligerada | D105: m² | E105: =SUMIFS('DATOS MODELO'!$G$5:$G$227,'DATOS MODELO'!$B$5:$B$227,"NIVEL 4",'DATOS MODELO'!$C$5:$C$227,"Losa aligerada") -> 6.9200202 | F105: 0 | G105: =E105*(1+F105) -> 6.9200202 | H105: Losa bordes | O105: =G105*INDEX(PARÁMETROS!$B$58:$B$66,MATCH(H105,PARÁMETROS!$A$58:$A$66,0))/PARÁMETROS!$B$10 -> 5.1900151 | P105: =G105*INDEX(PARÁMETROS!$C$58:$C$66,MATCH(H105,PARÁMETROS!$A$58:$A$66,0))/PARÁMETROS!$B$11 -> 0 | Q105: =G105*INDEX(PARÁMETROS!$D$58:$D$66,MATCH(H105,PARÁMETROS!$A$58:$A$66,0)) -> 1.038003 | R105: =G105*INDEX(PARÁMETROS!$E$58:$E$66,MATCH(H105,PARÁMETROS!$A$58:$A$66,0)) -> 1.384004 | S105: =G105*INDEX(PARÁMETROS!$F$58:$F$66,MATCH(H105,PARÁMETROS!$A$58:$A$66,0))/PARÁMETROS!$B$12 -> 0 | T105: =G105*PARÁMETROS!$B$17/3.785 -> 0.14626199 | V105: =G105*INDEX(PARÁMETROS!$G$58:$G$66,MATCH(H105,PARÁMETROS!$A$58:$A$66,0)) -> 0
...

Sheet ACERO – DESPIECE
A1: ACERO – DESPIECE POR DIÁMETRO Y NIVEL (varillas comerciales de 9 m)
A2: Piezas y longitudes del modelo; varillas y retazos del PLAN DE CORTE. Unidad de compra: VARILLA de 9 m.
A4: Nivel | B4: Ø | C4: N° barras (modelo) | D4: Longitud neta (m) | E4: kg netos | F4: Varillas de 9 m (und) | G4: Longitud comprada (m) | H4: Longitud cortada (m) | I4: Traslape adicional (m) | J4: Retazos (m) | K4: Retazos reutilizables ≥ 1 m (m) | L4: Desperdicio real (%) | M4: kg comprados (referencia)
A5: CIMENTACIÓN | B5: 1/4 | C5: =SUMIFS('DATOS MODELO'!$D$232:$D$279,'DATOS MODELO'!$A$232:$A$279,A5,'DATOS MODELO'!$C$232:$C$279,B5) -> 0 | D5: =SUMIFS('DATOS MODELO'!$E$232:$E$279,'DATOS MODELO'!$A$232:$A$279,A5,'DATOS MODELO'!$C$232:$C$279,B5) -> 0 | E5: =D5*INDEX(PARÁMETROS!$B$93:$B$97,MATCH(B5,PARÁMETROS!$A$93:$A$97,0)) -> 0 | F5: =COUNTIFS('PLAN DE CORTE'!$A$5:$A$2516,A5,'PLAN DE CORTE'!$B$5:$B$2516,B5) -> 0 | G5: =F5*9 -> 0 | H5: =SUMIFS('PLAN DE CORTE'!$F$5:$F$2516,'PLAN DE CORTE'!$A$5:$A$2516,A5,'PLAN DE CORTE'!$B$5:$B$2516,B5) -> 0 | I5: =H5-D5 -> 0 | J5: =G5-H5 -> 0 | K5: =SUMIFS('PLAN DE CORTE'!$H$5:$H$2516,'PLAN DE CORTE'!$A$5:$A$2516,A5,'PLAN DE CORTE'!$B$5:$B$2516,B5) -> 0 | L5: =IF(G5>0,J5/G5,0) -> 0 | M5: =G5*INDEX(PARÁMETROS!$B$93:$B$97,MATCH(B5,PARÁMETROS!$A$93:$A$97,0)) -> 0
A6: CIMENTACIÓN | B6: 3/8 | C6: =SUMIFS('DATOS MODELO'!$D$232:$D$279,'DATOS MODELO'!$A$232:$A$279,A6,'DATOS MODELO'!$C$232:$C$279,B6) -> 387 | D6: =SUMIFS('DATOS MODELO'!$E$232:$E$279,'DATOS MODELO'!$A$232:$A$279,A6,'DATOS MODELO'!$C$232:$C$279,B6) -> 433.874 | E6: =D6*INDEX(PARÁMETROS!$B$93:$B$97,MATCH(B6,PARÁMETROS!$A$93:$A$97,0)) -> 242.96944 | F6: =COUNTIFS('PLAN DE CORTE'!$A$5:$A$2516,A6,'PLAN DE CORTE'!$B$5:$B$2516,B6) -> 49 | G6: =F6*9 -> 441 | H6: =SUMIFS('PLAN DE CORTE'!$F$5:$F$2516,'PLAN DE CORTE'!$A$5:$A$2516,A6,'PLAN DE CORTE'!$B$5:$B$2516,B6) -> 433.87444 | I6: =H6-D6 -> 0.00044341097 | J6: =G6-H6 -> 7.1255566 | K6: =SUMIFS('PLAN DE CORTE'!$H$5:$H$2516,'PLAN DE CORTE'!$A$5:$A$2516,A6,'PLAN DE CORTE'!$B$5:$B$2516,B6) -> 4.5251899 | L6: =IF(G6>0,J6/G6,0) -> 0.016157725 | M6: =G6*INDEX(PARÁMETROS!$B$93:$B$97,MATCH(B6,PARÁMETROS!$A$93:$A$97,0)) -> 246.96
A7: CIMENTACIÓN | B7: 1/2 | C7: =SUMIFS('DATOS MODELO'!$D$232:$D$279,'DATOS MODELO'!$A$232:$A$279,A7,'DATOS MODELO'!$C$232:$C$279,B7) -> 32 | D7: =SUMIFS('DATOS MODELO'!$E$232:$E$279,'DATOS MODELO'!$A$232:$A$279,A7,'DATOS MODELO'!$C$232:$C$279,B7) -> 44.773 | E7: =D7*INDEX(PARÁMETROS!$B$93:$B$97,MATCH(B7,PARÁMETROS!$A$93:$A$97,0)) -> 44.504362 | F7: =COUNTIFS('PLAN DE CORTE'!$A$5:$A$2516,A7,'PLAN DE CORTE'!$B$5:$B$2516,B7) -> 6 | G7: =F7*9 -> 54 | H7: =SUMIFS('PLAN DE CORTE'!$F$5:$F$2516,'PLAN DE CORTE'!$A$5:$A$2516,A7,'PLAN DE CORTE'!$B$5:$B$2516,B7) -> 44.772601 | I7: =H7-D7 -> -0.00039860953 | J7: =G7-H7 -> 9.2273986 | K7: =SUMIFS('PLAN DE CORTE'!$H$5:$H$2516,'PLAN DE CORTE'!$A$5:$A$2516,A7,'PLAN DE CORTE'!$B$5:$B$2516,B7) -> 6.2017124 | L7: =IF(G7>0,J7/G7,0) -> 0.17087775 | M7: =G7*INDEX(PARÁMETROS!$B$93:$B$97,MATCH(B7,PARÁMETROS!$A$93:$A$97,0)) -> 53.676
A8: CIMENTACIÓN | B8: 5/8 | C8: =SUMIFS('DATOS MODELO'!$D$232:$D$279,'DATOS MODELO'!$A$232:$A$279,A8,'DATOS MODELO'!$C$232:$C$279,B8) -> 244 | D8: =SUMIFS('DATOS MODELO'!$E$232:$E$279,'DATOS MODELO'!$A$232:$A$279,A8,'DATOS MODELO'!$C$232:$C$279,B8) -> 520.289 | E8: =D8*INDEX(PARÁMETROS!$B$93:$B$97,MATCH(B8,PARÁMETROS!$A$93:$A$97,0)) -> 807.48853 | F8: =COUNTIFS('PLAN DE CORTE'!$A$5:$A$2516,A8,'PLAN DE CORTE'!$B$5:$B$2516,B8) -> 61 | G8: =F8*9 -> 549 | H8: =SUMIFS('PLAN DE CORTE'!$F$5:$F$2516,'PLAN DE CORTE'!$A$5:$A$2516,A8,'PLAN DE CORTE'!$B$5:$B$2516,B8) -> 520.28886 | I8: =H8-D8 -> -0.00014299712 | J8: =G8-H8 -> 28.711143 | K8: =SUMIFS('PLAN DE CORTE'!$H$5:$H$2516,'PLAN DE CORTE'!$A$5:$A$2516,A8,'PLAN DE CORTE'!$B$5:$B$2516,B8) -> 19.959934 | L8: =IF(G8>0,J8/G8,0) -> 0.052297164 | M8: =G8*INDEX(PARÁMETROS!$B$93:$B$97,MATCH(B8,PARÁMETROS!$A$93:$A$97,0)) -> 852.048
A9: CIMENTACIÓN | B9: 3/4 | C9: =SUMIFS('DATOS MODELO'!$D$232:$D$279,'DATOS MODELO'!$A$232:$A$279,A9,'DATOS MODELO'!$C$232:$C$279,B9) -> 90 | D9: =SUMIFS('DATOS MODELO'!$E$232:$E$279,'DATOS MODELO'!$A$232:$A$279,A9,'DATOS MODELO'!$C$232:$C$279,B9) -> 579.716 | E9: =D9*INDEX(PARÁMETROS!$B$93:$B$97,MATCH(B9,PARÁMETROS!$A$93:$A$97,0)) -> 1295.6653 | F9: =COUNTIFS('PLAN DE CORTE'!$A$5:$A$2516,A9,'PLAN DE CORTE'!$B$5:$B$2516,B9) -> 75 | G9: =F9*9 -> 675 | H9: =SUMIFS('PLAN DE CORTE'!$F$5:$F$2516,'PLAN DE CORTE'!$A$5:$A$2516,A9,'PLAN DE CORTE'!$B$5:$B$2516,B9) -> 586.61642 | I9: =H9-D9 -> 6.9004223 | J9: =G9-H9 -> 88.383578 | K9: =SUMIFS('PLAN DE CORTE'!$H$5:$H$2516,'PLAN DE CORTE'!$A$5:$A$2516,A9,'PLAN DE CORTE'!$B$5:$B$2516,B9) -> 68.125343 | L9: =IF(G9>0,J9/G9,0) -> 0.13093863 | M9: =G9*INDEX(PARÁMETROS!$B$93:$B$97,MATCH(B9,PARÁMETROS!$A$93:$A$97,0)) -> 1508.625
A10: Subtotal CIMENTACIÓN | C10: =SUM(C5:C9) -> 753 | D10: =SUM(D5:D9) -> 1578.652 | E10: =SUM(E5:E9) -> 2390.6276 | F10: =SUM(F5:F9) -> 191 | G10: =SUM(G5:G9) -> 1719 | H10: =SUM(H5:H9) -> 1585.5523 | I10: =SUM(I5:I9) -> 6.9003241 | J10: =SUM(J5:J9) -> 133.44768 | K10: =SUM(K5:K9) -> 98.81218 | L10: =IF(G10>0,J10/G10,0) -> 0.077630992 | M10: =SUM(M5:M9) -> 2661.309
A11: NIVEL 1 | B11: 1/4 | C11: =SUMIFS('DATOS MODELO'!$D$232:$D$279,'DATOS MODELO'!$A$232:$A$279,A11,'DATOS MODELO'!$C$232:$C$279,B11) -> 0 | D11: =SUMIFS('DATOS MODELO'!$E$232:$E$279,'DATOS MODELO'!$A$232:$A$279,A11,'DATOS MODELO'!$C$232:$C$279,B11) -> 0 | E11: =D11*INDEX(PARÁMETROS!$B$93:$B$97,MATCH(B11,PARÁMETROS!$A$93:$A$97,0)) -> 0 | F11: =COUNTIFS('PLAN DE CORTE'!$A$5:$A$2516,A11,'PLAN DE CORTE'!$B$5:$B$2516,B11) -> 0 | G11: =F11*9 -> 0 | H11: =SUMIFS('PLAN DE CORTE'!$F$5:$F$2516,'PLAN DE CORTE'!$A$5:$A$2516,A11,'PLAN DE CORTE'!$B$5:$B$2516,B11) -> 0 | I11: =H11-D11 -> 0 | J11: =G11-H11 -> 0 | K11: =SUMIFS('PLAN DE CORTE'!$H$5:$H$2516,'PLAN DE CORTE'!$A$5:$A$2516,A11,'PLAN DE CORTE'!$B$5:$B$2516,B11) -> 0 | L11: =IF(G11>0,J11/G11,0) -> 0 | M11: =G11*INDEX(PARÁMETROS!$B$93:$B$97,MATCH(B11,PARÁMETROS!$A$93:$A$97,0)) -> 0
A12: NIVEL 1 | B12: 3/8 | C12: =SUMIFS('DATOS MODELO'!$D$232:$D$279,'DATOS MODELO'!$A$232:$A$279,A12,'DATOS MODELO'!$C$232:$C$279,B12) -> 762 | D12: =SUMIFS('DATOS MODELO'!$E$232:$E$279,'DATOS MODELO'!$A$232:$A$279,A12,'DATOS MODELO'!$C$232:$C$279,B12) -> 735.885 | E12: =D12*INDEX(PARÁMETROS!$B$93:$B$97,MATCH(B12,PARÁMETROS!$A$93:$A$97,0)) -> 412.0956 | F12: =COUNTIFS('PLAN DE CORTE'!$A$5:$A$2516,A12,'PLAN DE CORTE'!$B$5:$B$2516,B12) -> 84 | G12: =F12*9 -> 756 | H12: =SUMIFS('PLAN DE CORTE'!$F$5:$F$2516,'PLAN DE CORTE'!$A$5:$A$2516,A12,'PLAN DE CORTE'!$B$5:$B$2516,B12) -> 735.88537 | I12: =H12-D12 -> 0.00037041882 | J12: =G12-H12 -> 20.11463 | K12: =SUMIFS('PLAN DE CORTE'!$H$5:$H$2516,'PLAN DE CORTE'!$A$5:$A$2516,A12,'PLAN DE CORTE'!$B$5:$B$2516,B12) -> 0 | L12: =IF(G12>0,J12/G12,0) -> 0.026606653 | M12: =G12*INDEX(PARÁMETROS!$B$93:$B$97,MATCH(B12,PARÁMETROS!$A$93:$A$97,0)) -> 423.36
A13: NIVEL 1 | B13: 1/2 | C13: =SUMIFS('DATOS MODELO'!$D$232:$D$279,'DATOS MODELO'!$A$232:$A$279,A13,'DATOS MODELO'!$C$232:$C$279,B13) -> 20 | D13: =SUMIFS('DATOS MODELO'!$E$232:$E$279,'DATOS MODELO'!$A$232:$A$279,A13,'DATOS MODELO'!$C$232:$C$279,B13) -> 73.554 | E13: =D13*INDEX(PARÁMETROS!$B$93:$B$97,MATCH(B13,PARÁMETROS!$A$93:$A$97,0)) -> 73.112676 | F13: =COUNTIFS('PLAN DE CORTE'!$A$5:$A$2516,A13,'PLAN DE CORTE'!$B$5:$B$2516,B13) -> 10 | G13: =F13*9 -> 90 | H13: =SUMIFS('PLAN DE CORTE'!$F$5:$F$2516,'PLAN DE CORTE'!$A$5:$A$2516,A13,'PLAN DE CORTE'!$B$5:$B$2516,B13) -> 73.553938 | I13: =H13-D13 -> -6.2065479e-05 | J13: =G13-H13 -> 16.446062 | K13: =SUMIFS('PLAN DE CORTE'!$H$5:$H$2516,'PLAN DE CORTE'!$A$5:$A$2516,A13,'PLAN DE CORTE'!$B$5:$B$2516,B13) -> 16.446062 | L13: =IF(G13>0,J13/G13,0) -> 0.18273402 | M13: =G13*INDEX(PARÁMETROS!$B$93:$B$97,MATCH(B13,PARÁMETROS!$A$93:$A$97,0)) -> 89.46
A14: NIVEL 1 | B14: 5/8 | C14: =SUMIFS('DATOS MODELO'!$D$232:$D$279,'DATOS MODELO'!$A$232:$A$279,A14,'DATOS MODELO'!$C$232:$C$279,B14) -> 136 | D14: =SUMIFS('DATOS MODELO'!$E$232:$E$279,'DATOS MODELO'!$A$232:$A$279,A14,'DATOS MODELO'!$C$232:$C$279,B14) -> 515.651 | E14: =D14*INDEX(PARÁMETROS!$B$93:$B$97,MATCH(B14,PARÁMETROS!$A$93:$A$97,0)) -> 800.29035 | F14: =COUNTIFS('PLAN DE CORTE'!$A$5:$A$2516,A14,'PLAN DE CORTE'!$B$5:$B$2516,B14) -> 68 | G14: =F14*9 -> 612 | H14: =SUMIFS('PLAN DE CORTE'!$F$5:$F$2516,'PLAN DE CORTE'!$A$5:$A$2516,A14,'PLAN DE CORTE'!$B$5:$B$2516,B14) -> 515.65132 | I14: =H14-D14 -> 0.00032244343 | J14: =G14-H14 -> 96.348678 | K14: =SUMIFS('PLAN DE CORTE'!$H$5:$H$2516,'PLAN DE CORTE'!$A$5:$A$2516,A14,'PLAN DE CORTE'!$B$5:$B$2516,B14) -> 96.348678 | L14: =IF(G14>0,J14/G14,0) -> 0.15743248 | M14: =G14*INDEX(PARÁMETROS!$B$93:$B$97,MATCH(B14,PARÁMETROS!$A$93:$A$97,0)) -> 949.824
A15: NIVEL 1 | B15: 3/4 | C15: =SUMIFS('DATOS MODELO'!$D$232:$D$279,'DATOS MODELO'!$A$232:$A$279,A15,'DATOS MODELO'!$C$232:$C$279,B15) -> 0 | D15: =SUMIFS('DATOS MODELO'!$E$232:$E$279,'DATOS MODELO'!$A$232:$A$279,A15,'DATOS MODELO'!$C$232:$C$279,B15) -> 0 | E15: =D15*INDEX(PARÁMETROS!$B$93:$B$97,MATCH(B15,PARÁMETROS!$A$93:$A$97,0)) -> 0 | F15: =COUNTIFS('PLAN DE CORTE'!$A$5:$A$2516,A15,'PLAN DE CORTE'!$B$5:$B$2516,B15) -> 0 | G15: =F15*9 -> 0 | H15: =SUMIFS('PLAN DE CORTE'!$F$5:$F$2516,'PLAN DE CORTE'!$A$5:$A$2516,A15,'PLAN DE CORTE'!$B$5:$B$2516,B15) -> 0 | I15: =H15-D15 -> 0 | J15: =G15-H15 -> 0 | K15: =SUMIFS('PLAN DE CORTE'!$H$5:$H$2516,'PLAN DE CORTE'!$A$5:$A$2516,A15,'PLAN DE CORTE'!$B$5:$B$2516,B15) -> 0 | L15: =IF(G15>0,J15/G15,0) -> 0 | M15: =G15*INDEX(PARÁMETROS!$B$93:$B$97,MATCH(B15,PARÁMETROS!$A$93:$A$97,0)) -> 0
A16: Subtotal NIVEL 1 | C16: =SUM(C11:C15) -> 918 | D16: =SUM(D11:D15) -> 1325.09 | E16: =SUM(E11:E15) -> 1285.4986 | F16: =SUM(F11:F15) -> 162 | G16: =SUM(G11:G15) -> 1458 | H16: =SUM(H11:H15) -> 1325.0906 | I16: =SUM(I11:I15) -> 0.00063079676 | J16: =SUM(J11:J15) -> 132.90937 | K16: =SUM(K11:K15) -> 112.79474 | L16: =IF(G16>0,J16/G16,0) -> 0.091158689 | M16: =SUM(M11:M15) -> 1462.644
A17: NIVEL 2 | B17: 1/4 | C17: =SUMIFS('DATOS MODELO'!$D$232:$D$279,'DATOS MODELO'!$A$232:$A$279,A17,'DATOS MODELO'!$C$232:$C$279,B17) -> 228 | D17: =SUMIFS('DATOS MODELO'!$E$232:$E$279,'DATOS MODELO'!$A$232:$A$279,A17,'DATOS MODELO'!$C$232:$C$279,B17) -> 839.284 | E17: =D17*INDEX(PARÁMETROS!$B$93:$B$97,MATCH(B17,PARÁMETROS!$A$93:$A$97,0)) -> 209.821 | F17: =COUNTIFS('PLAN DE CORTE'!$A$5:$A$2516,A17,'PLAN DE CORTE'!$B$5:$B$2516,B17) -> 110 | G17: =F17*9 -> 990 | H17: =SUMIFS('PLAN DE CORTE'!$F$5:$F$2516,'PLAN DE CORTE'!$A$5:$A$2516,A17,'PLAN DE CORTE'!$B$5:$B$2516,B17) -> 839.28397 | I17: =H17-D17 -> -2.8841426e-05 | J17: =G17-H17 -> 150.71603 | K17: =SUMIFS('PLAN DE CORTE'!$H$5:$H$2516,'PLAN DE CORTE'!$A$5:$A$2516,A17,'PLAN DE CORTE'!$B$5:$B$2516,B17) -> 128.52286 | L17: =IF(G17>0,J17/G17,0) -> 0.15223841 | M17: =G17*INDEX(PARÁMETROS!$B$93:$B$97,MATCH(B17,PARÁMETROS!$A$93:$A$97,0)) -> 247.5
A18: NIVEL 2 | B18: 3/8 | C18: =SUMIFS('DATOS MODELO'!$D$232:$D$279,'DATOS MODELO'!$A$232:$A$279,A18,'DATOS MODELO'!$C$232:$C$279,B18) -> 2130 | D18: =SUMIFS('DATOS MODELO'!$E$232:$E$279,'DATOS MODELO'!$A$232:$A$279,A18,'DATOS MODELO'!$C$232:$C$279,B18) -> 2448.966 | E18: =D18*INDEX(PARÁMETROS!$B$93:$B$97,MATCH(B18,PARÁMETROS!$A$93:$A$97,0)) -> 1371.421 | F18: =COUNTIFS('PLAN DE CORTE'!$A$5:$A$2516,A18,'PLAN DE CORTE'!$B$5:$B$2516,B18) -> 278 | G18: =F18*9 -> 2502 | H18: =SUMIFS('PLAN DE CORTE'!$F$5:$F$2516,'PLAN DE CORTE'!$A$5:$A$2516,A18,'PLAN DE CORTE'!$B$5:$B$2516,B18) -> 2448.966 | I18: =H18-D18 -> -2.2521553e-05 | J18: =G18-H18 -> 53.034023 | K18: =SUMIFS('PLAN DE CORTE'!$H$5:$H$2516,'PLAN DE CORTE'!$A$5:$A$2516,A18,'PLAN DE CORTE'!$B$5:$B$2516,B18) -> 1.9343023 | L18: =IF(G18>0,J18/G18,0) -> 0.021196652 | M18: =G18*INDEX(PARÁMETROS!$B$93:$B$97,MATCH(B18,PARÁMETROS!$A$93:$A$97,0)) -> 1401.12
A19: NIVEL 2 | B19: 1/2 | C19: =SUMIFS('DATOS MODELO'!$D$232:$D$279,'DATOS MODELO'!$A$232:$A$279,A19,'DATOS MODELO'!$C$232:$C$279,B19) -> 80 | D19: =SUMIFS('DATOS MODELO'!$E$232:$E$279,'DATOS MODELO'!$A$232:$A$279,A19,'DATOS MODELO'!$C$232:$C$279,B19) -> 317.822 | E19: =D19*INDEX(PARÁMETROS!$B$93:$B$97,MATCH(B19,PARÁMETROS!$A$93:$A$97,0)) -> 315.91507 | F19: =COUNTIFS('PLAN DE CORTE'!$A$5:$A$2516,A19,'PLAN DE CORTE'!$B$5:$B$2516,B19) -> 42 | G19: =F19*9 -> 378 | H19: =SUMIFS('PLAN DE CORTE'!$F$5:$F$2516,'PLAN DE CORTE'!$A$5:$A$2516,A19,'PLAN DE CORTE'!$B$5:$B$2516,B19) -> 317.82183 | I19: =H19-D19 -> -0.00016614448 | J19: =G19-H19 -> 60.178166 | K19: =SUMIFS('PLAN DE CORTE'!$H$5:$H$2516,'PLAN DE CORTE'!$A$5:$A$2516,A19,'PLAN DE CORTE'!$B$5:$B$2516,B19) -> 53.836223 | L19: =IF(G19>0,J19/G19,0) -> 0.1592015 | M19: =G19*INDEX(PARÁMETROS!$B$93:$B$97,MATCH(B19,PARÁMETROS!$A$93:$A$97,0)) -> 375.732
A20: NIVEL 2 | B20: 5/8 | C20: =SUMIFS('DATOS MODELO'!$D$232:$D$279,'DATOS MODELO'!$A$232:$A$279,A20,'DATOS MODELO'!$C$232:$C$279,B20) -> 142 | D20: =SUMIFS('DATOS MODELO'!$E$232:$E$279,'DATOS MODELO'!$A$232:$A$279,A20,'DATOS MODELO'!$C$232:$C$279,B20) -> 522.368 | E20: =D20*INDEX(PARÁMETROS!$B$93:$B$97,MATCH(B20,PARÁMETROS!$A$93:$A$97,0)) -> 810.71514 | F20: =COUNTIFS('PLAN DE CORTE'!$A$5:$A$2516,A20,'PLAN DE CORTE'!$B$5:$B$2516,B20) -> 71 | G20: =F20*9 -> 639 | H20: =SUMIFS('PLAN DE CORTE'!$F$5:$F$2516,'PLAN DE CORTE'!$A$5:$A$2516,A20,'PLAN DE CORTE'!$B$5:$B$2516,B20) -> 522.36794 | I20: =H20-D20 -> -6.4116981e-05 | J20: =G20-H20 -> 116.63206 | K20: =SUMIFS('PLAN DE CORTE'!$H$5:$H$2516,'PLAN DE CORTE'!$A$5:$A$2516,A20,'PLAN DE CORTE'!$B$5:$B$2516,B20) -> 115.40449 | L20: =IF(G20>0,J20/G20,0) -> 0.18252279 | M20: =G20*INDEX(PARÁMETROS!$B$93:$B$97,MATCH(B20,PARÁMETROS!$A$93:$A$97,0)) -> 991.728
A21: NIVEL 2 | B21: 3/4 | C21: =SUMIFS('DATOS MODELO'!$D$232:$D$279,'DATOS MODELO'!$A$232:$A$279,A21,'DATOS MODELO'!$C$232:$C$279,B21) -> 130 | D21: =SUMIFS('DATOS MODELO'!$E$232:$E$279,'DATOS MODELO'!$A$232:$A$279,A21,'DATOS MODELO'!$C$232:$C$279,B21) -> 721.345 | E21: =D21*INDEX(PARÁMETROS!$B$93:$B$97,MATCH(B21,PARÁMETROS!$A$93:$A$97,0)) -> 1612.2061 | F21: =COUNTIFS('PLAN DE CORTE'!$A$5:$A$2516,A21,'PLAN DE CORTE'!$B$5:$B$2516,B21) -> 90 | G21: =F21*9 -> 810 | H21: =SUMIFS('PLAN DE CORTE'!$F$5:$F$2516,'PLAN DE CORTE'!$A$5:$A$2516,A21,'PLAN DE CORTE'!$B$5:$B$2516,B21) -> 735.14467 | I21: =H21-D21 -> 13.799671 | J21: =G21-H21 -> 74.855329 | K21: =SUMIFS('PLAN DE CORTE'!$H$5:$H$2516,'PLAN DE CORTE'!$A$5:$A$2516,A21,'PLAN DE CORTE'!$B$5:$B$2516,B21) -> 57.825026 | L21: =IF(G21>0,J21/G21,0) -> 0.092413987 | M21: =G21*INDEX(PARÁMETROS!$B$93:$B$97,MATCH(B21,PARÁMETROS!$A$93:$A$97,0)) -> 1810.35
A22: Subtotal NIVEL 2 | C22: =SUM(C17:C21) -> 2710 | D22: =SUM(D17:D21) -> 4849.785 | E22: =SUM(E17:E21) -> 4320.0782 | F22: =SUM(F17:F21) -> 591 | G22: =SUM(G17:G21) -> 5319 | H22: =SUM(H17:H21) -> 4863.5844 | I22: =SUM(I17:I21) -> 13.799389 | J22: =SUM(J17:J21) -> 455.41561 | K22: =SUM(K17:K21) -> 357.5229 | L22: =IF(G22>0,J22/G22,0) -> 0.085620532 | M22: =SUM(M17:M21) -> 4826.43
A23: NIVEL 3 | B23: 1/4 | C23: =SUMIFS('DATOS MODELO'!$D$232:$D$279,'DATOS MODELO'!$A$232:$A$279,A23,'DATOS MODELO'!$C$232:$C$279,B23) -> 228 | D23: =SUMIFS('DATOS MODELO'!$E$232:$E$279,'DATOS MODELO'!$A$232:$A$279,A23,'DATOS MODELO'!$C$232:$C$279,B23) -> 839.284 | E23: =D23*INDEX(PARÁMETROS!$B$93:$B$97,MATCH(B23,PARÁMETROS!$A$93:$A$97,0)) -> 209.821 | F23: =COUNTIFS('PLAN DE CORTE'!$A$5:$A$2516,A23,'PLAN DE CORTE'!$B$5:$B$2516,B23) -> 110 | G23: =F23*9 -> 990 | H23: =SUMIFS('PLAN DE CORTE'!$F$5:$F$2516,'PLAN DE CORTE'!$A$5:$A$2516,A23,'PLAN DE CORTE'!$B$5:$B$2516,B23) -> 839.28397 | I23: =H23-D23 -> -2.8841426e-05 | J23: =G23-H23 -> 150.71603 | K23: =SUMIFS('PLAN DE CORTE'!$H$5:$H$2516,'PLAN DE CORTE'!$A$5:$A$2516,A23,'PLAN DE CORTE'!$B$5:$B$2516,B23) -> 128.52286 | L23: =IF(G23>0,J23/G23,0) -> 0.15223841 | M23: =G23*INDEX(PARÁMETROS!$B$93:$B$97,MATCH(B23,PARÁMETROS!$A$93:$A$97,0)) -> 247.5
A24: NIVEL 3 | B24: 3/8 | C24: =SUMIFS('DATOS MODELO'!$D$232:$D$279,'DATOS MODELO'!$A$232:$A$279,A24,'DATOS MODELO'!$C$232:$C$279,B24) -> 1856 | D24: =SUMIFS('DATOS MODELO'!$E$232:$E$279,'DATOS MODELO'!$A$232:$A$279,A24,'DATOS MODELO'!$C$232:$C$279,B24) -> 2173.839 | E24: =D24*INDEX(PARÁMETROS!$B$93:$B$97,MATCH(B24,PARÁMETROS!$A$93:$A$97,0)) -> 1217.3498 | F24: =COUNTIFS('PLAN DE CORTE'!$A$5:$A$2516,A24,'PLAN DE CORTE'!$B$5:$B$2516,B24) -> 247 | G24: =F24*9 -> 2223 | H24: =SUMIFS('PLAN DE CORTE'!$F$5:$F$2516,'PLAN DE CORTE'!$A$5:$A$2516,A24,'PLAN DE CORTE'!$B$5:$B$2516,B24) -> 2173.838 | I24: =H24-D24 -> -0.00097337408 | J24: =G24-H24 -> 49.161973 | K24: =SUMIFS('PLAN DE CORTE'!$H$5:$H$2516,'PLAN DE CORTE'!$A$5:$A$2516,A24,'PLAN DE CORTE'!$B$5:$B$2516,B24) -> 4.2895348 | L24: =IF(G24>0,J24/G24,0) -> 0.022115148 | M24: =G24*INDEX(PARÁMETROS!$B$93:$B$97,MATCH(B24,PARÁMETROS!$A$93:$A$97,0)) -> 1244.88
A25: NIVEL 3 | B25: 1/2 | C25: =SUMIFS('DATOS MODELO'!$D$232:$D$279,'DATOS MODELO'!$A$232:$A$279,A25,'DATOS MODELO'!$C$232:$C$279,B25) -> 80 | D25: =SUMIFS('DATOS MODELO'!$E$232:$E$279,'DATOS MODELO'!$A$232:$A$279,A25,'DATOS MODELO'!$C$232:$C$279,B25) -> 311.818 | E25: =D25*INDEX(PARÁMETROS!$B$93:$B$97,MATCH(B25,PARÁMETROS!$A$93:$A$97,0)) -> 309.94709 | F25: =COUNTIFS('PLAN DE CORTE'!$A$5:$A$2516,A25,'PLAN DE CORTE'!$B$5:$B$2516,B25) -> 39 | G25: =F25*9 -> 351 | H25: =SUMIFS('PLAN DE CORTE'!$F$5:$F$2516,'PLAN DE CORTE'!$A$5:$A$2516,A25,'PLAN DE CORTE'!$B$5:$B$2516,B25) -> 311.81762 | I25: =H25-D25 -> -0.00038119824 | J25: =G25-H25 -> 39.182381 | K25: =SUMIFS('PLAN DE CORTE'!$H$5:$H$2516,'PLAN DE CORTE'!$A$5:$A$2516,A25,'PLAN DE CORTE'!$B$5:$B$2516,B25) -> 30.063499 | L25: =IF(G25>0,J25/G25,0) -> 0.11163072 | M25: =G25*INDEX(PARÁMETROS!$B$93:$B$97,MATCH(B25,PARÁMETROS!$A$93:$A$97,0)) -> 348.894
A26: NIVEL 3 | B26: 5/8 | C26: =SUMIFS('DATOS MODELO'!$D$232:$D$279,'DATOS MODELO'!$A$232:$A$279,A26,'DATOS MODELO'!$C$232:$C$279,B26) -> 142 | D26: =SUMIFS('DATOS MODELO'!$E$232:$E$279,'DATOS MODELO'!$A$232:$A$279,A26,'DATOS MODELO'!$C$232:$C$279,B26) -> 481.568 | E26: =D26*INDEX(PARÁMETROS!$B$93:$B$97,MATCH(B26,PARÁMETROS!$A$93:$A$97,0)) -> 747.39354 | F26: =COUNTIFS('PLAN DE CORTE'!$A$5:$A$2516,A26,'PLAN DE CORTE'!$B$5:$B$2516,B26) -> 71 | G26: =F26*9 -> 639 | H26: =SUMIFS('PLAN DE CORTE'!$F$5:$F$2516,'PLAN DE CORTE'!$A$5:$A$2516,A26,'PLAN DE CORTE'!$B$5:$B$2516,B26) -> 481.56794 | I26: =H26-D26 -> -6.4116981e-05 | J26: =G26-H26 -> 157.43206 | K26: =SUMIFS('PLAN DE CORTE'!$H$5:$H$2516,'PLAN DE CORTE'!$A$5:$A$2516,A26,'PLAN DE CORTE'!$B$5:$B$2516,B26) -> 156.20449 | L26: =IF(G26>0,J26/G26,0) -> 0.24637256 | M26: =G26*INDEX(PARÁMETROS!$B$93:$B$97,MATCH(B26,PARÁMETROS!$A$93:$A$97,0)) -> 991.728
A27: NIVEL 3 | B27: 3/4 | C27: =SUMIFS('DATOS MODELO'!$D$232:$D$279,'DATOS MODELO'!$A$232:$A$279,A27,'DATOS MODELO'!$C$232:$C$279,B27) -> 102 | D27: =SUMIFS('DATOS MODELO'!$E$232:$E$279,'DATOS MODELO'!$A$232:$A$279,A27,'DATOS MODELO'!$C$232:$C$279,B27) -> 560.78 | E27: =D27*INDEX(PARÁMETROS!$B$93:$B$97,MATCH(B27,PARÁMETROS!$A$93:$A$97,0)) -> 1253.3433 | F27: =COUNTIFS('PLAN DE CORTE'!$A$5:$A$2516,A27,'PLAN DE CORTE'!$B$5:$B$2516,B27) -> 71 | G27: =F27*9 -> 639 | H27: =SUMIFS('PLAN DE CORTE'!$F$5:$F$2516,'PLAN DE CORTE'!$A$5:$A$2516,A27,'PLAN DE CORTE'!$B$5:$B$2516,B27) -> 569.97958 | I27: =H27-D27 -> 9.1995757 | J27: =G27-H27 -> 69.020424 | K27: =SUMIFS('PLAN DE CORTE'!$H$5:$H$2516,'PLAN DE CORTE'!$A$5:$A$2516,A27,'PLAN DE CORTE'!$B$5:$B$2516,B27) -> 53.789751 | L27: =IF(G27>0,J27/G27,0) -> 0.10801318 | M27: =G27*INDEX(PARÁMETROS!$B$93:$B$97,MATCH(B27,PARÁMETROS!$A$93:$A$97,0)) -> 1428.165
A28: Subtotal NIVEL 3 | C28: =SUM(C23:C27) -> 2408 | D28: =SUM(D23:D27) -> 4367.289 | E28: =SUM(E23:E27) -> 3737.8548 | F28: =SUM(F23:F27) -> 538 | G28: =SUM(G23:G27) -> 4842 | H28: =SUM(H23:H27) -> 4376.4871 | I28: =SUM(I23:I27) -> 9.1981282 | J28: =SUM(J23:J27) -> 465.51287 | K28: =SUM(K23:K27) -> 372.87013 | L28: =IF(G28>0,J28/G28,0) -> 0.096140618 | M28: =SUM(M23:M27) -> 4261.167
A29: NIVEL 4 | B29: 1/4 | C29: =SUMIFS('DATOS MODELO'!$D$232:$D$279,'DATOS MODELO'!$A$232:$A$279,A29,'DATOS MODELO'!$C$232:$C$279,B29) -> 228 | D29: =SUMIFS('DATOS MODELO'!$E$232:$E$279,'DATOS MODELO'!$A$232:$A$279,A29,'DATOS MODELO'!$C$232:$C$279,B29) -> 839.284 | E29: =D29*INDEX(PARÁMETROS!$B$93:$B$97,MATCH(B29,PARÁMETROS!$A$93:$A$97,0)) -> 209.821 | F29: =COUNTIFS('PLAN DE CORTE'!$A$5:$A$2516,A29,'PLAN DE CORTE'!$B$5:$B$2516,B29) -> 110 | G29: =F29*9 -> 990 | H29: =SUMIFS('PLAN DE CORTE'!$F$5:$F$2516,'PLAN DE CORTE'!$A$5:$A$2516,A29,'PLAN DE CORTE'!$B$5:$B$2516,B29) -> 839.28397 | I29: =H29-D29 -> -2.8841426e-05 | J29: =G29-H29 -> 150.71603 | K29: =SUMIFS('PLAN DE CORTE'!$H$5:$H$2516,'PLAN DE CORTE'!$A$5:$A$2516,A29,'PLAN DE CORTE'!$B$5:$B$2516,B29) -> 128.52286 | L29: =IF(G29>0,J29/G29,0) -> 0.15223841 | M29: =G29*INDEX(PARÁMETROS!$B$93:$B$97,MATCH(B29,PARÁMETROS!$A$93:$A$97,0)) -> 247.5
A30: NIVEL 4 | B30: 3/8 | C30: =SUMIFS('DATOS MODELO'!$D$232:$D$279,'DATOS MODELO'!$A$232:$A$279,A30,'DATOS MODELO'!$C$232:$C$279,B30) -> 1856 | D30: =SUMIFS('DATOS MODELO'!$E$232:$E$279,'DATOS MODELO'!$A$232:$A$279,A30,'DATOS MODELO'!$C$232:$C$279,B30) -> 2175.53 | E30: =D30*INDEX(PARÁMETROS!$B$93:$B$97,MATCH(B30,PARÁMETROS!$A$93:$A$97,0)) -> 1218.2968 | F30: =COUNTIFS('PLAN DE CORTE'!$A$5:$A$2516,A30,'PLAN DE CORTE'!$B$5:$B$2516,B30) -> 247 | G30: =F30*9 -> 2223 | H30: =SUMIFS('PLAN DE CORTE'!$F$5:$F$2516,'PLAN DE CORTE'!$A$5:$A$2516,A30,'PLAN DE CORTE'!$B$5:$B$2516,B30) -> 2175.5291 | I30: =H30-D30 -> -0.00091061336 | J30: =G30-H30 -> 47.470911 | K30: =SUMIFS('PLAN DE CORTE'!$H$5:$H$2516,'PLAN DE CORTE'!$A$5:$A$2516,A30,'PLAN DE CORTE'!$B$5:$B$2516,B30) -> 3.1119186 | L30: =IF(G30>0,J30/G30,0) -> 0.021354436 | M30: =G30*INDEX(PARÁMETROS!$B$93:$B$97,MATCH(B30,PARÁMETROS!$A$93:$A$97,0)) -> 1244.88
A31: NIVEL 4 | B31: 1/2 | C31: =SUMIFS('DATOS MODELO'!$D$232:$D$279,'DATOS MODELO'!$A$232:$A$279,A31,'DATOS MODELO'!$C$232:$C$279,B31) -> 80 | D31: =SUMIFS('DATOS MODELO'!$E$232:$E$279,'DATOS MODELO'!$A$232:$A$279,A31,'DATOS MODELO'!$C$232:$C$279,B31) -> 311.818 | E31: =D31*INDEX(PARÁMETROS!$B$93:$B$97,MATCH(B31,PARÁMETROS!$A$93:$A$97,0)) -> 309.94709 | F31: =COUNTIFS('PLAN DE CORTE'!$A$5:$A$2516,A31,'PLAN DE CORTE'!$B$5:$B$2516,B31) -> 39 | G31: =F31*9 -> 351 | H31: =SUMIFS('PLAN DE CORTE'!$F$5:$F$2516,'PLAN DE CORTE'!$A$5:$A$2516,A31,'PLAN DE CORTE'!$B$5:$B$2516,B31) -> 311.81762 | I31: =H31-D31 -> -0.00038119824 | J31: =G31-H31 -> 39.182381 | K31: =SUMIFS('PLAN DE CORTE'!$H$5:$H$2516,'PLAN DE CORTE'!$A$5:$A$2516,A31,'PLAN DE CORTE'!$B$5:$B$2516,B31) -> 30.063499 | L31: =IF(G31>0,J31/G31,0) -> 0.11163072 | M31: =G31*INDEX(PARÁMETROS!$B$93:$B$97,MATCH(B31,PARÁMETROS!$A$93:$A$97,0)) -> 348.894
A32: NIVEL 4 | B32: 5/8 | C32: =SUMIFS('DATOS MODELO'!$D$232:$D$279,'DATOS MODELO'!$A$232:$A$279,A32,'DATOS MODELO'!$C$232:$C$279,B32) -> 142 | D32: =SUMIFS('DATOS MODELO'!$E$232:$E$279,'DATOS MODELO'!$A$232:$A$279,A32,'DATOS MODELO'!$C$232:$C$279,B32) -> 481.568 | E32: =D32*INDEX(PARÁMETROS!$B$93:$B$97,MATCH(B32,PARÁMETROS!$A$93:$A$97,0)) -> 747.39354 | F32: =COUNTIFS('PLAN DE CORTE'!$A$5:$A$2516,A32,'PLAN DE CORTE'!$B$5:$B$2516,B32) -> 71 | G32: =F32*9 -> 639 | H32: =SUMIFS('PLAN DE CORTE'!$F$5:$F$2516,'PLAN DE CORTE'!$A$5:$A$2516,A32,'PLAN DE CORTE'!$B$5:$B$2516,B32) -> 481.56794 | I32: =H32-D32 -> -6.4116981e-05 | J32: =G32-H32 -> 157.43206 | K32: =SUMIFS('PLAN DE CORTE'!$H$5:$H$2516,'PLAN DE CORTE'!$A$5:$A$2516,A32,'PLAN DE CORTE'!$B$5:$B$2516,B32) -> 156.20449 | L32: =IF(G32>0,J32/G32,0) -> 0.24637256 | M32: =G32*INDEX(PARÁMETROS!$B$93:$B$97,MATCH(B32,PARÁMETROS!$A$93:$A$97,0)) -> 991.728
A33: NIVEL 4 | B33: 3/4 | C33: =SUMIFS('DATOS MODELO'!$D$232:$D$279,'DATOS MODELO'!$A$232:$A$279,A33,'DATOS MODELO'!$C$232:$C$279,B33) -> 100 | D33: =SUMIFS('DATOS MODELO'!$E$232:$E$279,'DATOS MODELO'!$A$232:$A$279,A33,'DATOS MODELO'!$C$232:$C$279,B33) -> 548.913 | E33: =D33*INDEX(PARÁMETROS!$B$93:$B$97,MATCH(B33,PARÁMETROS!$A$93:$A$97,0)) -> 1226.8206 | F33: =COUNTIFS('PLAN DE CORTE'!$A$5:$A$2516,A33,'PLAN DE CORTE'!$B$5:$B$2516,B33) -> 69 | G33: =F33*9 -> 621 | H33: =SUMIFS('PLAN DE CORTE'!$F$5:$F$2516,'PLAN DE CORTE'!$A$5:$A$2516,A33,'PLAN DE CORTE'!$B$5:$B$2516,B33) -> 558.11291 | I33: =H33-D33 -> 9.199906 | J33: =G33-H33 -> 62.887094 | K33: =SUMIFS('PLAN DE CORTE'!$H$5:$H$2516,'PLAN DE CORTE'!$A$5:$A$2516,A33,'PLAN DE CORTE'!$B$5:$B$2516,B33) -> 48.514542 | L33: =IF(G33>0,J33/G33,0) -> 0.10126746 | M33: =G33*INDEX(PARÁMETROS!$B$93:$B$97,MATCH(B33,PARÁMETROS!$A$93:$A$97,0)) -> 1387.935
A34: Subtotal NIVEL 4 | C34: =SUM(C29:C33) -> 2406 | D34: =SUM(D29:D33) -> 4357.113 | E34: =SUM(E29:E33) -> 3712.279 | F34: =SUM(F29:F33) -> 536 | G34: =SUM(G29:G33) -> 4824 | H34: =SUM(H29:H33) -> 4366.3115 | I34: =SUM(I29:I33) -> 9.1985212 | J34: =SUM(J29:J33) -> 457.68848 | K34: =SUM(K29:K33) -> 366.41731 | L34: =IF(G34>0,J34/G34,0) -> 0.09487738 | M34: =SUM(M29:M33) -> 4220.937
A35: NIVEL 5 | B35: 1/4 | C35: =SUMIFS('DATOS MODELO'!$D$232:$D$279,'DATOS MODELO'!$A$232:$A$279,A35,'DATOS MODELO'!$C$232:$C$279,B35) -> 228 | D35: =SUMIFS('DATOS MODELO'!$E$232:$E$279,'DATOS MODELO'!$A$232:$A$279,A35,'DATOS MODELO'!$C$232:$C$279,B35) -> 839.282 | E35: =D35*INDEX(PARÁMETROS!$B$93:$B$97,MATCH(B35,PARÁMETROS!$A$93:$A$97,0)) -> 209.8205 | F35: =COUNTIFS('PLAN DE CORTE'!$A$5:$A$2516,A35,'PLAN DE CORTE'!$B$5:$B$2516,B35) -> 110 | G35: =F35*9 -> 990 | H35: =SUMIFS('PLAN DE CORTE'!$F$5:$F$2516,'PLAN DE CORTE'!$A$5:$A$2516,A35,'PLAN DE CORTE'!$B$5:$B$2516,B35) -> 839.28247 | I35: =H35-D35 -> 0.00046578223 | J35: =G35-H35 -> 150.71753 | K35: =SUMIFS('PLAN DE CORTE'!$H$5:$H$2516,'PLAN DE CORTE'!$A$5:$A$2516,A35,'PLAN DE CORTE'!$B$5:$B$2516,B35) -> 128.52436 | L35: =IF(G35>0,J35/G35,0) -> 0.15223993 | M35: =G35*INDEX(PARÁMETROS!$B$93:$B$97,MATCH(B35,PARÁMETROS!$A$93:$A$97,0)) -> 247.5
A36: NIVEL 5 | B36: 3/8 | C36: =SUMIFS('DATOS MODELO'!$D$232:$D$279,'DATOS MODELO'!$A$232:$A$279,A36,'DATOS MODELO'!$C$232:$C$279,B36) -> 1856 | D36: =SUMIFS('DATOS MODELO'!$E$232:$E$279,'DATOS MODELO'!$A$232:$A$279,A36,'DATOS MODELO'!$C$232:$C$279,B36) -> 2175.53 | E36: =D36*INDEX(PARÁMETROS!$B$93:$B$97,MATCH(B36,PARÁMETROS!$A$93:$A$97,0)) -> 1218.2968 | F36: =COUNTIFS('PLAN DE CORTE'!$A$5:$A$2516,A36,'PLAN DE CORTE'!$B$5:$B$2516,B36) -> 247 | G36: =F36*9 -> 2223 | H36: =SUMIFS('PLAN DE CORTE'!$F$5:$F$2516,'PLAN DE CORTE'!$A$5:$A$2516,A36,'PLAN DE CORTE'!$B$5:$B$2516,B36) -> 2175.5291 | I36: =H36-D36 -> -0.00091061336 | J36: =G36-H36 -> 47.470911 | K36: =SUMIFS('PLAN DE CORTE'!$H$5:$H$2516,'PLAN DE CORTE'!$A$5:$A$2516,A36,'PLAN DE CORTE'!$B$5:$B$2516,B36) -> 3.1119186 | L36: =IF(G36>0,J36/G36,0) -> 0.021354436 | M36: =G36*INDEX(PARÁMETROS!$B$93:$B$97,MATCH(B36,PARÁMETROS!$A$93:$A$97,0)) -> 1244.88
A37: NIVEL 5 | B37: 1/2 | C37: =SUMIFS('DATOS MODELO'!$D$232:$D$279,'DATOS MODELO'!$A$232:$A$279,A37,'DATOS MODELO'!$C$232:$C$279,B37) -> 80 | D37: =SUMIFS('DATOS MODELO'!$E$232:$E$279,'DATOS MODELO'!$A$232:$A$279,A37,'DATOS MODELO'!$C$232:$C$279,B37) -> 284.36 | E37: =D37*INDEX(PARÁMETROS!$B$93:$B$97,MATCH(B37,PARÁMETROS!$A$93:$A$97,0)) -> 282.65384 | F37: =COUNTIFS('PLAN DE CORTE'!$A$5:$A$2516,A37,'PLAN DE CORTE'!$B$5:$B$2516,B37) -> 35 | G37: =F37*9 -> 315 | H37: =SUMIFS('PLAN DE CORTE'!$F$5:$F$2516,'PLAN DE CORTE'!$A$5:$A$2516,A37,'PLAN DE CORTE'!$B$5:$B$2516,B37) -> 284.36027 | I37: =H37-D37 -> 0.00027179005 | J37: =G37-H37 -> 30.639728 | K37: =SUMIFS('PLAN DE CORTE'!$H$5:$H$2516,'PLAN DE CORTE'!$A$5:$A$2516,A37,'PLAN DE CORTE'!$B$5:$B$2516,B37) -> 23.198087 | L37: =IF(G37>0,J37/G37,0) -> 0.097268978 | M37: =G37*INDEX(PARÁMETROS!$B$93:$B$97,MATCH(B37,PARÁMETROS!$A$93:$A$97,0)) -> 313.11
A38: NIVEL 5 | B38: 5/8 | C38: =SUMIFS('DATOS MODELO'!$D$232:$D$279,'DATOS MODELO'!$A$232:$A$279,A38,'DATOS MODELO'!$C$232:$C$279,B38) -> 142 | D38: =SUMIFS('DATOS MODELO'!$E$232:$E$279,'DATOS MODELO'!$A$232:$A$279,A38,'DATOS MODELO'!$C$232:$C$279,B38) -> 280.154 | E38: =D38*INDEX(PARÁMETROS!$B$93:$B$97,MATCH(B38,PARÁMETROS!$A$93:$A$97,0)) -> 434.79901 | F38: =COUNTIFS('PLAN DE CORTE'!$A$5:$A$2516,A38,'PLAN DE CORTE'!$B$5:$B$2516,B38) -> 35 | G38: =F38*9 -> 315 | H38: =SUMIFS('PLAN DE CORTE'!$F$5:$F$2516,'PLAN DE CORTE'!$A$5:$A$2516,A38,'PLAN DE CORTE'!$B$5:$B$2516,B38) -> 280.15435 | I38: =H38-D38 -> 0.00035400651 | J38: =G38-H38 -> 34.845646 | K38: =SUMIFS('PLAN DE CORTE'!$H$5:$H$2516,'PLAN DE CORTE'!$A$5:$A$2516,A38,'PLAN DE CORTE'!$B$5:$B$2516,B38) -> 30.813936 | L38: =IF(G38>0,J38/G38,0) -> 0.1106211 | M38: =G38*INDEX(PARÁMETROS!$B$93:$B$97,MATCH(B38,PARÁMETROS!$A$93:$A$97,0)) -> 488.88
A39: NIVEL 5 | B39: 3/4 | C39: =SUMIFS('DATOS MODELO'!$D$232:$D$279,'DATOS MODELO'!$A$232:$A$279,A39,'DATOS MODELO'!$C$232:$C$279,B39) -> 98 | D39: =SUMIFS('DATOS MODELO'!$E$232:$E$279,'DATOS MODELO'!$A$232:$A$279,A39,'DATOS MODELO'!$C$232:$C$279,B39) -> 537.465 | E39: =D39*INDEX(PARÁMETROS!$B$93:$B$97,MATCH(B39,PARÁMETROS!$A$93:$A$97,0)) -> 1201.2343 | F39: =COUNTIFS('PLAN DE CORTE'!$A$5:$A$2516,A39,'PLAN DE CORTE'!$B$5:$B$2516,B39) -> 67 | G39: =F39*9 -> 603 | H39: =SUMIFS('PLAN DE CORTE'!$F$5:$F$2516,'PLAN DE CORTE'!$A$5:$A$2516,A39,'PLAN DE CORTE'!$B$5:$B$2516,B39) -> 546.66478 | I39: =H39-D39 -> 9.199775 | J39: =G39-H39 -> 56.335225 | K39: =SUMIFS('PLAN DE CORTE'!$H$5:$H$2516,'PLAN DE CORTE'!$A$5:$A$2516,A39,'PLAN DE CORTE'!$B$5:$B$2516,B39) -> 41.873864 | L39: =IF(G39>0,J39/G39,0) -> 0.093424917 | M39: =G39*INDEX(PARÁMETROS!$B$93:$B$97,MATCH(B39,PARÁMETROS!$A$93:$A$97,0)) -> 1347.705
A40: Subtotal NIVEL 5 | C40: =SUM(C35:C39) -> 2404 | D40: =SUM(D35:D39) -> 4116.791 | E40: =SUM(E35:E39) -> 3346.8044 | F40: =SUM(F35:F39) -> 494 | G40: =SUM(G35:G39) -> 4446 | H40: =SUM(H35:H39) -> 4125.991 | I40: =SUM(I35:I39) -> 9.199956 | J40: =SUM(J35:J39) -> 320.00904 | K40: =SUM(K35:K39) -> 227.52217 | L40: =IF(G40>0,J40/G40,0) -> 0.071976843 | M40: =SUM(M35:M39) -> 3642.075
A42: TOTAL POR DIÁMETRO
A43: Nivel | B43: Ø | C43: N° barras (modelo) | D43: Longitud neta (m) | E43: kg netos | F43: Varillas de 9 m (und) | G43: Longitud comprada (m) | H43: Longitud cortada (m) | I43: Traslape adicional (m) | J43: Retazos (m) | K43: Retazos reutilizables ≥ 1 m (m) | L43: Desperdicio real (%) | M43: kg comprados (referencia)
A44: TODOS | B44: 1/4 | C44: =SUMIFS(C$5:C$41,$B$5:$B$41,B44,$A$5:$A$41,"<>Subtotal*") -> 912 | D44: =SUMIFS(D$5:D$41,$B$5:$B$41,B44,$A$5:$A$41,"<>Subtotal*") -> 3357.134 | E44: =SUMIFS(E$5:E$41,$B$5:$B$41,B44,$A$5:$A$41,"<>Subtotal*") -> 839.2835 | F44: =SUMIFS(F$5:F$41,$B$5:$B$41,B44,$A$5:$A$41,"<>Subtotal*") -> 440 | G44: =SUMIFS(G$5:G$41,$B$5:$B$41,B44,$A$5:$A$41,"<>Subtotal*") -> 3960 | H44: =SUMIFS(H$5:H$41,$B$5:$B$41,B44,$A$5:$A$41,"<>Subtotal*") -> 3357.1344 | I44: =SUMIFS(I$5:I$41,$B$5:$B$41,B44,$A$5:$A$41,"<>Subtotal*") -> 0.00037925795 | J44: =SUMIFS(J$5:J$41,$B$5:$B$41,B44,$A$5:$A$41,"<>Subtotal*") -> 602.86562 | K44: =SUMIFS(K$5:K$41,$B$5:$B$41,B44,$A$5:$A$41,"<>Subtotal*") -> 514.09293 | L44: =IF(G44>0,J44/G44,0) -> 0.15223879 | M44: =SUMIFS(M$5:M$41,$B$5:$B$41,B44,$A$5:$A$41,"<>Subtotal*") -> 990
A45: TODOS | B45: 3/8 | C45: =SUMIFS(C$5:C$41,$B$5:$B$41,B45,$A$5:$A$41,"<>Subtotal*") -> 8847 | D45: =SUMIFS(D$5:D$41,$B$5:$B$41,B45,$A$5:$A$41,"<>Subtotal*") -> 10143.624 | E45: =SUMIFS(E$5:E$41,$B$5:$B$41,B45,$A$5:$A$41,"<>Subtotal*") -> 5680.4294 | F45: =SUMIFS(F$5:F$41,$B$5:$B$41,B45,$A$5:$A$41,"<>Subtotal*") -> 1152 | G45: =SUMIFS(G$5:G$41,$B$5:$B$41,B45,$A$5:$A$41,"<>Subtotal*") -> 10368 | H45: =SUMIFS(H$5:H$41,$B$5:$B$41,B45,$A$5:$A$41,"<>Subtotal*") -> 10143.622 | I45: =SUMIFS(I$5:I$41,$B$5:$B$41,B45,$A$5:$A$41,"<>Subtotal*") -> -0.0020032926 | J45: =SUMIFS(J$5:J$41,$B$5:$B$41,B45,$A$5:$A$41,"<>Subtotal*") -> 224.378 | K45: =SUMIFS(K$5:K$41,$B$5:$B$41,B45,$A$5:$A$41,"<>Subtotal*") -> 16.972864 | L45: =IF(G45>0,J45/G45,0) -> 0.021641397 | M45: =SUMIFS(M$5:M$41,$B$5:$B$41,B45,$A$5:$A$41,"<>Subtotal*") -> 5806.08
A46: TODOS | B46: 1/2 | C46: =SUMIFS(C$5:C$41,$B$5:$B$41,B46,$A$5:$A$41,"<>Subtotal*") -> 372 | D46: =SUMIFS(D$5:D$41,$B$5:$B$41,B46,$A$5:$A$41,"<>Subtotal*") -> 1344.145 | E46: =SUMIFS(E$5:E$41,$B$5:$B$41,B46,$A$5:$A$41,"<>Subtotal*") -> 1336.0801 | F46: =SUMIFS(F$5:F$41,$B$5:$B$41,B46,$A$5:$A$41,"<>Subtotal*") -> 171 | G46: =SUMIFS(G$5:G$41,$B$5:$B$41,B46,$A$5:$A$41,"<>Subtotal*") -> 1539 | H46: =SUMIFS(H$5:H$41,$B$5:$B$41,B46,$A$5:$A$41,"<>Subtotal*") -> 1344.1439 | I46: =SUMIFS(I$5:I$41,$B$5:$B$41,B46,$A$5:$A$41,"<>Subtotal*") -> -0.0011174259 | J46: =SUMIFS(J$5:J$41,$B$5:$B$41,B46,$A$5:$A$41,"<>Subtotal*") -> 194.85612 | K46: =SUMIFS(K$5:K$41,$B$5:$B$41,B46,$A$5:$A$41,"<>Subtotal*") -> 159.80908 | L46: =IF(G46>0,J46/G46,0) -> 0.12661216 | M46: =SUMIFS(M$5:M$41,$B$5:$B$41,B46,$A$5:$A$41,"<>Subtotal*") -> 1529.766
A47: TODOS | B47: 5/8 | C47: =SUMIFS(C$5:C$41,$B$5:$B$41,B47,$A$5:$A$41,"<>Subtotal*") -> 948 | D47: =SUMIFS(D$5:D$41,$B$5:$B$41,B47,$A$5:$A$41,"<>Subtotal*") -> 2801.598 | E47: =SUMIFS(E$5:E$41,$B$5:$B$41,B47,$A$5:$A$41,"<>Subtotal*") -> 4348.0801 | F47: =SUMIFS(F$5:F$41,$B$5:$B$41,B47,$A$5:$A$41,"<>Subtotal*") -> 377 | G47: =SUMIFS(G$5:G$41,$B$5:$B$41,B47,$A$5:$A$41,"<>Subtotal*") -> 3393 | H47: =SUMIFS(H$5:H$41,$B$5:$B$41,B47,$A$5:$A$41,"<>Subtotal*") -> 2801.5983 | I47: =SUMIFS(I$5:I$41,$B$5:$B$41,B47,$A$5:$A$41,"<>Subtotal*") -> 0.00034110187 | J47: =SUMIFS(J$5:J$41,$B$5:$B$41,B47,$A$5:$A$41,"<>Subtotal*") -> 591.40166 | K47: =SUMIFS(K$5:K$41,$B$5:$B$41,B47,$A$5:$A$41,"<>Subtotal*") -> 574.93603 | L47: =IF(G47>0,J47/G47,0) -> 0.17430052 | M47: =SUMIFS(M$5:M$41,$B$5:$B$41,B47,$A$5:$A$41,"<>Subtotal*") -> 5265.936
A48: TODOS | B48: 3/4 | C48: =SUMIFS(C$5:C$41,$B$5:$B$41,B48,$A$5:$A$41,"<>Subtotal*") -> 520 | D48: =SUMIFS(D$5:D$41,$B$5:$B$41,B48,$A$5:$A$41,"<>Subtotal*") -> 2948.219 | E48: =SUMIFS(E$5:E$41,$B$5:$B$41,B48,$A$5:$A$41,"<>Subtotal*") -> 6589.2695 | F48: =SUMIFS(F$5:F$41,$B$5:$B$41,B48,$A$5:$A$41,"<>Subtotal*") -> 372 | G48: =SUMIFS(G$5:G$41,$B$5:$B$41,B48,$A$5:$A$41,"<>Subtotal*") -> 3348 | H48: =SUMIFS(H$5:H$41,$B$5:$B$41,B48,$A$5:$A$41,"<>Subtotal*") -> 2996.5183 | I48: =SUMIFS(I$5:I$41,$B$5:$B$41,B48,$A$5:$A$41,"<>Subtotal*") -> 48.29935 | J48: =SUMIFS(J$5:J$41,$B$5:$B$41,B48,$A$5:$A$41,"<>Subtotal*") -> 351.48165 | K48: =SUMIFS(K$5:K$41,$B$5:$B$41,B48,$A$5:$A$41,"<>Subtotal*") -> 270.12853 | L48: =IF(G48>0,J48/G48,0) -> 0.10498257 | M48: =SUMIFS(M$5:M$41,$B$5:$B$41,B48,$A$5:$A$41,"<>Subtotal*") -> 7482.78
A49: TOTAL GENERAL | C49: =SUM(C44:C48) -> 11599 | D49: =SUM(D44:D48) -> 20594.72 | E49: =SUM(E44:E48) -> 18793.143 | F49: =SUM(F44:F48) -> 2512 | G49: =SUM(G44:G48) -> 22608 | H49: =SUM(H44:H48) -> 20643.017 | I49: =SUM(I44:I48) -> 48.296949 | J49: =SUM(J44:J48) -> 1964.9831 | K49: =SUM(K44:K48) -> 1535.9394 | L49: =IF(G49>0,J49/G49,0) -> 0.086915386 | M49: =SUM(M44:M48) -> 21074.562
A51: CONTROL DE CALIDAD contra los conteos del IFC (dato del usuario)
A52: Control | B52: Ø / grupo | C52: Esperado | D52: Calculado | E52: Diferencia | F52: Estado
A53: N° de barras | B53: 3/8 | C53: 8847 | D53: =SUMIFS(C44:C48,B44:B48,B53) -> 8847 | E53: =D53-C53 -> 0 | F53: =IF(ABS(E53)<0.5,"OK","REVISAR") -> OK
A54: N° de barras | B54: 5/8 | C54: 948 | D54: =SUMIFS(C44:C48,B44:B48,B54) -> 948 | E54: =D54-C54 -> 0 | F54: =IF(ABS(E54)<0.5,"OK","REVISAR") -> OK
A55: N° de barras | B55: 1/4 | C55: 912 | D55: =SUMIFS(C44:C48,B44:B48,B55) -> 912 | E55: =D55-C55 -> 0 | F55: =IF(ABS(E55)<0.5,"OK","REVISAR") -> OK
A56: N° de barras | B56: 3/4 | C56: 520 | D56: =SUMIFS(C44:C48,B44:B48,B56) -> 520 | E56: =D56-C56 -> 0 | F56: =IF(ABS(E56)<0.5,"OK","REVISAR") -> OK
A57: N° de barras | B57: 1/2 | C57: 372 | D57: =SUMIFS(C44:C48,B44:B48,B57) -> 372 | E57: =D57-C57 -> 0 | F57: =IF(ABS(E57)<0.5,"OK","REVISAR") -> OK
A58: Longitud Ø3/4" (m) | B58: Vigas de conexión | C58: 580 | D58: =SUMIFS('DATOS MODELO'!$E$232:$E$279,'DATOS MODELO'!$A$232:$A$279,"CIMENTACIÓN",'DATOS MODELO'!$B$232:$B$279,"Vigas de conexión",'DATOS MODELO'!$C$232:$C$279,"3/4") -> 579.716 | E58: =D58-C58 -> -0.284 | F58: =IF(ABS(E58)<=1,"OK","REVISAR") -> OK
A59: Longitud Ø3/4" (m) | B59: Vigas N2 | C59: 721 | D59: =SUMIFS('DATOS MODELO'!$E$232:$E$279,'DATOS MODELO'!$A$232:$A$279,"NIVEL 2",'DATOS MODELO'!$B$232:$B$279,"Vigas",'DATOS MODELO'!$C$232:$C$279,"3/4") -> 721.345 | E59: =D59-C59 -> 0.345 | F59: =IF(ABS(E59)<=1,"OK","REVISAR") -> OK
A60: Longitud Ø3/4" (m) | B60: Vigas N3 | C60: 561 | D60: =SUMIFS('DATOS MODELO'!$E$232:$E$279,'DATOS MODELO'!$A$232:$A$279,"NIVEL 3",'DATOS MODELO'!$B$232:$B$279,"Vigas",'DATOS MODELO'!$C$232:$C$279,"3/4") -> 560.78 | E60: =D60-C60 -> -0.22 | F60: =IF(ABS(E60)<=1,"OK","REVISAR") -> OK
A61: Longitud Ø3/4" (m) | B61: Vigas N4 | C61: 549 | D61: =SUMIFS('DATOS MODELO'!$E$232:$E$279,'DATOS MODELO'!$A$232:$A$279,"NIVEL 4",'DATOS MODELO'!$B$232:$B$279,"Vigas",'DATOS MODELO'!$C$232:$C$279,"3/4") -> 548.913 | E61: =D61-C61 -> -0.087 | F61: =IF(ABS(E61)<=1,"OK","REVISAR") -> OK
A62: Longitud Ø3/4" (m) | B62: Vigas N5 | C62: 538 | D62: =SUMIFS('DATOS MODELO'!$E$232:$E$279,'DATOS MODELO'!$A$232:$A$279,"NIVEL 5",'DATOS MODELO'!$B$232:$B$279,"Vigas",'DATOS MODELO'!$C$232:$C$279,"3/4") -> 537.465 | E62: =D62-C62 -> -0.535 | F62: =IF(ABS(E62)<=1,"OK","REVISAR") -> OK
A63: Longitud Ø3/4" total (m) | B63: Solo en vigas | C63: 2948 | D63: =SUMIFS('DATOS MODELO'!$E$232:$E$279,'DATOS MODELO'!$C$232:$C$279,"3/4") -> 2948.219 | E63: =D63-C63 -> 0.219 | F63: =IF(ABS(E63)<=1,"OK","REVISAR") -> OK

Sheet LISTA DE COMPRAS
A1: LISTA DE COMPRAS - CASCO ESTRUCTURAL (unidades comerciales, precios referenciales Cusco)
A2: Acero: unidad de compra = VARILLA de 9 m; los kg van solo como referencia. Alambres en kg.
A4: RESUMEN CONSOLIDADO (todos los niveles)
B5: Categoría | C5: Insumo | D5: Unidad de compra | E5: Cantidad requerida | F5: Cantidad a comprar | G5: Precio unitario (S/) | H5: Total (S/) | I5: Peso de referencia (kg) | J5: % del costo
B6: =INDEX(PARÁMETROS!$F$70:$F$89,MATCH(C6,PARÁMETROS!$A$70:$A$89,0)) -> Concreto | C6: Cemento Portland IP 42.5 kg | D6: =INDEX(PARÁMETROS!$B$70:$B$89,MATCH(C6,PARÁMETROS!$A$70:$A$89,0)) -> bolsa | E6: =SUMIFS($E$38:$E$182,$C$38:$C$182,C6) -> 1547.7451 | F6: =SUMIFS($F$38:$F$182,$C$38:$C$182,C6) -> 1552 | G6: =INDEX(PARÁMETROS!$C$70:$C$89,MATCH(C6,PARÁMETROS!$A$70:$A$89,0)) -> 27 | H6: =SUMIFS($H$38:$H$182,$C$38:$C$182,C6) -> 41904 | I6: =IF(SUMIFS($I$38:$I$182,$C$38:$C$182,C6)=0,"",SUMIFS($I$38:$I$182,$C$38:$C$182,C6)) | J6: =IF($H$26>0,H6/$H$26,0) -> 0.24519054
B7: =INDEX(PARÁMETROS!$F$70:$F$89,MATCH(C7,PARÁMETROS!$A$70:$A$89,0)) -> Concreto | C7: Arena gruesa | D7: =INDEX(PARÁMETROS!$B$70:$B$89,MATCH(C7,PARÁMETROS!$A$70:$A$89,0)) -> m³ | E7: =SUMIFS($E$38:$E$182,$C$38:$C$182,C7) -> 85.269933 | F7: =SUMIFS($F$38:$F$182,$C$38:$C$182,C7) -> 86.5 | G7: =INDEX(PARÁMETROS!$C$70:$C$89,MATCH(C7,PARÁMETROS!$A$70:$A$89,0)) -> 70 | H7: =SUMIFS($H$38:$H$182,$C$38:$C$182,C7) -> 6055 | I7: =IF(SUMIFS($I$38:$I$182,$C$38:$C$182,C7)=0,"",SUMIFS($I$38:$I$182,$C$38:$C$182,C7)) | J7: =IF($H$26>0,H7/$H$26,0) -> 0.035429284
B8: =INDEX(PARÁMETROS!$F$70:$F$89,MATCH(C8,PARÁMETROS!$A$70:$A$89,0)) -> Concreto | C8: Piedra chancada 1/2" | D8: =INDEX(PARÁMETROS!$B$70:$B$89,MATCH(C8,PARÁMETROS!$A$70:$A$89,0)) -> m³ | E8: =SUMIFS($E$38:$E$182,$C$38:$C$182,C8) -> 87.565645 | F8: =SUMIFS($F$38:$F$182,$C$38:$C$182,C8) -> 90 | G8: =INDEX(PARÁMETROS!$C$70:$C$89,MATCH(C8,PARÁMETROS!$A$70:$A$89,0)) -> 80 | H8: =SUMIFS($H$38:$H$182,$C$38:$C$182,C8) -> 7200 | I8: =IF(SUMIFS($I$38:$I$182,$C$38:$C$182,C8)=0,"",SUMIFS($I$38:$I$182,$C$38:$C$182,C8)) | J8: =IF($H$26>0,H8/$H$26,0) -> 0.042128959
B9: =INDEX(PARÁMETROS!$F$70:$F$89,MATCH(C9,PARÁMETROS!$A$70:$A$89,0)) -> Concreto | C9: Agua | D9: =INDEX(PARÁMETROS!$B$70:$B$89,MATCH(C9,PARÁMETROS!$A$70:$A$89,0)) -> m³ | E9: =SUMIFS($E$38:$E$182,$C$38:$C$182,C9) -> 30.312349 | F9: =SUMIFS($F$38:$F$182,$C$38:$C$182,C9) -> 32.5 | G9: =INDEX(PARÁMETROS!$C$70:$C$89,MATCH(C9,PARÁMETROS!$A$70:$A$89,0)) -> 7 | H9: =SUMIFS($H$38:$H$182,$C$38:$C$182,C9) -> 227.5 | I9: =IF(SUMIFS($I$38:$I$182,$C$38:$C$182,C9)=0,"",SUMIFS($I$38:$I$182,$C$38:$C$182,C9)) | J9: =IF($H$26>0,H9/$H$26,0) -> 0.0013311581
B10: =INDEX(PARÁMETROS!$F$70:$F$89,MATCH(C10,PARÁMETROS!$A$70:$A$89,0)) -> Concreto | C10: Casetón EPS 1.20x0.30x0.15 | D10: =INDEX(PARÁMETROS!$B$70:$B$89,MATCH(C10,PARÁMETROS!$A$70:$A$89,0)) -> und | E10: =SUMIFS($E$38:$E$182,$C$38:$C$182,C10) -> 596.33567 | F10: =SUMIFS($F$38:$F$182,$C$38:$C$182,C10) -> 600 | G10: =INDEX(PARÁMETROS!$C$70:$C$89,MATCH(C10,PARÁMETROS!$A$70:$A$89,0)) -> 12.9 | H10: =SUMIFS($H$38:$H$182,$C$38:$C$182,C10) -> 7740 | I10: =IF(SUMIFS($I$38:$I$182,$C$38:$C$182,C10)=0,"",SUMIFS($I$38:$I$182,$C$38:$C$182,C10)) | J10: =IF($H$26>0,H10/$H$26,0) -> 0.045288631
B11: =INDEX(PARÁMETROS!$F$70:$F$89,MATCH(C11,PARÁMETROS!$A$70:$A$89,0)) -> Acero | C11: Varilla Ø1/4" x 9 m | D11: =INDEX(PARÁMETROS!$B$70:$B$89,MATCH(C11,PARÁMETROS!$A$70:$A$89,0)) -> und | E11: =SUMIFS($E$38:$E$182,$C$38:$C$182,C11) -> 440 | F11: =SUMIFS($F$38:$F$182,$C$38:$C$182,C11) -> 440 | G11: =INDEX(PARÁMETROS!$C$70:$C$89,MATCH(C11,PARÁMETROS!$A$70:$A$89,0)) -> 9.5 | H11: =SUMIFS($H$38:$H$182,$C$38:$C$182,C11) -> 4180 | I11: =IF(SUMIFS($I$38:$I$182,$C$38:$C$182,C11)=0,"",SUMIFS($I$38:$I$182,$C$38:$C$182,C11)) -> 990 | J11: =IF($H$26>0,H11/$H$26,0) -> 0.024458201
B12: =INDEX(PARÁMETROS!$F$70:$F$89,MATCH(C12,PARÁMETROS!$A$70:$A$89,0)) -> Acero | C12: Varilla Ø3/8" x 9 m | D12: =INDEX(PARÁMETROS!$B$70:$B$89,MATCH(C12,PARÁMETROS!$A$70:$A$89,0)) -> und | E12: =SUMIFS($E$38:$E$182,$C$38:$C$182,C12) -> 1152 | F12: =SUMIFS($F$38:$F$182,$C$38:$C$182,C12) -> 1152 | G12: =INDEX(PARÁMETROS!$C$70:$C$89,MATCH(C12,PARÁMETROS!$A$70:$A$89,0)) -> 20.13 | H12: =SUMIFS($H$38:$H$182,$C$38:$C$182,C12) -> 23189.76 | I12: =IF(SUMIFS($I$38:$I$182,$C$38:$C$182,C12)=0,"",SUMIFS($I$38:$I$182,$C$38:$C$182,C12)) -> 5806.08 | J12: =IF($H$26>0,H12/$H$26,0) -> 0.13568895
B13: =INDEX(PARÁMETROS!$F$70:$F$89,MATCH(C13,PARÁMETROS!$A$70:$A$89,0)) -> Acero | C13: Varilla Ø1/2" x 9 m | D13: =INDEX(PARÁMETROS!$B$70:$B$89,MATCH(C13,PARÁMETROS!$A$70:$A$89,0)) -> und | E13: =SUMIFS($E$38:$E$182,$C$38:$C$182,C13) -> 171 | F13: =SUMIFS($F$38:$F$182,$C$38:$C$182,C13) -> 171 | G13: =INDEX(PARÁMETROS!$C$70:$C$89,MATCH(C13,PARÁMETROS!$A$70:$A$89,0)) -> 36.09 | H13: =SUMIFS($H$38:$H$182,$C$38:$C$182,C13) -> 6171.39 | I13: =IF(SUMIFS($I$38:$I$182,$C$38:$C$182,C13)=0,"",SUMIFS($I$38:$I$182,$C$38:$C$182,C13)) -> 1529.766 | J13: =IF($H$26>0,H13/$H$26,0) -> 0.03611031
B14: =INDEX(PARÁMETROS!$F$70:$F$89,MATCH(C14,PARÁMETROS!$A$70:$A$89,0)) -> Acero | C14: Varilla Ø5/8" x 9 m | D14: =INDEX(PARÁMETROS!$B$70:$B$89,MATCH(C14,PARÁMETROS!$A$70:$A$89,0)) -> und | E14: =SUMIFS($E$38:$E$182,$C$38:$C$182,C14) -> 377 | F14: =SUMIFS($F$38:$F$182,$C$38:$C$182,C14) -> 377 | G14: =INDEX(PARÁMETROS!$C$70:$C$89,MATCH(C14,PARÁMETROS!$A$70:$A$89,0)) -> 55.82 | H14: =SUMIFS($H$38:$H$182,$C$38:$C$182,C14) -> 21044.14 | I14: =IF(SUMIFS($I$38:$I$182,$C$38:$C$182,C14)=0,"",SUMIFS($I$38:$I$182,$C$38:$C$182,C14)) -> 5265.936 | J14: =IF($H$26>0,H14/$H$26,0) -> 0.1231344
B15: =INDEX(PARÁMETROS!$F$70:$F$89,MATCH(C15,PARÁMETROS!$A$70:$A$89,0)) -> Acero | C15: Varilla Ø3/4" x 9 m | D15: =INDEX(PARÁMETROS!$B$70:$B$89,MATCH(C15,PARÁMETROS!$A$70:$A$89,0)) -> und | E15: =SUMIFS($E$38:$E$182,$C$38:$C$182,C15) -> 372 | F15: =SUMIFS($F$38:$F$182,$C$38:$C$182,C15) -> 372 | G15: =INDEX(PARÁMETROS!$C$70:$C$89,MATCH(C15,PARÁMETROS!$A$70:$A$89,0)) -> 82.09 | H15: =SUMIFS($H$38:$H$182,$C$38:$C$182,C15) -> 30537.48 | I15: =IF(SUMIFS($I$38:$I$182,$C$38:$C$182,C15)=0,"",SUMIFS($I$38:$I$182,$C$38:$C$182,C15)) -> 7482.78 | J15: =IF($H$26>0,H15/$H$26,0) -> 0.17868226
B16: =INDEX(PARÁMETROS!$F$70:$F$89,MATCH(C16,PARÁMETROS!$A$70:$A$89,0)) -> Acero | C16: Alambre negro N°16 | D16: =INDEX(PARÁMETROS!$B$70:$B$89,MATCH(C16,PARÁMETROS!$A$70:$A$89,0)) -> kg | E16: =SUMIFS($E$38:$E$182,$C$38:$C$182,C16) -> 563.79428 | F16: =SUMIFS($F$38:$F$182,$C$38:$C$182,C16) -> 567 | G16: =INDEX(PARÁMETROS!$C$70:$C$89,MATCH(C16,PARÁMETROS!$A$70:$A$89,0)) -> 3.65 | H16: =SUMIFS($H$38:$H$182,$C$38:$C$182,C16) -> 2069.55 | I16: =IF(SUMIFS($I$38:$I$182,$C$38:$C$182,C16)=0,"",SUMIFS($I$38:$I$182,$C$38:$C$182,C16)) -> 567 | J16: =IF($H$26>0,H16/$H$26,0) -> 0.012109443
B17: =INDEX(PARÁMETROS!$F$70:$F$89,MATCH(C17,PARÁMETROS!$A$70:$A$89,0)) -> Acero | C17: Disco de corte 7" | D17: =INDEX(PARÁMETROS!$B$70:$B$89,MATCH(C17,PARÁMETROS!$A$70:$A$89,0)) -> und | E17: =SUMIFS($E$38:$E$182,$C$38:$C$182,C17) -> 77.326667 | F17: =SUMIFS($F$38:$F$182,$C$38:$C$182,C17) -> 83 | G17: =INDEX(PARÁMETROS!$C$70:$C$89,MATCH(C17,PARÁMETROS!$A$70:$A$89,0)) -> 12 | H17: =SUMIFS($H$38:$H$182,$C$38:$C$182,C17) -> 996 | I17: =IF(SUMIFS($I$38:$I$182,$C$38:$C$182,C17)=0,"",SUMIFS($I$38:$I$182,$C$38:$C$182,C17)) | J17: =IF($H$26>0,H17/$H$26,0) -> 0.0058278393
... B25: =INDEX(PARÁMETROS!$F$70:$F$89,MATCH(C25,PARÁMETROS!$A$70:$A$89,0)) -> Curado | C25: Curador químico (membrana) | D25: =INDEX(PARÁMETROS!$B$70:$B$89,MATCH(C25,PARÁMETROS!$A$70:$A$89,0)) -> gal | E25: =SUMIFS($E$38:$E$182,$C$38:$C$182,C25) -> 58.193416 | F25: =SUMIFS($F$38:$F$182,$C$38:$C$182,C25) -> 61 | G25: =INDEX(PARÁMETROS!$C$70:$C$89,MATCH(C25,PARÁMETROS!$A$70:$A$89,0)) -> 40 | H25: =SUMIFS($H$38:$H$182,$C$38:$C$182,C25) -> 2440 | I25: =IF(SUMIFS($I$38:$I$182,$C$38:$C$182,C25)=0,"",SUMIFS($I$38:$I$182,$C$38:$C$182,C25)) | J25: =IF($H$26>0,H25/$H$26,0) -> 0.014277036
C26: TOTAL GENERAL (S/) | H26: =SUM(H6:H25) -> 170903.82
A28: SUBTOTAL POR NIVEL Y CATEGORÍA (S/)
A29: Nivel | B29: Concreto | C29: Acero | D29: Encofrado | E29: Curado | F29: Total nivel (S/) | G29: % del total
A30: CIMENTACIÓN | B30: =SUMIFS($H$38:$H$182,$A$38:$A$182,$A30,$B$38:$B$182,"Concreto") -> 12201 | C30: =SUMIFS($H$38:$H$182,$A$38:$A$182,$A30,$B$38:$B$182,"Acero") -> 11205.48 | D30: =SUMIFS($H$38:$H$182,$A$38:$A$182,$A30,$B$38:$B$182,"Encofrado") -> 352.6 | E30: =SUMIFS($H$38:$H$182,$A$38:$A$182,$A30,$B$38:$B$182,"Curado") -> 200 | F30: =SUM(B30:E30) -> 23959.08 | G30: =IF($F$36>0,F30/$F$36,0) -> 0.14019043
A31: NIVEL 1 | B31: =SUMIFS($H$38:$H$182,$A$38:$A$182,$A31,$B$38:$B$182,"Concreto") -> 4507 | C31: =SUMIFS($H$38:$H$182,$A$38:$A$182,$A31,$B$38:$B$182,"Acero") -> 6108.93 | D31: =SUMIFS($H$38:$H$182,$A$38:$A$182,$A31,$B$38:$B$182,"Encofrado") -> 630.6 | E31: =SUMIFS($H$38:$H$182,$A$38:$A$182,$A31,$B$38:$B$182,"Curado") -> 280 | F31: =SUM(B31:E31) -> 11526.53 | G31: =IF($F$36>0,F31/$F$36,0) -> 0.067444543
A32: NIVEL 2 | B32: =SUMIFS($H$38:$H$182,$A$38:$A$182,$A32,$B$38:$B$182,"Concreto") -> 12145 | C32: =SUMIFS($H$38:$H$182,$A$38:$A$182,$A32,$B$38:$B$182,"Acero") -> 20473.24 | D32: =SUMIFS($H$38:$H$182,$A$38:$A$182,$A32,$B$38:$B$182,"Encofrado") -> 3966.9 | E32: =SUMIFS($H$38:$H$182,$A$38:$A$182,$A32,$B$38:$B$182,"Curado") -> 520 | F32: =SUM(B32:E32) -> 37105.14 | G32: =IF($F$36>0,F32/$F$36,0) -> 0.21711124
A33: NIVEL 3 | B33: =SUMIFS($H$38:$H$182,$A$38:$A$182,$A33,$B$38:$B$182,"Concreto") -> 11424.5 | C33: =SUMIFS($H$38:$H$182,$A$38:$A$182,$A33,$B$38:$B$182,"Acero") -> 18077.68 | D33: =SUMIFS($H$38:$H$182,$A$38:$A$182,$A33,$B$38:$B$182,"Encofrado") -> 3686.8 | E33: =SUMIFS($H$38:$H$182,$A$38:$A$182,$A33,$B$38:$B$182,"Curado") -> 480 | F33: =SUM(B33:E33) -> 33668.98 | G33: =IF($F$36>0,F33/$F$36,0) -> 0.19700543
A34: NIVEL 4 | B34: =SUMIFS($H$38:$H$182,$A$38:$A$182,$A34,$B$38:$B$182,"Concreto") -> 11424.5 | C34: =SUMIFS($H$38:$H$182,$A$38:$A$182,$A34,$B$38:$B$182,"Acero") -> 17909.85 | D34: =SUMIFS($H$38:$H$182,$A$38:$A$182,$A34,$B$38:$B$182,"Encofrado") -> 3686.8 | E34: =SUMIFS($H$38:$H$182,$A$38:$A$182,$A34,$B$38:$B$182,"Curado") -> 480 | F34: =SUM(B34:E34) -> 33501.15 | G34: =IF($F$36>0,F34/$F$36,0) -> 0.19602341
A35: NIVEL 5 | B35: =SUMIFS($H$38:$H$182,$A$38:$A$182,$A35,$B$38:$B$182,"Concreto") -> 11424.5 | C35: =SUMIFS($H$38:$H$182,$A$38:$A$182,$A35,$B$38:$B$182,"Acero") -> 15551.64 | D35: =SUMIFS($H$38:$H$182,$A$38:$A$182,$A35,$B$38:$B$182,"Encofrado") -> 3686.8 | E35: =SUMIFS($H$38:$H$182,$A$38:$A$182,$A35,$B$38:$B$182,"Curado") -> 480 | F35: =SUM(B35:E35) -> 31142.94 | G35: =IF($F$36>0,F35/$F$36,0) -> 0.18222495
A36: TOTAL | B36: =SUM(B30:B35) -> 63126.5 | C36: =SUM(C30:C35) -> 89326.82 | D36: =SUM(D30:D35) -> 16010.5 | E36: =SUM(E30:E35) -> 2440 | F36: =SUM(F30:F35) -> 170903.82 | G36: =SUM(G30:G35) -> 1
A38: CIMENTACIÓN
A39: Nivel | B39: Categoría | C39: Insumo | D39: Unidad de compra | E39: Cantidad requerida | F39: Cantidad a comprar | G39: Precio unitario (S/) | H39: Subtotal (S/) | I39: Peso de referencia (kg) | J39: Nota
A40: CIMENTACIÓN | B40: =INDEX(PARÁMETROS!$F$70:$F$89,MATCH(C40,PARÁMETROS!$A$70:$A$89,0)) -> Concreto | C40: Cemento Portland IP 42.5 kg | D40: =INDEX(PARÁMETROS!$B$70:$B$89,MATCH(C40,PARÁMETROS!$A$70:$A$89,0)) -> bolsa | E40: =SUMIFS('METRADO POR NIVEL'!$I$4:$I$150,'METRADO POR NIVEL'!$A$4:$A$150,A40) -> 335.46224 | F40: =ROUNDUP(E40,0) -> 336 | G40: =INDEX(PARÁMETROS!$C$70:$C$89,MATCH(C40,PARÁMETROS!$A$70:$A$89,0)) -> 27 | H40: =F40*G40 -> 9072
A41: CIMENTACIÓN | B41: =INDEX(PARÁMETROS!$F$70:$F$89,MATCH(C41,PARÁMETROS!$A$70:$A$89,0)) -> Concreto | C41: Arena gruesa | D41: =INDEX(PARÁMETROS!$B$70:$B$89,MATCH(C41,PARÁMETROS!$A$70:$A$89,0)) -> m³ | E41: =SUMIFS('METRADO POR NIVEL'!$J$4:$J$150,'METRADO POR NIVEL'!$A$4:$A$150,A41) -> 19.631461 | F41: =CEILING(E41,0.5) -> 20 | G41: =INDEX(PARÁMETROS!$C$70:$C$89,MATCH(C41,PARÁMETROS!$A$70:$A$89,0)) -> 70 | H41: =F41*G41 -> 1400
A42: CIMENTACIÓN | B42: =INDEX(PARÁMETROS!$F$70:$F$89,MATCH(C42,PARÁMETROS!$A$70:$A$89,0)) -> Concreto | C42: Piedra chancada 1/2" | D42: =INDEX(PARÁMETROS!$B$70:$B$89,MATCH(C42,PARÁMETROS!$A$70:$A$89,0)) -> m³ | E42: =SUMIFS('METRADO POR NIVEL'!$K$4:$K$150,'METRADO POR NIVEL'!$A$4:$A$150,A42) -> 20.66855 | F42: =CEILING(E42,0.5) -> 21 | G42: =INDEX(PARÁMETROS!$C$70:$C$89,MATCH(C42,PARÁMETROS!$A$70:$A$89,0)) -> 80 | H42: =F42*G42 -> 1680
A43: CIMENTACIÓN | B43: =INDEX(PARÁMETROS!$F$70:$F$89,MATCH(C43,PARÁMETROS!$A$70:$A$89,0)) -> Concreto | C43: Agua | D43: =INDEX(PARÁMETROS!$B$70:$B$89,MATCH(C43,PARÁMETROS!$A$70:$A$89,0)) -> m³ | E43: =SUMIFS('METRADO POR NIVEL'!$L$4:$L$150,'METRADO POR NIVEL'!$A$4:$A$150,A43) -> 6.9114764 | F43: =CEILING(E43,0.5) -> 7 | G43: =INDEX(PARÁMETROS!$C$70:$C$89,MATCH(C43,PARÁMETROS!$A$70:$A$89,0)) -> 7 | H43: =F43*G43 -> 49
A44: CIMENTACIÓN | B44: =INDEX(PARÁMETROS!$F$70:$F$89,MATCH(C44,PARÁMETROS!$A$70:$A$89,0)) -> Concreto | C44: Casetón EPS 1.20x0.30x0.15 | D44: =INDEX(PARÁMETROS!$B$70:$B$89,MATCH(C44,PARÁMETROS!$A$70:$A$89,0)) -> und | E44: =SUMIFS('METRADO POR NIVEL'!$M$4:$M$150,'METRADO POR NIVEL'!$A$4:$A$150,A44) -> 0 | F44: =ROUNDUP(E44,0) -> 0 | G44: =INDEX(PARÁMETROS!$C$70:$C$89,MATCH(C44,PARÁMETROS!$A$70:$A$89,0)) -> 12.9 | H44: =F44*G44 -> 0
A45: CIMENTACIÓN | B45: =INDEX(PARÁMETROS!$F$70:$F$89,MATCH(C45,PARÁMETROS!$A$70:$A$89,0)) -> Acero | C45: Varilla Ø1/4" x 9 m | D45: =INDEX(PARÁMETROS!$B$70:$B$89,MATCH(C45,PARÁMETROS!$A$70:$A$89,0)) -> und | E45: =COUNTIFS('PLAN DE CORTE'!$A$5:$A$2516,A45,'PLAN DE CORTE'!$B$5:$B$2516,"1/4") -> 0 | F45: =ROUNDUP(E45,0) -> 0 | G45: =INDEX(PARÁMETROS!$C$70:$C$89,MATCH(C45,PARÁMETROS!$A$70:$A$89,0)) -> 9.5 | H45: =F45*G45 -> 0 | I45: =F45*9*INDEX(PARÁMETROS!$B$93:$B$97,MATCH("1/4",PARÁMETROS!$A$93:$A$97,0)) -> 0 | J45: kg solo de referencia
A46: CIMENTACIÓN | B46: =INDEX(PARÁMETROS!$F$70:$F$89,MATCH(C46,PARÁMETROS!$A$70:$A$89,0)) -> Acero | C46: Varilla Ø3/8" x 9 m | D46: =INDEX(PARÁMETROS!$B$70:$B$89,MATCH(C46,PARÁMETROS!$A$70:$A$89,0)) -> und | E46: =COUNTIFS('PLAN DE CORTE'!$A$5:$A$2516,A46,'PLAN DE CORTE'!$B$5:$B$2516,"3/8") -> 49 | F46: =ROUNDUP(E46,0) -> 49 | G46: =INDEX(PARÁMETROS!$C$70:$C$89,MATCH(C46,PARÁMETROS!$A$70:$A$89,0)) -> 20.13 | H46: =F46*G46 -> 986.37 | I46: =F46*9*INDEX(PARÁMETROS!$B$93:$B$97,MATCH("3/8",PARÁMETROS!$A$93:$A$97,0)) -> 246.96 | J46: kg solo de referencia
A47: CIMENTACIÓN | B47: =INDEX(PARÁMETROS!$F$70:$F$89,MATCH(C47,PARÁMETROS!$A$70:$A$89,0)) -> Acero | C47: Varilla Ø1/2" x 9 m | D47: =INDEX(PARÁMETROS!$B$70:$B$89,MATCH(C47,PARÁMETROS!$A$70:$A$89,0)) -> und | E47: =COUNTIFS('PLAN DE CORTE'!$A$5:$A$2516,A47,'PLAN DE CORTE'!$B$5:$B$2516,"1/2") -> 6 | F47: =ROUNDUP(E47,0) -> 6 | G47: =INDEX(PARÁMETROS!$C$70:$C$89,MATCH(C47,PARÁMETROS!$A$70:$A$89,0)) -> 36.09 | H47: =F47*G47 -> 216.54 | I47: =F47*9*INDEX(PARÁMETROS!$B$93:$B$97,MATCH("1/2",PARÁMETROS!$A$93:$A$97,0)) -> 53.676 | J47: kg solo de referencia
A48: CIMENTACIÓN | B48: =INDEX(PARÁMETROS!$F$70:$F$89,MATCH(C48,PARÁMETROS!$A$70:$A$89,0)) -> Acero | C48: Varilla Ø5/8" x 9 m | D48: =INDEX(PARÁMETROS!$B$70:$B$89,MATCH(C48,PARÁMETROS!$A$70:$A$89,0)) -> und | E48: =COUNTIFS('PLAN DE CORTE'!$A$5:$A$2516,A48,'PLAN DE CORTE'!$B$5:$B$2516,"5/8") -> 61 | F48: =ROUNDUP(E48,0) -> 61 | G48: =INDEX(PARÁMETROS!$C$70:$C$89,MATCH(C48,PARÁMETROS!$A$70:$A$89,0)) -> 55.82 | H48: =F48*G48 -> 3405.02 | I48: =F48*9*INDEX(PARÁMETROS!$B$93:$B$97,MATCH("5/8",PARÁMETROS!$A$93:$A$97,0)) -> 852.048 | J48: kg solo de referencia
A49: CIMENTACIÓN | B49: =INDEX(PARÁMETROS!$F$70:$F$89,MATCH(C49,PARÁMETROS!$A$70:$A$89,0)) -> Acero | C49: Varilla Ø3/4" x 9 m | D49: =INDEX(PARÁMETROS!$B$70:$B$89,MATCH(C49,PARÁMETROS!$A$70:$A$89,0)) -> und | E49: =COUNTIFS('PLAN DE CORTE'!$A$5:$A$2516,A49,'PLAN DE CORTE'!$B$5:$B$2516,"3/4") -> 75 | F49: =ROUNDUP(E49,0) -> 75 | G49: =INDEX(PARÁMETROS!$C$70:$C$89,MATCH(C49,PARÁMETROS!$A$70:$A$89,0)) -> 82.09 | H49: =F49*G49 -> 6156.75 | I49: =F49*9*INDEX(PARÁMETROS!$B$93:$B$97,MATCH("3/4",PARÁMETROS!$A$93:$A$97,0)) -> 1508.625 | J49: kg solo de referencia
A50: CIMENTACIÓN | B50: =INDEX(PARÁMETROS!$F$70:$F$89,MATCH(C50,PARÁMETROS!$A$70:$A$89,0)) -> Acero | C50: Alambre negro N°16 | D50: =INDEX(PARÁMETROS!$B$70:$B$89,MATCH(C50,PARÁMETROS!$A$70:$A$89,0)) -> kg | E50: =SUMIFS('METRADO POR NIVEL'!$N$4:$N$150,'METRADO POR NIVEL'!$A$4:$A$150,A50) -> 71.718828 | F50: =ROUNDUP(E50,0) -> 72 | G50: =INDEX(PARÁMETROS!$C$70:$C$89,MATCH(C50,PARÁMETROS!$A$70:$A$89,0)) -> 3.65 | H50: =F50*G50 -> 262.8 | I50: =F50 -> 72 | J50: Se compra en kg
A51: CIMENTACIÓN | B51: =INDEX(PARÁMETROS!$F$70:$F$89,MATCH(C51,PARÁMETROS!$A$70:$A$89,0)) -> Acero | C51: Disco de corte 7" | D51: =INDEX(PARÁMETROS!$B$70:$B$89,MATCH(C51,PARÁMETROS!$A$70:$A$89,0)) -> und | E51: =SUMIFS('METRADO POR NIVEL'!$W$4:$W$150,'METRADO POR NIVEL'!$A$4:$A$150,A51) -> 5.02 | F51: =ROUNDUP(E51,0) -> 6 | G51: =INDEX(PARÁMETROS!$C$70:$C$89,MATCH(C51,PARÁMETROS!$A$70:$A$89,0)) -> 12 | H51: =F51*G51 -> 72
A52: CIMENTACIÓN | B52: =INDEX(PARÁMETROS!$F$70:$F$89,MATCH(C52,PARÁMETROS!$A$70:$A$89,0)) -> Acero | C52: Dados de concreto | D52: =INDEX(PARÁMETROS!$B$70:$B$89,MATCH(C52,PARÁMETROS!$A$70:$A$89,0)) -> und | E52: =SUMIFS('METRADO POR NIVEL'!$V$4:$V$150,'METRADO POR NIVEL'!$A$4:$A$150,A52) -> 211.99237 | F52: =ROUNDUP(E52,0) -> 212 | G52: =INDEX(PARÁMETROS!$C$70:$C$89,MATCH(C52,PARÁMETROS!$A$70:$A$89,0)) -> 0.5 | H52: =F52*G52 -> 106
A53: CIMENTACIÓN | B53: =INDEX(PARÁMETROS!$F$70:$F$89,MATCH(C53,PARÁMETROS!$A$70:$A$89,0)) -> Encofrado | C53: Madera tornillo | D53: =INDEX(PARÁMETROS!$B$70:$B$89,MATCH(C53,PARÁMETROS!$A$70:$A$89,0)) -> p² | E53: =SUMIFS('METRADO POR NIVEL'!$O$4:$O$150,'METRADO POR NIVEL'!$A$4:$A$150,A53) -> 37.62166 | F53: =ROUNDUP(E53,0) -> 38 | G53: =INDEX(PARÁMETROS!$C$70:$C$89,MATCH(C53,PARÁMETROS!$A$70:$A$89,0)) -> 5.5 | H53: =F53*G53 -> 209 | J53: Madera/triplay/puntales: requerido ÷ N° de usos
A54: CIMENTACIÓN | B54: =INDEX(PARÁMETROS!$F$70:$F$89,MATCH(C54,PARÁMETROS!$A$70:$A$89,0)) -> Encofrado | C54: Triplay 18 mm 1.22x2.44 | D54: =INDEX(PARÁMETROS!$B$70:$B$89,MATCH(C54,PARÁMETROS!$A$70:$A$89,0)) -> plancha | E54: =SUMIFS('METRADO POR NIVEL'!$P$4:$P$150,'METRADO POR NIVEL'!$A$4:$A$150,A54)/(1.22*2.44) -> 0 | F54: =ROUNDUP(E54,0) -> 0 | G54: =INDEX(PARÁMETROS!$C$70:$C$89,MATCH(C54,PARÁMETROS!$A$70:$A$89,0)) -> 115 | H54: =F54*G54 -> 0 | J54: Planchas de 1.22 x 2.44
A55: CIMENTACIÓN | B55: =INDEX(PARÁMETROS!$F$70:$F$89,MATCH(C55,PARÁMETROS!$A$70:$A$89,0)) -> Encofrado | C55: Puntal eucalipto 3"-4" x 3 m | D55: =INDEX(PARÁMETROS!$B$70:$B$89,MATCH(C55,PARÁMETROS!$A$70:$A$89,0)) -> und | E55: =SUMIFS('METRADO POR NIVEL'!$S$4:$S$150,'METRADO POR NIVEL'!$A$4:$A$150,A55) -> 0 | F55: =ROUNDUP(E55,0) -> 0 | G55: =INDEX(PARÁMETROS!$C$70:$C$89,MATCH(C55,PARÁMETROS!$A$70:$A$89,0)) -> 18 | H55: =F55*G55 -> 0 | J55: Madera/triplay/puntales: requerido ÷ N° de usos
A56: CIMENTACIÓN | B56: =INDEX(PARÁMETROS!$F$70:$F$89,MATCH(C56,PARÁMETROS!$A$70:$A$89,0)) -> Encofrado | C56: Clavos 3" | D56: =INDEX(PARÁMETROS!$B$70:$B$89,MATCH(C56,PARÁMETROS!$A$70:$A$89,0)) -> kg | E56: =SUMIFS('METRADO POR NIVEL'!$Q$4:$Q$150,'METRADO POR NIVEL'!$A$4:$A$150,A56) -> 6.4494274 | F56: =ROUNDUP(E56,0) -> 7 | G56: =INDEX(PARÁMETROS!$C$70:$C$89,MATCH(C56,PARÁMETROS!$A$70:$A$89,0)) -> 6.5 | H56: =F56*G56 -> 45.5
A57: CIMENTACIÓN | B57: =INDEX(PARÁMETROS!$F$70:$F$89,MATCH(C57,PARÁMETROS!$A$70:$A$89,0)) -> Encofrado | C57: Alambre negro N°8 | D57: =INDEX(PARÁMETROS!$B$70:$B$89,MATCH(C57,PARÁMETROS!$A$70:$A$89,0)) -> kg | E57: =SUMIFS('METRADO POR NIVEL'!$R$4:$R$150,'METRADO POR NIVEL'!$A$4:$A$150,A57) -> 8.5992366 | F57: =ROUNDUP(E57,0) -> 9 | G57: =INDEX(PARÁMETROS!$C$70:$C$89,MATCH(C57,PARÁMETROS!$A$70:$A$89,0)) -> 5.9 | H57: =F57*G57 -> 53.1 | I57: =F57 -> 9 | J57: Se compra en kg
A58: CIMENTACIÓN | B58: =INDEX(PARÁMETROS!$F$70:$F$89,MATCH(C58,PARÁMETROS!$A$70:$A$89,0)) -> Encofrado | C58: Desmoldante | D58: =INDEX(PARÁMETROS!$B$70:$B$89,MATCH(C58,PARÁMETROS!$A$70:$A$89,0)) -> gal | E58: =SUMIFS('METRADO POR NIVEL'!$T$4:$T$150,'METRADO POR NIVEL'!$A$4:$A$150,A58) -> 0.90877005 | F58: =ROUNDUP(E58,0) -> 1 | G58: =INDEX(PARÁMETROS!$C$70:$C$89,MATCH(C58,PARÁMETROS!$A$70:$A$89,0)) -> 45 | H58: =F58*G58 -> 45
A59: CIMENTACIÓN | B59: =INDEX(PARÁMETROS!$F$70:$F$89,MATCH(C59,PARÁMETROS!$A$70:$A$89,0)) -> Curado | C59: Curador químico (membrana) | D59: =INDEX(PARÁMETROS!$B$70:$B$89,MATCH(C59,PARÁMETROS!$A$70:$A$89,0)) -> gal | E59: =SUMIFS('METRADO POR NIVEL'!$U$4:$U$150,'METRADO POR NIVEL'!$A$4:$A$150,A59) -> 4.6845149 | F59: =ROUNDUP(E59,0) -> 5 | G59: =INDEX(PARÁMETROS!$C$70:$C$89,MATCH(C59,PARÁMETROS!$A$70:$A$89,0)) -> 40 | H59: =F59*G59 -> 200
C60: SUBTOTAL CIMENTACIÓN | H60: =SUM(H40:H59) -> 23959.08
A62: NIVEL 1
A63: Nivel | B63: Categoría | C63: Insumo | D63: Unidad de compra | E63: Cantidad requerida | F63: Cantidad a comprar | G63: Precio unitario (S/) | H63: Subtotal (S/) | I63: Peso de referencia (kg) | J63: Nota
A64: NIVEL 1 | B64: =INDEX(PARÁMETROS!$F$70:$F$89,MATCH(C64,PARÁMETROS!$A$70:$A$89,0)) -> Concreto | C64: Cemento Portland IP 42.5 kg | D64: =INDEX(PARÁMETROS!$B$70:$B$89,MATCH(C64,PARÁMETROS!$A$70:$A$89,0)) -> bolsa | E64: =SUMIFS('METRADO POR NIVEL'!$I$4:$I$150,'METRADO POR NIVEL'!$A$4:$A$150,A64) -> 122.97681 | F64: =ROUNDUP(E64,0) -> 123 | G64: =INDEX(PARÁMETROS!$C$70:$C$89,MATCH(C64,PARÁMETROS!$A$70:$A$89,0)) -> 27 | H64: =F64*G64 -> 3321
A65: NIVEL 1 | B65: =INDEX(PARÁMETROS!$F$70:$F$89,MATCH(C65,PARÁMETROS!$A$70:$A$89,0)) -> Concreto | C65: Arena gruesa | D65: =INDEX(PARÁMETROS!$B$70:$B$89,MATCH(C65,PARÁMETROS!$A$70:$A$89,0)) -> m³ | E65: =SUMIFS('METRADO POR NIVEL'!$J$4:$J$150,'METRADO POR NIVEL'!$A$4:$A$150,A65) -> 7.422731 | F65: =CEILING(E65,0.5) -> 7.5 | G65: =INDEX(PARÁMETROS!$C$70:$C$89,MATCH(C65,PARÁMETROS!$A$70:$A$89,0)) -> 70 | H65: =F65*G65 -> 525
A66: NIVEL 1 | B66: =INDEX(PARÁMETROS!$F$70:$F$89,MATCH(C66,PARÁMETROS!$A$70:$A$89,0)) -> Concreto | C66: Piedra chancada 1/2" | D66: =INDEX(PARÁMETROS!$B$70:$B$89,MATCH(C66,PARÁMETROS!$A$70:$A$89,0)) -> m³ | E66: =SUMIFS('METRADO POR NIVEL'!$K$4:$K$150,'METRADO POR NIVEL'!$A$4:$A$150,A66) -> 7.56182 | F66: =CEILING(E66,0.5) -> 8 | G66: =INDEX(PARÁMETROS!$C$70:$C$89,MATCH(C66,PARÁMETROS!$A$70:$A$89,0)) -> 80 | H66: =F66*G66 -> 640
A67: NIVEL 1 | B67: =INDEX(PARÁMETROS!$F$70:$F$89,MATCH(C67,PARÁMETROS!$A$70:$A$89,0)) -> Concreto | C67: Agua | D67: =INDEX(PARÁMETROS!$B$70:$B$89,MATCH(C67,PARÁMETROS!$A$70:$A$89,0)) -> m³ | E67: =SUMIFS('METRADO POR NIVEL'!$L$4:$L$150,'METRADO POR NIVEL'!$A$4:$A$150,A67) -> 2.5775498 | F67: =CEILING(E67,0.5) -> 3 | G67: =INDEX(PARÁMETROS!$C$70:$C$89,MATCH(C67,PARÁMETROS!$A$70:$A$89,0)) -> 7 | H67: =F67*G67 -> 21
A68: NIVEL 1 | B68: =INDEX(PARÁMETROS!$F$70:$F$89,MATCH(C68,PARÁMETROS!$A$70:$A$89,0)) -> Concreto | C68: Casetón EPS 1.20x0.30x0.15 | D68: =INDEX(PARÁMETROS!$B$70:$B$89,MATCH(C68,PARÁMETROS!$A$70:$A$89,0)) -> und | E68: =SUMIFS('METRADO POR NIVEL'!$M$4:$M$150,'METRADO POR NIVEL'!$A$4:$A$150,A68) -> 0 | F68: =ROUNDUP(E68,0) -> 0 | G68: =INDEX(PARÁMETROS!$C$70:$C$89,MATCH(C68,PARÁMETROS!$A$70:$A$89,0)) -> 12.9 | H68: =F68*G68 -> 0
A69: NIVEL 1 | B69: =INDEX(PARÁMETROS!$F$70:$F$89,MATCH(C69,PARÁMETROS!$A$70:$A$89,0)) -> Acero | C69: Varilla Ø1/4" x 9 m | D69: =INDEX(PARÁMETROS!$B$70:$B$89,MATCH(C69,PARÁMETROS!$A$70:$A$89,0)) -> und | E69: =COUNTIFS('PLAN DE CORTE'!$A$5:$A$2516,A69,'PLAN DE CORTE'!$B$5:$B$2516,"1/4") -> 0 | F69: =ROUNDUP(E69,0) -> 0 | G69: =INDEX(PARÁMETROS!$C$70:$C$89,MATCH(C69,PARÁMETROS!$A$70:$A$89,0)) -> 9.5 | H69: =F69*G69 -> 0 | I69: =F69*9*INDEX(PARÁMETROS!$B$93:$B$97,MATCH("1/4",PARÁMETROS!$A$93:$A$97,0)) -> 0 | J69: kg solo de referencia
A70: NIVEL 1 | B70: =INDEX(PARÁMETROS!$F$70:$F$89,MATCH(C70,PARÁMETROS!$A$70:$A$89,0)) -> Acero | C70: Varilla Ø3/8" x 9 m | D70: =INDEX(PARÁMETROS!$B$70:$B$89,MATCH(C70,PARÁMETROS!$A$70:$A$89,0)) -> und | E70: =COUNTIFS('PLAN DE CORTE'!$A$5:$A$2516,A70,'PLAN DE CORTE'!$B$5:$B$2516,"3/8") -> 84 | F70: =ROUNDUP(E70,0) -> 84 | G70: =INDEX(PARÁMETROS!$C$70:$C$89,MATCH(C70,PARÁMETROS!$A$70:$A$89,0)) -> 20.13 | H70: =F70*G70 -> 1690.92 | I70: =F70*9*INDEX(PARÁMETROS!$B$93:$B$97,MATCH("3/8",PARÁMETROS!$A$93:$A$97,0)) -> 423.36 | J70: kg solo de referencia
A71: NIVEL 1 | B71: =INDEX(PARÁMETROS!$F$70:$F$89,MATCH(C71,PARÁMETROS!$A$70:$A$89,0)) -> Acero | C71: Varilla Ø1/2" x 9 m | D71: =INDEX(PARÁMETROS!$B$70:$B$89,MATCH(C71,PARÁMETROS!$A$70:$A$89,0)) -> und | E71: =COUNTIFS('PLAN DE CORTE'!$A$5:$A$2516,A71,'PLAN DE CORTE'!$B$5:$B$2516,"1/2") -> 10 | F71: =ROUNDUP(E71,0) -> 10 | G71: =INDEX(PARÁMETROS!$C$70:$C$89,MATCH(C71,PARÁMETROS!$A$70:$A$89,0)) -> 36.09 | H71: =F71*G71 -> 360.9 | I71: =F71*9*INDEX(PARÁMETROS!$B$93:$B$97,MATCH("1/2",PARÁMETROS!$A$93:$A$97,0)) -> 89.46 | J71: kg solo de referencia
A72: NIVEL 1 | B72: =INDEX(PARÁMETROS!$F$70:$F$89,MATCH(C72,PARÁMETROS!$A$70:$A$89,0)) -> Acero | C72: Varilla Ø5/8" x 9 m | D72: =INDEX(PARÁMETROS!$B$70:$B$89,MATCH(C72,PARÁMETROS!$A$70:$A$89,0)) -> und | E72: =COUNTIFS('PLAN DE CORTE'!$A$5:$A$2516,A72,'PLAN DE CORTE'!$B$5:$B$2516,"5/8") -> 68 | F72: =ROUNDUP(E72,0) -> 68 | G72: =INDEX(PARÁMETROS!$C$70:$C$89,MATCH(C72,PARÁMETROS!$A$70:$A$89,0)) -> 55.82 | H72: =F72*G72 -> 3795.76 | I72: =F72*9*INDEX(PARÁMETROS!$B$93:$B$97,MATCH("5/8",PARÁMETROS!$A$93:$A$97,0)) -> 949.824 | J72: kg solo de referencia
A73: NIVEL 1 | B73: =INDEX(PARÁMETROS!$F$70:$F$89,MATCH(C73,PARÁMETROS!$A$70:$A$89,0)) -> Acero | C73: Varilla Ø3/4" x 9 m | D73: =INDEX(PARÁMETROS!$B$70:$B$89,MATCH(C73,PARÁMETROS!$A$70:$A$89,0)) -> und | E73: =COUNTIFS('PLAN DE CORTE'!$A$5:$A$2516,A73,'PLAN DE CORTE'!$B$5:$B$2516,"3/4") -> 0 | F73: =ROUNDUP(E73,0) -> 0 | G73: =INDEX(PARÁMETROS!$C$70:$C$89,MATCH(C73,PARÁMETROS!$A$70:$A$89,0)) -> 82.09 | H73: =F73*G73 -> 0 | I73: =F73*9*INDEX(PARÁMETROS!$B$93:$B$97,MATCH("3/4",PARÁMETROS!$A$93:$A$97,0)) -> 0 | J73: kg solo de referencia
A74: NIVEL 1 | B74: =INDEX(PARÁMETROS!$F$70:$F$89,MATCH(C74,PARÁMETROS!$A$70:$A$89,0)) -> Acero | C74: Alambre negro N°16 | D74: =INDEX(PARÁMETROS!$B$70:$B$89,MATCH(C74,PARÁMETROS!$A$70:$A$89,0)) -> kg | E74: =SUMIFS('METRADO POR NIVEL'!$N$4:$N$150,'METRADO POR NIVEL'!$A$4:$A$150,A74) -> 38.564959 | F74: =ROUNDUP(E74,0) -> 39 | G74: =INDEX(PARÁMETROS!$C$70:$C$89,MATCH(C74,PARÁMETROS!$A$70:$A$89,0)) -> 3.65 | H74: =F74*G74 -> 142.35 | I74: =F74 -> 39 | J74: Se compra en kg
A75: NIVEL 1 | B75: =INDEX(PARÁMETROS!$F$70:$F$89,MATCH(C75,PARÁMETROS!$A$70:$A$89,0)) -> Acero | C75: Disco de corte 7" | D75: =INDEX(PARÁMETROS!$B$70:$B$89,MATCH(C75,PARÁMETROS!$A$70:$A$89,0)) -> und | E75: =SUMIFS('METRADO POR NIVEL'!$W$4:$W$150,'METRADO POR NIVEL'!$A$4:$A$150,A75) -> 6.12 | F75: =ROUNDUP(E75,0) -> 7 | G75: =INDEX(PARÁMETROS!$C$70:$C$89,MATCH(C75,PARÁMETROS!$A$70:$A$89,0)) -> 12 | H75: =F75*G75 -> 84
A76: NIVEL 1 | B76: =INDEX(PARÁMETROS!$F$70:$F$89,MATCH(C76,PARÁMETROS!$A$70:$A$89,0)) -> Acero | C76: Dados de concreto | D76: =INDEX(PARÁMETROS!$B$70:$B$89,MATCH(C76,PARÁMETROS!$A$70:$A$89,0)) -> und | E76: =SUMIFS('METRADO POR NIVEL'!$V$4:$V$150,'METRADO POR NIVEL'!$A$4:$A$150,A76) -> 69.384169 | F76: =ROUNDUP(E76,0) -> 70 | G76: =INDEX(PARÁMETROS!$C$70:$C$89,MATCH(C76,PARÁMETROS!$A$70:$A$89,0)) -> 0.5 | H76: =F76*G76 -> 35
A77: NIVEL 1 | B77: =INDEX(PARÁMETROS!$F$70:$F$89,MATCH(C77,PARÁMETROS!$A$70:$A$89,0)) -> Encofrado | C77: Madera tornillo | D77: =INDEX(PARÁMETROS!$B$70:$B$89,MATCH(C77,PARÁMETROS!$A$70:$A$89,0)) -> p² | E77: =SUMIFS('METRADO POR NIVEL'!$O$4:$O$150,'METRADO POR NIVEL'!$A$4:$A$150,A77) -> 26.019063 | F77: =ROUNDUP(E77,0) -> 27 | G77: =INDEX(PARÁMETROS!$C$70:$C$89,MATCH(C77,PARÁMETROS!$A$70:$A$89,0)) -> 5.5 | H77: =F77*G77 -> 148.5 | J77: Madera/triplay/puntales: requerido ÷ N° de usos
A78: NIVEL 1 | B78: =INDEX(PARÁMETROS!$F$70:$F$89,MATCH(C78,PARÁMETROS!$A$70:$A$89,0)) -> Encofrado | C78: Triplay 18 mm 1.22x2.44 | D78: =INDEX(PARÁMETROS!$B$70:$B$89,MATCH(C78,PARÁMETROS!$A$70:$A$89,0)) -> plancha | E78: =SUMIFS('METRADO POR NIVEL'!$P$4:$P$150,'METRADO POR NIVEL'!$A$4:$A$150,A78)/(1.22*2.44) -> 2.4473723 | F78: =ROUNDUP(E78,0) -> 3 | G78: =INDEX(PARÁMETROS!$C$70:$C$89,MATCH(C78,PARÁMETROS!$A$70:$A$89,0)) -> 115 | H78: =F78*G78 -> 345 | J78: Planchas de 1.22 x 2.44
A79: NIVEL 1 | B79: =INDEX(PARÁMETROS!$F$70:$F$89,MATCH(C79,PARÁMETROS!$A$70:$A$89,0)) -> Encofrado | C79: Puntal eucalipto 3"-4" x 3 m | D79: =INDEX(PARÁMETROS!$B$70:$B$89,MATCH(C79,PARÁMETROS!$A$70:$A$89,0)) -> und | E79: =SUMIFS('METRADO POR NIVEL'!$S$4:$S$150,'METRADO POR NIVEL'!$A$4:$A$150,A79) -> 0 | F79: =ROUNDUP(E79,0) -> 0 | G79: =INDEX(PARÁMETROS!$C$70:$C$89,MATCH(C79,PARÁMETROS!$A$70:$A$89,0)) -> 18 | H79: =F79*G79 -> 0 | J79: Madera/triplay/puntales: requerido ÷ N° de usos
A80: NIVEL 1 | B80: =INDEX(PARÁMETROS!$F$70:$F$89,MATCH(C80,PARÁMETROS!$A$70:$A$89,0)) -> Encofrado | C80: Clavos 3" | D80: =INDEX(PARÁMETROS!$B$70:$B$89,MATCH(C80,PARÁMETROS!$A$70:$A$89,0)) -> kg | E80: =SUMIFS('METRADO POR NIVEL'!$Q$4:$Q$150,'METRADO POR NIVEL'!$A$4:$A$150,A80) -> 5.2038127 | F80: =ROUNDUP(E80,0) -> 6 | G80: =INDEX(PARÁMETROS!$C$70:$C$89,MATCH(C80,PARÁMETROS!$A$70:$A$89,0)) -> 6.5 | H80: =F80*G80 -> 39
A81: NIVEL 1 | B81: =INDEX(PARÁMETROS!$F$70:$F$89,MATCH(C81,PARÁMETROS!$A$70:$A$89,0)) -> Encofrado | C81: Alambre negro N°8 | D81: =INDEX(PARÁMETROS!$B$70:$B$89,MATCH(C81,PARÁMETROS!$A$70:$A$89,0)) -> kg | E81: =SUMIFS('METRADO POR NIVEL'!$R$4:$R$150,'METRADO POR NIVEL'!$A$4:$A$150,A81) -> 8.6730212 | F81: =ROUNDUP(E81,0) -> 9 | G81: =INDEX(PARÁMETROS!$C$70:$C$89,MATCH(C81,PARÁMETROS!$A$70:$A$89,0)) -> 5.9 | H81: =F81*G81 -> 53.1 | I81: =F81 -> 9 | J81: Se compra en kg
A82: NIVEL 1 | B82: =INDEX(PARÁMETROS!$F$70:$F$89,MATCH(C82,PARÁMETROS!$A$70:$A$89,0)) -> Encofrado | C82: Desmoldante | D82: =INDEX(PARÁMETROS!$B$70:$B$89,MATCH(C82,PARÁMETROS!$A$70:$A$89,0)) -> gal | E82: =SUMIFS('METRADO POR NIVEL'!$T$4:$T$150,'METRADO POR NIVEL'!$A$4:$A$150,A82) -> 0.7332541 | F82: =ROUNDUP(E82,0) -> 1 | G82: =INDEX(PARÁMETROS!$C$70:$C$89,MATCH(C82,PARÁMETROS!$A$70:$A$89,0)) -> 45 | H82: =F82*G82 -> 45
A83: NIVEL 1 | B83: =INDEX(PARÁMETROS!$F$70:$F$89,MATCH(C83,PARÁMETROS!$A$70:$A$89,0)) -> Curado | C83: Curador químico (membrana) | D83: =INDEX(PARÁMETROS!$B$70:$B$89,MATCH(C83,PARÁMETROS!$A$70:$A$89,0)) -> gal | E83: =SUMIFS('METRADO POR NIVEL'!$U$4:$U$150,'METRADO POR NIVEL'!$A$4:$A$150,A83) -> 6.4471819 | F83: =ROUNDUP(E83,0) -> 7 | G83: =INDEX(PARÁMETROS!$C$70:$C$89,MATCH(C83,PARÁMETROS!$A$70:$A$89,0)) -> 40 | H83: =F83*G83 -> 280
C84: SUBTOTAL NIVEL 1 | H84: =SUM(H64:H83) -> 11526.53
A86: NIVEL 2
A87: Nivel | B87: Categoría | C87: Insumo | D87: Unidad de compra | E87: Cantidad requerida | F87: Cantidad a comprar | G87: Precio unitario (S/) | H87: Subtotal (S/) | I87: Peso de referencia (kg) | J87: Nota
A88: NIVEL 2 | B88: =INDEX(PARÁMETROS!$F$70:$F$89,MATCH(C88,PARÁMETROS!$A$70:$A$89,0)) -> Concreto | C88: Cemento Portland IP 42.5 kg | D88: =INDEX(PARÁMETROS!$B$70:$B$89,MATCH(C88,PARÁMETROS!$A$70:$A$89,0)) -> bolsa | E88: =SUMIFS('METRADO POR NIVEL'!$I$4:$I$150,'METRADO POR NIVEL'!$A$4:$A$150,A88) -> 288.21129 | F88: =ROUNDUP(E88,0) -> 289 | G88: =INDEX(PARÁMETROS!$C$70:$C$89,MATCH(C88,PARÁMETROS!$A$70:$A$89,0)) -> 27 | H88: =F88*G88 -> 7803
A89: NIVEL 2 | B89: =INDEX(PARÁMETROS!$F$70:$F$89,MATCH(C89,PARÁMETROS!$A$70:$A$89,0)) -> Concreto | C89: Arena gruesa | D89: =INDEX(PARÁMETROS!$B$70:$B$89,MATCH(C89,PARÁMETROS!$A$70:$A$89,0)) -> m³ | E89: =SUMIFS('METRADO POR NIVEL'!$J$4:$J$150,'METRADO POR NIVEL'!$A$4:$A$150,A89) -> 15.402865 | F89: =CEILING(E89,0.5) -> 15.5 | G89: =INDEX(PARÁMETROS!$C$70:$C$89,MATCH(C89,PARÁMETROS!$A$70:$A$89,0)) -> 70 | H89: =F89*G89 -> 1085
A90: NIVEL 2 | B90: =INDEX(PARÁMETROS!$F$70:$F$89,MATCH(C90,PARÁMETROS!$A$70:$A$89,0)) -> Concreto | C90: Piedra chancada 1/2" | D90: =INDEX(PARÁMETROS!$B$70:$B$89,MATCH(C90,PARÁMETROS!$A$70:$A$89,0)) -> m³ | E90: =SUMIFS('METRADO POR NIVEL'!$K$4:$K$150,'METRADO POR NIVEL'!$A$4:$A$150,A90) -> 15.699074 | F90: =CEILING(E90,0.5) -> 16 | G90: =INDEX(PARÁMETROS!$C$70:$C$89,MATCH(C90,PARÁMETROS!$A$70:$A$89,0)) -> 80 | H90: =F90*G90 -> 1280
A91: NIVEL 2 | B91: =INDEX(PARÁMETROS!$F$70:$F$89,MATCH(C91,PARÁMETROS!$A$70:$A$89,0)) -> Concreto | C91: Agua | D91: =INDEX(PARÁMETROS!$B$70:$B$89,MATCH(C91,PARÁMETROS!$A$70:$A$89,0)) -> m³ | E91: =SUMIFS('METRADO POR NIVEL'!$L$4:$L$150,'METRADO POR NIVEL'!$A$4:$A$150,A91) -> 5.5094862 | F91: =CEILING(E91,0.5) -> 6 | G91: =INDEX(PARÁMETROS!$C$70:$C$89,MATCH(C91,PARÁMETROS!$A$70:$A$89,0)) -> 7 | H91: =F91*G91 -> 42
A92: NIVEL 2 | B92: =INDEX(PARÁMETROS!$F$70:$F$89,MATCH(C92,PARÁMETROS!$A$70:$A$89,0)) -> Concreto | C92: Casetón EPS 1.20x0.30x0.15 | D92: =INDEX(PARÁMETROS!$B$70:$B$89,MATCH(C92,PARÁMETROS!$A$70:$A$89,0)) -> und | E92: =SUMIFS('METRADO POR NIVEL'!$M$4:$M$150,'METRADO POR NIVEL'!$A$4:$A$150,A92) -> 149.08392 | F92: =ROUNDUP(E92,0) -> 150 | G92: =INDEX(PARÁMETROS!$C$70:$C$89,MATCH(C92,PARÁMETROS!$A$70:$A$89,0)) -> 12.9 | H92: =F92*G92 -> 1935
A93: NIVEL 2 | B93: =INDEX(PARÁMETROS!$F$70:$F$89,MATCH(C93,PARÁMETROS!$A$70:$A$89,0)) -> Acero | C93: Varilla Ø1/4" x 9 m | D93: =INDEX(PARÁMETROS!$B$70:$B$89,MATCH(C93,PARÁMETROS!$A$70:$A$89,0)) -> und | E93: =COUNTIFS('PLAN DE CORTE'!$A$5:$A$2516,A93,'PLAN DE CORTE'!$B$5:$B$2516,"1/4") -> 110 | F93: =ROUNDUP(E93,0) -> 110 | G93: =INDEX(PARÁMETROS!$C$70:$C$89,MATCH(C93,PARÁMETROS!$A$70:$A$89,0)) -> 9.5 | H93: =F93*G93 -> 1045 | I93: =F93*9*INDEX(PARÁMETROS!$B$93:$B$97,MATCH("1/4",PARÁMETROS!$A$93:$A$97,0)) -> 247.5 | J93: kg solo de referencia
A94: NIVEL 2 | B94: =INDEX(PARÁMETROS!$F$70:$F$89,MATCH(C94,PARÁMETROS!$A$70:$A$89,0)) -> Acero | C94: Varilla Ø3/8" x 9 m | D94: =INDEX(PARÁMETROS!$B$70:$B$89,MATCH(C94,PARÁMETROS!$A$70:$A$89,0)) -> und | E94: =COUNTIFS('PLAN DE CORTE'!$A$5:$A$2516,A94,'PLAN DE CORTE'!$B$5:$B$2516,"3/8") -> 278 | F94: =ROUNDUP(E94,0) -> 278 | G94: =INDEX(PARÁMETROS!$C$70:$C$89,MATCH(C94,PARÁMETROS!$A$70:$A$89,0)) -> 20.13 | H94: =F94*G94 -> 5596.14 | I94: =F94*9*INDEX(PARÁMETROS!$B$93:$B$97,MATCH("3/8",PARÁMETROS!$A$93:$A$97,0)) -> 1401.12 | J94: kg solo de referencia
A95: NIVEL 2 | B95: =INDEX(PARÁMETROS!$F$70:$F$89,MATCH(C95,PARÁMETROS!$A$70:$A$89,0)) -> Acero | C95: Varilla Ø1/2" x 9 m | D95: =INDEX(PARÁMETROS!$B$70:$B$89,MATCH(C95,PARÁMETROS!$A$70:$A$89,0)) -> und | E95: =COUNTIFS('PLAN DE CORTE'!$A$5:$A$2516,A95,'PLAN DE CORTE'!$B$5:$B$2516,"1/2") -> 42 | F95: =ROUNDUP(E95,0) -> 42 | G95: =INDEX(PARÁMETROS!$C$70:$C$89,MATCH(C95,PARÁMETROS!$A$70:$A$89,0)) -> 36.09 | H95: =F95*G95 -> 1515.78 | I95: =F95*9*INDEX(PARÁMETROS!$B$93:$B$97,MATCH("1/2",PARÁMETROS!$A$93:$A$97,0)) -> 375.732 | J95: kg solo de referencia
A96: NIVEL 2 | B96: =INDEX(PARÁMETROS!$F$70:$F$89,MATCH(C96,PARÁMETROS!$A$70:$A$89,0)) -> Acero | C96: Varilla Ø5/8" x 9 m | D96: =INDEX(PARÁMETROS!$B$70:$B$89,MATCH(C96,PARÁMETROS!$A$70:$A$89,0)) -> und | E96: =COUNTIFS('PLAN DE CORTE'!$A$5:$A$2516,A96,'PLAN DE CORTE'!$B$5:$B$2516,"5/8") -> 71 | F96: =ROUNDUP(E96,0) -> 71 | G96: =INDEX(PARÁMETROS!$C$70:$C$89,MATCH(C96,PARÁMETROS!$A$70:$A$89,0)) -> 55.82 | H96: =F96*G96 -> 3963.22 | I96: =F96*9*INDEX(PARÁMETROS!$B$93:$B$97,MATCH("5/8",PARÁMETROS!$A$93:$A$97,0)) -> 991.728 | J96: kg solo de referencia
A97: NIVEL 2 | B97: =INDEX(PARÁMETROS!$F$70:$F$89,MATCH(C97,PARÁMETROS!$A$70:$A$89,0)) -> Acero | C97: Varilla Ø3/4" x 9 m | D97: =INDEX(PARÁMETROS!$B$70:$B$89,MATCH(C97,PARÁMETROS!$A$70:$A$89,0)) -> und | E97: =COUNTIFS('PLAN DE CORTE'!$A$5:$A$2516,A97,'PLAN DE CORTE'!$B$5:$B$2516,"3/4") -> 90 | F97: =ROUNDUP(E97,0) -> 90 | G97: =INDEX(PARÁMETROS!$C$70:$C$89,MATCH(C97,PARÁMETROS!$A$70:$A$89,0)) -> 82.09 | H97: =F97*G97 -> 7388.1 | I97: =F97*9*INDEX(PARÁMETROS!$B$93:$B$97,MATCH("3/4",PARÁMETROS!$A$93:$A$97,0)) -> 1810.35 | J97: kg solo de referencia
A98: NIVEL 2 | B98: =INDEX(PARÁMETROS!$F$70:$F$89,MATCH(C98,PARÁMETROS!$A$70:$A$89,0)) -> Acero | C98: Alambre negro N°16 | D98: =INDEX(PARÁMETROS!$B$70:$B$89,MATCH(C98,PARÁMETROS!$A$70:$A$89,0)) -> kg | E98: =SUMIFS('METRADO POR NIVEL'!$N$4:$N$150,'METRADO POR NIVEL'!$A$4:$A$150,A98) -> 129.60235 | F98: =ROUNDUP(E98,0) -> 130 | G98: =INDEX(PARÁMETROS!$C$70:$C$89,MATCH(C98,PARÁMETROS!$A$70:$A$89,0)) -> 3.65 | H98: =F98*G98 -> 474.5 | I98: =F98 -> 130 | J98: Se compra en kg
A99: NIVEL 2 | B99: =INDEX(PARÁMETROS!$F$70:$F$89,MATCH(C99,PARÁMETROS!$A$70:$A$89,0)) -> Acero | C99: Disco de corte 7" | D99: =INDEX(PARÁMETROS!$B$70:$B$89,MATCH(C99,PARÁMETROS!$A$70:$A$89,0)) -> und | E99: =SUMIFS('METRADO POR NIVEL'!$W$4:$W$150,'METRADO POR NIVEL'!$A$4:$A$150,A99) -> 18.066667 | F99: =ROUNDUP(E99,0) -> 19 | G99: =INDEX(PARÁMETROS!$C$70:$C$89,MATCH(C99,PARÁMETROS!$A$70:$A$89,0)) -> 12 | H99: =F99*G99 -> 228
A100: NIVEL 2 | B100: =INDEX(PARÁMETROS!$F$70:$F$89,MATCH(C100,PARÁMETROS!$A$70:$A$89,0)) -> Acero | C100: Dados de concreto | D100: =INDEX(PARÁMETROS!$B$70:$B$89,MATCH(C100,PARÁMETROS!$A$70:$A$89,0)) -> und | E100: =SUMIFS('METRADO POR NIVEL'!$V$4:$V$150,'METRADO POR NIVEL'!$A$4:$A$150,A100) -> 524.88296 | F100: =ROUNDUP(E100,0) -> 525 | G100: =INDEX(PARÁMETROS!$C$70:$C$89,MATCH(C100,PARÁMETROS!$A$70:$A$89,0)) -> 0.5 | H100: =F100*G100 -> 262.5
A101: NIVEL 2 | B101: =INDEX(PARÁMETROS!$F$70:$F$89,MATCH(C101,PARÁMETROS!$A$70:$A$89,0)) -> Encofrado | C101: Madera tornillo | D101: =INDEX(PARÁMETROS!$B$70:$B$89,MATCH(C101,PARÁMETROS!$A$70:$A$89,0)) -> p² | E101: =SUMIFS('METRADO POR NIVEL'!$O$4:$O$150,'METRADO POR NIVEL'!$A$4:$A$150,A101) -> 176.66354 | F101: =ROUNDUP(E101,0) -> 177 | G101: =INDEX(PARÁMETROS!$C$70:$C$89,MATCH(C101,PARÁMETROS!$A$70:$A$89,0)) -> 5.5 | H101: =F101*G101 -> 973.5 | J101: Madera/triplay/puntales: requerido ÷ N° de usos
A102: NIVEL 2 | B102: =INDEX(PARÁMETROS!$F$70:$F$89,MATCH(C102,PARÁMETROS!$A$70:$A$89,0)) -> Encofrado | C102: Triplay 18 mm 1.22x2.44 | D102: =INDEX(PARÁMETROS!$B$70:$B$89,MATCH(C102,PARÁMETROS!$A$70:$A$89,0)) -> plancha | E102: =SUMIFS('METRADO POR NIVEL'!$P$4:$P$150,'METRADO POR NIVEL'!$A$4:$A$150,A102)/(1.22*2.44) -> 15.744488 | F102: =ROUNDUP(E102,0) -> 16 | G102: =INDEX(PARÁMETROS!$C$70:$C$89,MATCH(C102,PARÁMETROS!$A$70:$A$89,0)) -> 115 | H102: =F102*G102 -> 1840 | J102: Planchas de 1.22 x 2.44
A103: NIVEL 2 | B103: =INDEX(PARÁMETROS!$F$70:$F$89,MATCH(C103,PARÁMETROS!$A$70:$A$89,0)) -> Encofrado | C103: Puntal eucalipto 3"-4" x 3 m | D103: =INDEX(PARÁMETROS!$B$70:$B$89,MATCH(C103,PARÁMETROS!$A$70:$A$89,0)) -> und | E103: =SUMIFS('METRADO POR NIVEL'!$S$4:$S$150,'METRADO POR NIVEL'!$A$4:$A$150,A103) -> 18.751951 | F103: =ROUNDUP(E103,0) -> 19 | G103: =INDEX(PARÁMETROS!$C$70:$C$89,MATCH(C103,PARÁMETROS!$A$70:$A$89,0)) -> 18 | H103: =F103*G103 -> 342 | J103: Madera/triplay/puntales: requerido ÷ N° de usos
A104: NIVEL 2 | B104: =INDEX(PARÁMETROS!$F$70:$F$89,MATCH(C104,PARÁMETROS!$A$70:$A$89,0)) -> Encofrado | C104: Clavos 3" | D104: =INDEX(PARÁMETROS!$B$70:$B$89,MATCH(C104,PARÁMETROS!$A$70:$A$89,0)) -> kg | E104: =SUMIFS('METRADO POR NIVEL'!$Q$4:$Q$150,'METRADO POR NIVEL'!$A$4:$A$150,A104) -> 36.001933 | F104: =ROUNDUP(E104,0) -> 37 | G104: =INDEX(PARÁMETROS!$C$70:$C$89,MATCH(C104,PARÁMETROS!$A$70:$A$89,0)) -> 6.5 | H104: =F104*G104 -> 240.5
A105: NIVEL 2 | B105: =INDEX(PARÁMETROS!$F$70:$F$89,MATCH(C105,PARÁMETROS!$A$70:$A$89,0)) -> Encofrado | C105: Alambre negro N°8 | D105: =INDEX(PARÁMETROS!$B$70:$B$89,MATCH(C105,PARÁMETROS!$A$70:$A$89,0)) -> kg | E105: =SUMIFS('METRADO POR NIVEL'!$R$4:$R$150,'METRADO POR NIVEL'!$A$4:$A$150,A105) -> 50.671335 | F105: =ROUNDUP(E105,0) -> 51 | G105: =INDEX(PARÁMETROS!$C$70:$C$89,MATCH(C105,PARÁMETROS!$A$70:$A$89,0)) -> 5.9 | H105: =F105*G105 -> 300.9 | I105: =F105 -> 51 | J105: Se compra en kg
A106: NIVEL 2 | B106: =INDEX(PARÁMETROS!$F$70:$F$89,MATCH(C106,PARÁMETROS!$A$70:$A$89,0)) -> Encofrado | C106: Desmoldante | D106: =INDEX(PARÁMETROS!$B$70:$B$89,MATCH(C106,PARÁMETROS!$A$70:$A$89,0)) -> gal | E106: =SUMIFS('METRADO POR NIVEL'!$T$4:$T$150,'METRADO POR NIVEL'!$A$4:$A$150,A106) -> 5.0167526 | F106: =ROUNDUP(E106,0) -> 6 | G106: =INDEX(PARÁMETROS!$C$70:$C$89,MATCH(C106,PARÁMETROS!$A$70:$A$89,0)) -> 45 | H106: =F106*G106 -> 270
A107: NIVEL 2 | B107: =INDEX(PARÁMETROS!$F$70:$F$89,MATCH(C107,PARÁMETROS!$A$70:$A$89,0)) -> Curado | C107: Curador químico (membrana) | D107: =INDEX(PARÁMETROS!$B$70:$B$89,MATCH(C107,PARÁMETROS!$A$70:$A$89,0)) -> gal | E107: =SUMIFS('METRADO POR NIVEL'!$U$4:$U$150,'METRADO POR NIVEL'!$A$4:$A$150,A107) -> 12.482453 | F107: =ROUNDUP(E107,0) -> 13 | G107: =INDEX(PARÁMETROS!$C$70:$C$89,MATCH(C107,PARÁMETROS!$A$70:$A$89,0)) -> 40 | H107: =F107*G107 -> 520
C108: SUBTOTAL NIVEL 2 | H108: =SUM(H88:H107) -> 37105.14
A110: NIVEL 3
A111: Nivel | B111: Categoría | C111: Insumo | D111: Unidad de compra | E111: Cantidad requerida | F111: Cantidad a comprar | G111: Precio unitario (S/) | H111: Subtotal (S/) | I111: Peso de referencia (kg) | J111: Nota
A112: NIVEL 3 | B112: =INDEX(PARÁMETROS!$F$70:$F$89,MATCH(C112,PARÁMETROS!$A$70:$A$89,0)) -> Concreto | C112: Cemento Portland IP 42.5 kg | D112: =INDEX(PARÁMETROS!$B$70:$B$89,MATCH(C112,PARÁMETROS!$A$70:$A$89,0)) -> bolsa | E112: =SUMIFS('METRADO POR NIVEL'!$I$4:$I$150,'METRADO POR NIVEL'!$A$4:$A$150,A112) -> 267.03159 | F112: =ROUNDUP(E112,0) -> 268 | G112: =INDEX(PARÁMETROS!$C$70:$C$89,MATCH(C112,PARÁMETROS!$A$70:$A$89,0)) -> 27 | H112: =F112*G112 -> 7236
A113: NIVEL 3 | B113: =INDEX(PARÁMETROS!$F$70:$F$89,MATCH(C113,PARÁMETROS!$A$70:$A$89,0)) -> Concreto | C113: Arena gruesa | D113: =INDEX(PARÁMETROS!$B$70:$B$89,MATCH(C113,PARÁMETROS!$A$70:$A$89,0)) -> m³ | E113: =SUMIFS('METRADO POR NIVEL'!$J$4:$J$150,'METRADO POR NIVEL'!$A$4:$A$150,A113) -> 14.270958 | F113: =CEILING(E113,0.5) -> 14.5 | G113: =INDEX(PARÁMETROS!$C$70:$C$89,MATCH(C113,PARÁMETROS!$A$70:$A$89,0)) -> 70 | H113: =F113*G113 -> 1015
...

Sheet CRONOGRAMA
A1: CRONOGRAMA PROGRAMADO - PARTIDAS POR NIVEL (peso % por costo)
A2: Duraciones editables (días calendario). Secuencia: acero → encofrado (desfase) → concreto → curado; el siguiente nivel inicia al terminar el concreto.
L3: Curva S: fracción programada por semana (fin de semana)
L4: 1 | M4: 2 | N4: 3 | O4: 4 | P4: 5 | Q4: 6 | R4: 7 | S4: 8 | T4: 9 | U4: 10 | V4: 11 | W4: 12 | X4: 13 | Y4: 14 | Z4: 15 | AA4: 16 | AB4: 17 | AC4: 18 | AD4: 19 | AE4: 20 | AF4: 21 | AG4: 22 | AH4: 23 | AI4: 24 | AJ4: 25 | AK4: 26
A5: N° | B5: Nivel | C5: Partida | D5: Costo (S/) | E5: Peso (%) | F5: Duración (días) | G5: Inicio | H5: Fin | I5: % programado a la fecha de corte | J5: % ejecutado a la fecha de corte | L5: =PARÁMETROS!$B$6+7*1-1 -> 46306 | M5: =PARÁMETROS!$B$6+7*2-1 -> 46313 | N5: =PARÁMETROS!$B$6+7*3-1 -> 46320 | O5: =PARÁMETROS!$B$6+7*4-1 -> 46327 | P5: =PARÁMETROS!$B$6+7*5-1 -> 46334 | Q5: =PARÁMETROS!$B$6+7*6-1 -> 46341 | R5: =PARÁMETROS!$B$6+7*7-1 -> 46348 | S5: =PARÁMETROS!$B$6+7*8-1 -> 46355 | T5: =PARÁMETROS!$B$6+7*9-1 -> 46362 | U5: =PARÁMETROS!$B$6+7*10-1 -> 46369 | V5: =PARÁMETROS!$B$6+7*11-1 -> 46376 | W5: =PARÁMETROS!$B$6+7*12-1 -> 46383 | X5: =PARÁMETROS!$B$6+7*13-1 -> 46390 | Y5: =PARÁMETROS!$B$6+7*14-1 -> 46397 | Z5: =PARÁMETROS!$B$6+7*15-1 -> 46404 | AA5: =PARÁMETROS!$B$6+7*16-1 -> 46411 | AB5: =PARÁMETROS!$B$6+7*17-1 -> 46418 | AC5: =PARÁMETROS!$B$6+7*18-1 -> 46425 | AD5: =PARÁMETROS!$B$6+7*19-1 -> 46432 | AE5: =PARÁMETROS!$B$6+7*20-1 -> 46439 | AF5: =PARÁMETROS!$B$6+7*21-1 -> 46446 | AG5: =PARÁMETROS!$B$6+7*22-1 -> 46453 | AH5: =PARÁMETROS!$B$6+7*23-1 -> 46460 | AI5: =PARÁMETROS!$B$6+7*24-1 -> 46467 | AJ5: =PARÁMETROS!$B$6+7*25-1 -> 46474 | AK5: =PARÁMETROS!$B$6+7*26-1 -> 46481
A6: 1 | B6: CIMENTACIÓN | C6: Acero | D6: =INDEX('LISTA DE COMPRAS'!$B$30:$E$35,MATCH(B6,'LISTA DE COMPRAS'!$A$30:$A$35,0),MATCH(C6,'LISTA DE COMPRAS'!$B$29:$E$29,0)) -> 11205.48 | E6: =IF($D$30>0,D6/$D$30,0) -> 0.065566001 | F6: 8 | G6: =PARÁMETROS!$B$6 -> 46300 | H6: =G6+F6-1 -> 46307 | I6: =MAX(0,MIN(1,(PARÁMETROS!$B$7-G6+1)/(H6-G6+1))) -> 0.125 | J6: =_xlfn.MAXIFS('AVANCE REAL'!$E$6:$E$405,'AVANCE REAL'!$C$6:$C$405,B6,'AVANCE REAL'!$D$6:$D$405,C6,'AVANCE REAL'!$A$6:$A$405,"<="&PARÁMETROS!$B$7) -> 0 | L6: =MAX(0,MIN(1,(L$5-$G6+1)/($H6-$G6+1))) -> 0.875 | M6: =MAX(0,MIN(1,(M$5-$G6+1)/($H6-$G6+1))) -> 1 | N6: =MAX(0,MIN(1,(N$5-$G6+1)/($H6-$G6+1))) -> 1 | O6: =MAX(0,MIN(1,(O$5-$G6+1)/($H6-$G6+1))) -> 1 | P6: =MAX(0,MIN(1,(P$5-$G6+1)/($H6-$G6+1))) -> 1 | Q6: =MAX(0,MIN(1,(Q$5-$G6+1)/($H6-$G6+1))) -> 1 | R6: =MAX(0,MIN(1,(R$5-$G6+1)/($H6-$G6+1))) -> 1 | S6: =MAX(0,MIN(1,(S$5-$G6+1)/($H6-$G6+1))) -> 1 | ... AK6: =MAX(0,MIN(1,(AK$5-$G6+1)/($H6-$G6+1))) -> 1
A7: 2 | B7: CIMENTACIÓN | C7: Encofrado | D7: =INDEX('LISTA DE COMPRAS'!$B$30:$E$35,MATCH(B7,'LISTA DE COMPRAS'!$A$30:$A$35,0),MATCH(C7,'LISTA DE COMPRAS'!$B$29:$E$29,0)) -> 352.6 | E7: =IF($D$30>0,D7/$D$30,0) -> 0.0020631487 | F7: 6 | G7: =G6+PARÁMETROS!$B$21 -> 46302 | H7: =G7+F7-1 -> 46307 | I7: =MAX(0,MIN(1,(PARÁMETROS!$B$7-G7+1)/(H7-G7+1))) -> 0 | J7: =_xlfn.MAXIFS('AVANCE REAL'!$E$6:$E$405,'AVANCE REAL'!$C$6:$C$405,B7,'AVANCE REAL'!$D$6:$D$405,C7,'AVANCE REAL'!$A$6:$A$405,"<="&PARÁMETROS!$B$7) -> 0 | L7: =MAX(0,MIN(1,(L$5-$G7+1)/($H7-$G7+1))) -> 0.83333333 | M7: =MAX(0,MIN(1,(M$5-$G7+1)/($H7-$G7+1))) -> 1 | N7: =MAX(0,MIN(1,(N$5-$G7+1)/($H7-$G7+1))) -> 1 | O7: =MAX(0,MIN(1,(O$5-$G7+1)/($H7-$G7+1))) -> 1 | P7: =MAX(0,MIN(1,(P$5-$G7+1)/($H7-$G7+1))) -> 1 | Q7: =MAX(0,MIN(1,(Q$5-$G7+1)/($H7-$G7+1))) -> 1 | R7: =MAX(0,MIN(1,(R$5-$G7+1)/($H7-$G7+1))) -> 1 | S7: =MAX(0,MIN(1,(S$5-$G7+1)/($H7-$G7+1))) -> 1 | ... AK7: =MAX(0,MIN(1,(AK$5-$G7+1)/($H7-$G7+1))) -> 1
A8: 3 | B8: CIMENTACIÓN | C8: Concreto | D8: =INDEX('LISTA DE COMPRAS'!$B$30:$E$35,MATCH(B8,'LISTA DE COMPRAS'!$A$30:$A$35,0),MATCH(C8,'LISTA DE COMPRAS'!$B$29:$E$29,0)) -> 12201 | E8: =IF($D$30>0,D8/$D$30,0) -> 0.071391032 | F8: 3 | G8: =MAX(H6,H7)+1 -> 46308 | H8: =G8+F8-1 -> 46310 | I8: =MAX(0,MIN(1,(PARÁMETROS!$B$7-G8+1)/(H8-G8+1))) -> 0 | J8: =_xlfn.MAXIFS('AVANCE REAL'!$E$6:$E$405,'AVANCE REAL'!$C$6:$C$405,B8,'AVANCE REAL'!$D$6:$D$405,C8,'AVANCE REAL'!$A$6:$A$405,"<="&PARÁMETROS!$B$7) -> 0 | L8: =MAX(0,MIN(1,(L$5-$G8+1)/($H8-$G8+1))) -> 0 | M8: =MAX(0,MIN(1,(M$5-$G8+1)/($H8-$G8+1))) -> 1 | N8: =MAX(0,MIN(1,(N$5-$G8+1)/($H8-$G8+1))) -> 1 | O8: =MAX(0,MIN(1,(O$5-$G8+1)/($H8-$G8+1))) -> 1 | P8: =MAX(0,MIN(1,(P$5-$G8+1)/($H8-$G8+1))) -> 1 | Q8: =MAX(0,MIN(1,(Q$5-$G8+1)/($H8-$G8+1))) -> 1 | R8: =MAX(0,MIN(1,(R$5-$G8+1)/($H8-$G8+1))) -> 1 | S8: =MAX(0,MIN(1,(S$5-$G8+1)/($H8-$G8+1))) -> 1 | ... AK8: =MAX(0,MIN(1,(AK$5-$G8+1)/($H8-$G8+1))) -> 1
A9: 4 | B9: CIMENTACIÓN | C9: Curado | D9: =INDEX('LISTA DE COMPRAS'!$B$30:$E$35,MATCH(B9,'LISTA DE COMPRAS'!$A$30:$A$35,0),MATCH(C9,'LISTA DE COMPRAS'!$B$29:$E$29,0)) -> 200 | E9: =IF($D$30>0,D9/$D$30,0) -> 0.0011702489 | F9: 7 | G9: =H8+1 -> 46311 | H9: =G9+F9-1 -> 46317 | I9: =MAX(0,MIN(1,(PARÁMETROS!$B$7-G9+1)/(H9-G9+1))) -> 0 | J9: =_xlfn.MAXIFS('AVANCE REAL'!$E$6:$E$405,'AVANCE REAL'!$C$6:$C$405,B9,'AVANCE REAL'!$D$6:$D$405,C9,'AVANCE REAL'!$A$6:$A$405,"<="&PARÁMETROS!$B$7) -> 0 | L9: =MAX(0,MIN(1,(L$5-$G9+1)/($H9-$G9+1))) -> 0 | M9: =MAX(0,MIN(1,(M$5-$G9+1)/($H9-$G9+1))) -> 0.42857143 | N9: =MAX(0,MIN(1,(N$5-$G9+1)/($H9-$G9+1))) -> 1 | O9: =MAX(0,MIN(1,(O$5-$G9+1)/($H9-$G9+1))) -> 1 | P9: =MAX(0,MIN(1,(P$5-$G9+1)/($H9-$G9+1))) -> 1 | Q9: =MAX(0,MIN(1,(Q$5-$G9+1)/($H9-$G9+1))) -> 1 | R9: =MAX(0,MIN(1,(R$5-$G9+1)/($H9-$G9+1))) -> 1 | S9: =MAX(0,MIN(1,(S$5-$G9+1)/($H9-$G9+1))) -> 1 | ... AK9: =MAX(0,MIN(1,(AK$5-$G9+1)/($H9-$G9+1))) -> 1
A10: 5 | B10: NIVEL 1 | C10: Acero | D10: =INDEX('LISTA DE COMPRAS'!$B$30:$E$35,MATCH(B10,'LISTA DE COMPRAS'!$A$30:$A$35,0),MATCH(C10,'LISTA DE COMPRAS'!$B$29:$E$29,0)) -> 6108.93 | E10: =IF($D$30>0,D10/$D$30,0) -> 0.035744842 | F10: 4 | G10: =H8+1 -> 46311 | H10: =G10+F10-1 -> 46314 | I10: =MAX(0,MIN(1,(PARÁMETROS!$B$7-G10+1)/(H10-G10+1))) -> 0 | J10: =_xlfn.MAXIFS('AVANCE REAL'!$E$6:$E$405,'AVANCE REAL'!$C$6:$C$405,B10,'AVANCE REAL'!$D$6:$D$405,C10,'AVANCE REAL'!$A$6:$A$405,"<="&PARÁMETROS!$B$7) -> 0 | L10: =MAX(0,MIN(1,(L$5-$G10+1)/($H10-$G10+1))) -> 0 | M10: =MAX(0,MIN(1,(M$5-$G10+1)/($H10-$G10+1))) -> 0.75 | N10: =MAX(0,MIN(1,(N$5-$G10+1)/($H10-$G10+1))) -> 1 | O10: =MAX(0,MIN(1,(O$5-$G10+1)/($H10-$G10+1))) -> 1 | P10: =MAX(0,MIN(1,(P$5-$G10+1)/($H10-$G10+1))) -> 1 | Q10: =MAX(0,MIN(1,(Q$5-$G10+1)/($H10-$G10+1))) -> 1 | R10: =MAX(0,MIN(1,(R$5-$G10+1)/($H10-$G10+1))) -> 1 | S10: =MAX(0,MIN(1,(S$5-$G10+1)/($H10-$G10+1))) -> 1 | ... AK10: =MAX(0,MIN(1,(AK$5-$G10+1)/($H10-$G10+1))) -> 1
A11: 6 | B11: NIVEL 1 | C11: Encofrado | D11: =INDEX('LISTA DE COMPRAS'!$B$30:$E$35,MATCH(B11,'LISTA DE COMPRAS'!$A$30:$A$35,0),MATCH(C11,'LISTA DE COMPRAS'!$B$29:$E$29,0)) -> 630.6 | E11: =IF($D$30>0,D11/$D$30,0) -> 0.0036897946 | F11: 3 | G11: =G10+PARÁMETROS!$B$21 -> 46313 | H11: =G11+F11-1 -> 46315 | I11: =MAX(0,MIN(1,(PARÁMETROS!$B$7-G11+1)/(H11-G11+1))) -> 0 | J11: =_xlfn.MAXIFS('AVANCE REAL'!$E$6:$E$405,'AVANCE REAL'!$C$6:$C$405,B11,'AVANCE REAL'!$D$6:$D$405,C11,'AVANCE REAL'!$A$6:$A$405,"<="&PARÁMETROS!$B$7) -> 0 | L11: =MAX(0,MIN(1,(L$5-$G11+1)/($H11-$G11+1))) -> 0 | M11: =MAX(0,MIN(1,(M$5-$G11+1)/($H11-$G11+1))) -> 0.33333333 | N11: =MAX(0,MIN(1,(N$5-$G11+1)/($H11-$G11+1))) -> 1 | O11: =MAX(0,MIN(1,(O$5-$G11+1)/($H11-$G11+1))) -> 1 | P11: =MAX(0,MIN(1,(P$5-$G11+1)/($H11-$G11+1))) -> 1 | Q11: =MAX(0,MIN(1,(Q$5-$G11+1)/($H11-$G11+1))) -> 1 | R11: =MAX(0,MIN(1,(R$5-$G11+1)/($H11-$G11+1))) -> 1 | S11: =MAX(0,MIN(1,(S$5-$G11+1)/($H11-$G11+1))) -> 1 | ... AK11: =MAX(0,MIN(1,(AK$5-$G11+1)/($H11-$G11+1))) -> 1
A12: 7 | B12: NIVEL 1 | C12: Concreto | D12: =INDEX('LISTA DE COMPRAS'!$B$30:$E$35,MATCH(B12,'LISTA DE COMPRAS'!$A$30:$A$35,0),MATCH(C12,'LISTA DE COMPRAS'!$B$29:$E$29,0)) -> 4507 | E12: =IF($D$30>0,D12/$D$30,0) -> 0.026371558 | F12: 2 | G12: =MAX(H10,H11)+1 -> 46316 | H12: =G12+F12-1 -> 46317 | I12: =MAX(0,MIN(1,(PARÁMETROS!$B$7-G12+1)/(H12-G12+1))) -> 0 | J12: =_xlfn.MAXIFS('AVANCE REAL'!$E$6:$E$405,'AVANCE REAL'!$C$6:$C$405,B12,'AVANCE REAL'!$D$6:$D$405,C12,'AVANCE REAL'!$A$6:$A$405,"<="&PARÁMETROS!$B$7) -> 0 | L12: =MAX(0,MIN(1,(L$5-$G12+1)/($H12-$G12+1))) -> 0 | M12: =MAX(0,MIN(1,(M$5-$G12+1)/($H12-$G12+1))) -> 0 | N12: =MAX(0,MIN(1,(N$5-$G12+1)/($H12-$G12+1))) -> 1 | O12: =MAX(0,MIN(1,(O$5-$G12+1)/($H12-$G12+1))) -> 1 | P12: =MAX(0,MIN(1,(P$5-$G12+1)/($H12-$G12+1))) -> 1 | Q12: =MAX(0,MIN(1,(Q$5-$G12+1)/($H12-$G12+1))) -> 1 | R12: =MAX(0,MIN(1,(R$5-$G12+1)/($H12-$G12+1))) -> 1 | S12: =MAX(0,MIN(1,(S$5-$G12+1)/($H12-$G12+1))) -> 1 | ... AK12: =MAX(0,MIN(1,(AK$5-$G12+1)/($H12-$G12+1))) -> 1
A13: 8 | B13: NIVEL 1 | C13: Curado | D13: =INDEX('LISTA DE COMPRAS'!$B$30:$E$35,MATCH(B13,'LISTA DE COMPRAS'!$A$30:$A$35,0),MATCH(C13,'LISTA DE COMPRAS'!$B$29:$E$29,0)) -> 280 | E13: =IF($D$30>0,D13/$D$30,0) -> 0.0016383484 | F13: 7 | G13: =H12+1 -> 46318 | H13: =G13+F13-1 -> 46324 | I13: =MAX(0,MIN(1,(PARÁMETROS!$B$7-G13+1)/(H13-G13+1))) -> 0 | J13: =_xlfn.MAXIFS('AVANCE REAL'!$E$6:$E$405,'AVANCE REAL'!$C$6:$C$405,B13,'AVANCE REAL'!$D$6:$D$405,C13,'AVANCE REAL'!$A$6:$A$405,"<="&PARÁMETROS!$B$7) -> 0 | L13: =MAX(0,MIN(1,(L$5-$G13+1)/($H13-$G13+1))) -> 0 | M13: =MAX(0,MIN(1,(M$5-$G13+1)/($H13-$G13+1))) -> 0 | N13: =MAX(0,MIN(1,(N$5-$G13+1)/($H13-$G13+1))) -> 0.42857143 | O13: =MAX(0,MIN(1,(O$5-$G13+1)/($H13-$G13+1))) -> 1 | P13: =MAX(0,MIN(1,(P$5-$G13+1)/($H13-$G13+1))) -> 1 | Q13: =MAX(0,MIN(1,(Q$5-$G13+1)/($H13-$G13+1))) -> 1 | R13: =MAX(0,MIN(1,(R$5-$G13+1)/($H13-$G13+1))) -> 1 | S13: =MAX(0,MIN(1,(S$5-$G13+1)/($H13-$G13+1))) -> 1 | ... AK13: =MAX(0,MIN(1,(AK$5-$G13+1)/($H13-$G13+1))) -> 1
A14: 9 | B14: NIVEL 2 | C14: Acero | D14: =INDEX('LISTA DE COMPRAS'!$B$30:$E$35,MATCH(B14,'LISTA DE COMPRAS'!$A$30:$A$35,0),MATCH(C14,'LISTA DE COMPRAS'!$B$29:$E$29,0)) -> 20473.24 | E14: =IF($D$30>0,D14/$D$30,0) -> 0.11979393 | F14: 12 | G14: =H12+1 -> 46318 | H14: =G14+F14-1 -> 46329 | I14: =MAX(0,MIN(1,(PARÁMETROS!$B$7-G14+1)/(H14-G14+1))) -> 0 | J14: =_xlfn.MAXIFS('AVANCE REAL'!$E$6:$E$405,'AVANCE REAL'!$C$6:$C$405,B14,'AVANCE REAL'!$D$6:$D$405,C14,'AVANCE REAL'!$A$6:$A$405,"<="&PARÁMETROS!$B$7) -> 0 | L14: =MAX(0,MIN(1,(L$5-$G14+1)/($H14-$G14+1))) -> 0 | M14: =MAX(0,MIN(1,(M$5-$G14+1)/($H14-$G14+1))) -> 0 | N14: =MAX(0,MIN(1,(N$5-$G14+1)/($H14-$G14+1))) -> 0.25 | O14: =MAX(0,MIN(1,(O$5-$G14+1)/($H14-$G14+1))) -> 0.83333333 | P14: =MAX(0,MIN(1,(P$5-$G14+1)/($H14-$G14+1))) -> 1 | Q14: =MAX(0,MIN(1,(Q$5-$G14+1)/($H14-$G14+1))) -> 1 | R14: =MAX(0,MIN(1,(R$5-$G14+1)/($H14-$G14+1))) -> 1 | S14: =MAX(0,MIN(1,(S$5-$G14+1)/($H14-$G14+1))) -> 1 | ... AK14: =MAX(0,MIN(1,(AK$5-$G14+1)/($H14-$G14+1))) -> 1
A15: 10 | B15: NIVEL 2 | C15: Encofrado | D15: =INDEX('LISTA DE COMPRAS'!$B$30:$E$35,MATCH(B15,'LISTA DE COMPRAS'!$A$30:$A$35,0),MATCH(C15,'LISTA DE COMPRAS'!$B$29:$E$29,0)) -> 3966.9 | E15: =IF($D$30>0,D15/$D$30,0) -> 0.023211301 | F15: 12 | G15: =G14+PARÁMETROS!$B$21 -> 46320 | H15: =G15+F15-1 -> 46331 | I15: =MAX(0,MIN(1,(PARÁMETROS!$B$7-G15+1)/(H15-G15+1))) -> 0 | J15: =_xlfn.MAXIFS('AVANCE REAL'!$E$6:$E$405,'AVANCE REAL'!$C$6:$C$405,B15,'AVANCE REAL'!$D$6:$D$405,C15,'AVANCE REAL'!$A$6:$A$405,"<="&PARÁMETROS!$B$7) -> 0 | L15: =MAX(0,MIN(1,(L$5-$G15+1)/($H15-$G15+1))) -> 0 | M15: =MAX(0,MIN(1,(M$5-$G15+1)/($H15-$G15+1))) -> 0 | N15: =MAX(0,MIN(1,(N$5-$G15+1)/($H15-$G15+1))) -> 0.083333333 | O15: =MAX(0,MIN(1,(O$5-$G15+1)/($H15-$G15+1))) -> 0.66666667 | P15: =MAX(0,MIN(1,(P$5-$G15+1)/($H15-$G15+1))) -> 1 | Q15: =MAX(0,MIN(1,(Q$5-$G15+1)/($H15-$G15+1))) -> 1 | R15: =MAX(0,MIN(1,(R$5-$G15+1)/($H15-$G15+1))) -> 1 | S15: =MAX(0,MIN(1,(S$5-$G15+1)/($H15-$G15+1))) -> 1 | ... AK15: =MAX(0,MIN(1,(AK$5-$G15+1)/($H15-$G15+1))) -> 1
A16: 11 | B16: NIVEL 2 | C16: Concreto | D16: =INDEX('LISTA DE COMPRAS'!$B$30:$E$35,MATCH(B16,'LISTA DE COMPRAS'!$A$30:$A$35,0),MATCH(C16,'LISTA DE COMPRAS'!$B$29:$E$29,0)) -> 12145 | E16: =IF($D$30>0,D16/$D$30,0) -> 0.071063362 | F16: 2 | G16: =MAX(H14,H15)+1 -> 46332 | H16: =G16+F16-1 -> 46333 | I16: =MAX(0,MIN(1,(PARÁMETROS!$B$7-G16+1)/(H16-G16+1))) -> 0 | J16: =_xlfn.MAXIFS('AVANCE REAL'!$E$6:$E$405,'AVANCE REAL'!$C$6:$C$405,B16,'AVANCE REAL'!$D$6:$D$405,C16,'AVANCE REAL'!$A$6:$A$405,"<="&PARÁMETROS!$B$7) -> 0 | L16: =MAX(0,MIN(1,(L$5-$G16+1)/($H16-$G16+1))) -> 0 | M16: =MAX(0,MIN(1,(M$5-$G16+1)/($H16-$G16+1))) -> 0 | N16: =MAX(0,MIN(1,(N$5-$G16+1)/($H16-$G16+1))) -> 0 | O16: =MAX(0,MIN(1,(O$5-$G16+1)/($H16-$G16+1))) -> 0 | P16: =MAX(0,MIN(1,(P$5-$G16+1)/($H16-$G16+1))) -> 1 | Q16: =MAX(0,MIN(1,(Q$5-$G16+1)/($H16-$G16+1))) -> 1 | R16: =MAX(0,MIN(1,(R$5-$G16+1)/($H16-$G16+1))) -> 1 | S16: =MAX(0,MIN(1,(S$5-$G16+1)/($H16-$G16+1))) -> 1 | ... AK16: =MAX(0,MIN(1,(AK$5-$G16+1)/($H16-$G16+1))) -> 1
A17: 12 | B17: NIVEL 2 | C17: Curado | D17: =INDEX('LISTA DE COMPRAS'!$B$30:$E$35,MATCH(B17,'LISTA DE COMPRAS'!$A$30:$A$35,0),MATCH(C17,'LISTA DE COMPRAS'!$B$29:$E$29,0)) -> 520 | E17: =IF($D$30>0,D17/$D$30,0) -> 0.003042647 | F17: 7 | G17: =H16+1 -> 46334 | H17: =G17+F17-1 -> 46340 | I17: =MAX(0,MIN(1,(PARÁMETROS!$B$7-G17+1)/(H17-G17+1))) -> 0 | J17: =_xlfn.MAXIFS('AVANCE REAL'!$E$6:$E$405,'AVANCE REAL'!$C$6:$C$405,B17,'AVANCE REAL'!$D$6:$D$405,C17,'AVANCE REAL'!$A$6:$A$405,"<="&PARÁMETROS!$B$7) -> 0 | L17: =MAX(0,MIN(1,(L$5-$G17+1)/($H17-$G17+1))) -> 0 | M17: =MAX(0,MIN(1,(M$5-$G17+1)/($H17-$G17+1))) -> 0 | N17: =MAX(0,MIN(1,(N$5-$G17+1)/($H17-$G17+1))) -> 0 | O17: =MAX(0,MIN(1,(O$5-$G17+1)/($H17-$G17+1))) -> 0 | P17: =MAX(0,MIN(1,(P$5-$G17+1)/($H17-$G17+1))) -> 0.14285714 | Q17: =MAX(0,MIN(1,(Q$5-$G17+1)/($H17-$G17+1))) -> 1 | R17: =MAX(0,MIN(1,(R$5-$G17+1)/($H17-$G17+1))) -> 1 | S17: =MAX(0,MIN(1,(S$5-$G17+1)/($H17-$G17+1))) -> 1 | ... AK17: =MAX(0,MIN(1,(AK$5-$G17+1)/($H17-$G17+1))) -> 1
A18: 13 | B18: NIVEL 3 | C18: Acero | D18: =INDEX('LISTA DE COMPRAS'!$B$30:$E$35,MATCH(B18,'LISTA DE COMPRAS'!$A$30:$A$35,0),MATCH(C18,'LISTA DE COMPRAS'!$B$29:$E$29,0)) -> 18077.68 | E18: =IF($D$30>0,D18/$D$30,0) -> 0.10577692 | F18: 12 | G18: =H16+1 -> 46334 | H18: =G18+F18-1 -> 46345 | I18: =MAX(0,MIN(1,(PARÁMETROS!$B$7-G18+1)/(H18-G18+1))) -> 0 | J18: =_xlfn.MAXIFS('AVANCE REAL'!$E$6:$E$405,'AVANCE REAL'!$C$6:$C$405,B18,'AVANCE REAL'!$D$6:$D$405,C18,'AVANCE REAL'!$A$6:$A$405,"<="&PARÁMETROS!$B$7) -> 0 | L18: =MAX(0,MIN(1,(L$5-$G18+1)/($H18-$G18+1))) -> 0 | M18: =MAX(0,MIN(1,(M$5-$G18+1)/($H18-$G18+1))) -> 0 | N18: =MAX(0,MIN(1,(N$5-$G18+1)/($H18-$G18+1))) -> 0 | O18: =MAX(0,MIN(1,(O$5-$G18+1)/($H18-$G18+1))) -> 0 | P18: =MAX(0,MIN(1,(P$5-$G18+1)/($H18-$G18+1))) -> 0.083333333 | Q18: =MAX(0,MIN(1,(Q$5-$G18+1)/($H18-$G18+1))) -> 0.66666667 | R18: =MAX(0,MIN(1,(R$5-$G18+1)/($H18-$G18+1))) -> 1 | S18: =MAX(0,MIN(1,(S$5-$G18+1)/($H18-$G18+1))) -> 1 | ... AK18: =MAX(0,MIN(1,(AK$5-$G18+1)/($H18-$G18+1))) -> 1
A19: 14 | B19: NIVEL 3 | C19: Encofrado | D19: =INDEX('LISTA DE COMPRAS'!$B$30:$E$35,MATCH(B19,'LISTA DE COMPRAS'!$A$30:$A$35,0),MATCH(C19,'LISTA DE COMPRAS'!$B$29:$E$29,0)) -> 3686.8 | E19: =IF($D$30>0,D19/$D$30,0) -> 0.021572367 | F19: 12 | G19: =G18+PARÁMETROS!$B$21 -> 46336 | H19: =G19+F19-1 -> 46347 | I19: =MAX(0,MIN(1,(PARÁMETROS!$B$7-G19+1)/(H19-G19+1))) -> 0 | J19: =_xlfn.MAXIFS('AVANCE REAL'!$E$6:$E$405,'AVANCE REAL'!$C$6:$C$405,B19,'AVANCE REAL'!$D$6:$D$405,C19,'AVANCE REAL'!$A$6:$A$405,"<="&PARÁMETROS!$B$7) -> 0 | L19: =MAX(0,MIN(1,(L$5-$G19+1)/($H19-$G19+1))) -> 0 | M19: =MAX(0,MIN(1,(M$5-$G19+1)/($H19-$G19+1))) -> 0 | N19: =MAX(0,MIN(1,(N$5-$G19+1)/($H19-$G19+1))) -> 0 | O19: =MAX(0,MIN(1,(O$5-$G19+1)/($H19-$G19+1))) -> 0 | P19: =MAX(0,MIN(1,(P$5-$G19+1)/($H19-$G19+1))) -> 0 | Q19: =MAX(0,MIN(1,(Q$5-$G19+1)/($H19-$G19+1))) -> 0.5 | R19: =MAX(0,MIN(1,(R$5-$G19+1)/($H19-$G19+1))) -> 1 | S19: =MAX(0,MIN(1,(S$5-$G19+1)/($H19-$G19+1))) -> 1 | ... AK19: =MAX(0,MIN(1,(AK$5-$G19+1)/($H19-$G19+1))) -> 1
A20: 15 | B20: NIVEL 3 | C20: Concreto | D20: =INDEX('LISTA DE COMPRAS'!$B$30:$E$35,MATCH(B20,'LISTA DE COMPRAS'!$A$30:$A$35,0),MATCH(C20,'LISTA DE COMPRAS'!$B$29:$E$29,0)) -> 11424.5 | E20: =IF($D$30>0,D20/$D$30,0) -> 0.06684754 | F20: 2 | G20: =MAX(H18,H19)+1 -> 46348 | H20: =G20+F20-1 -> 46349 | I20: =MAX(0,MIN(1,(PARÁMETROS!$B$7-G20+1)/(H20-G20+1))) -> 0 | J20: =_xlfn.MAXIFS('AVANCE REAL'!$E$6:$E$405,'AVANCE REAL'!$C$6:$C$405,B20,'AVANCE REAL'!$D$6:$D$405,C20,'AVANCE REAL'!$A$6:$A$405,"<="&PARÁMETROS!$B$7) -> 0 | L20: =MAX(0,MIN(1,(L$5-$G20+1)/($H20-$G20+1))) -> 0 | M20: =MAX(0,MIN(1,(M$5-$G20+1)/($H20-$G20+1))) -> 0 | N20: =MAX(0,MIN(1,(N$5-$G20+1)/($H20-$G20+1))) -> 0 | O20: =MAX(0,MIN(1,(O$5-$G20+1)/($H20-$G20+1))) -> 0 | P20: =MAX(0,MIN(1,(P$5-$G20+1)/($H20-$G20+1))) -> 0 | Q20: =MAX(0,MIN(1,(Q$5-$G20+1)/($H20-$G20+1))) -> 0 | R20: =MAX(0,MIN(1,(R$5-$G20+1)/($H20-$G20+1))) -> 0.5 | S20: =MAX(0,MIN(1,(S$5-$G20+1)/($H20-$G20+1))) -> 1 | ... AK20: =MAX(0,MIN(1,(AK$5-$G20+1)/($H20-$G20+1))) -> 1
A21: 16 | B21: NIVEL 3 | C21: Curado | D21: =INDEX('LISTA DE COMPRAS'!$B$30:$E$35,MATCH(B21,'LISTA DE COMPRAS'!$A$30:$A$35,0),MATCH(C21,'LISTA DE COMPRAS'!$B$29:$E$29,0)) -> 480 | E21: =IF($D$30>0,D21/$D$30,0) -> 0.0028085973 | F21: 7 | G21: =H20+1 -> 46350 | H21: =G21+F21-1 -> 46356 | I21: =MAX(0,MIN(1,(PARÁMETROS!$B$7-G21+1)/(H21-G21+1))) -> 0 | J21: =_xlfn.MAXIFS('AVANCE REAL'!$E$6:$E$405,'AVANCE REAL'!$C$6:$C$405,B21,'AVANCE REAL'!$D$6:$D$405,C21,'AVANCE REAL'!$A$6:$A$405,"<="&PARÁMETROS!$B$7) -> 0 | L21: =MAX(0,MIN(1,(L$5-$G21+1)/($H21-$G21+1))) -> 0 | M21: =MAX(0,MIN(1,(M$5-$G21+1)/($H21-$G21+1))) -> 0 | N21: =MAX(0,MIN(1,(N$5-$G21+1)/($H21-$G21+1))) -> 0 | O21: =MAX(0,MIN(1,(O$5-$G21+1)/($H21-$G21+1))) -> 0 | P21: =MAX(0,MIN(1,(P$5-$G21+1)/($H21-$G21+1))) -> 0 | Q21: =MAX(0,MIN(1,(Q$5-$G21+1)/($H21-$G21+1))) -> 0 | R21: =MAX(0,MIN(1,(R$5-$G21+1)/($H21-$G21+1))) -> 0 | S21: =MAX(0,MIN(1,(S$5-$G21+1)/($H21-$G21+1))) -> 0.85714286 | ... AK21: =MAX(0,MIN(1,(AK$5-$G21+1)/($H21-$G21+1))) -> 1
A22: 17 | B22: NIVEL 4 | C22: Acero | D22: =INDEX('LISTA DE COMPRAS'!$B$30:$E$35,MATCH(B22,'LISTA DE COMPRAS'!$A$30:$A$35,0),MATCH(C22,'LISTA DE COMPRAS'!$B$29:$E$29,0)) -> 17909.85 | E22: =IF($D$30>0,D22/$D$30,0) -> 0.10479491 | F22: 12 | G22: =H20+1 -> 46350 | H22: =G22+F22-1 -> 46361 | I22: =MAX(0,MIN(1,(PARÁMETROS!$B$7-G22+1)/(H22-G22+1))) -> 0 | J22: =_xlfn.MAXIFS('AVANCE REAL'!$E$6:$E$405,'AVANCE REAL'!$C$6:$C$405,B22,'AVANCE REAL'!$D$6:$D$405,C22,'AVANCE REAL'!$A$6:$A$405,"<="&PARÁMETROS!$B$7) -> 0 | L22: =MAX(0,MIN(1,(L$5-$G22+1)/($H22-$G22+1))) -> 0 | M22: =MAX(0,MIN(1,(M$5-$G22+1)/($H22-$G22+1))) -> 0 | N22: =MAX(0,MIN(1,(N$5-$G22+1)/($H22-$G22+1))) -> 0 | O22: =MAX(0,MIN(1,(O$5-$G22+1)/($H22-$G22+1))) -> 0 | P22: =MAX(0,MIN(1,(P$5-$G22+1)/($H22-$G22+1))) -> 0 | Q22: =MAX(0,MIN(1,(Q$5-$G22+1)/($H22-$G22+1))) -> 0 | R22: =MAX(0,MIN(1,(R$5-$G22+1)/($H22-$G22+1))) -> 0 | S22: =MAX(0,MIN(1,(S$5-$G22+1)/($H22-$G22+1))) -> 0.5 | ... AK22: =MAX(0,MIN(1,(AK$5-$G22+1)/($H22-$G22+1))) -> 1
A23: 18 | B23: NIVEL 4 | C23: Encofrado | D23: =INDEX('LISTA DE COMPRAS'!$B$30:$E$35,MATCH(B23,'LISTA DE COMPRAS'!$A$30:$A$35,0),MATCH(C23,'LISTA DE COMPRAS'!$B$29:$E$29,0)) -> 3686.8 | E23: =IF($D$30>0,D23/$D$30,0) -> 0.021572367 | F23: 12 | G23: =G22+PARÁMETROS!$B$21 -> 46352 | H23: =G23+F23-1 -> 46363 | I23: =MAX(0,MIN(1,(PARÁMETROS!$B$7-G23+1)/(H23-G23+1))) -> 0 | J23: =_xlfn.MAXIFS('AVANCE REAL'!$E$6:$E$405,'AVANCE REAL'!$C$6:$C$405,B23,'AVANCE REAL'!$D$6:$D$405,C23,'AVANCE REAL'!$A$6:$A$405,"<="&PARÁMETROS!$B$7) -> 0 | L23: =MAX(0,MIN(1,(L$5-$G23+1)/($H23-$G23+1))) -> 0 | M23: =MAX(0,MIN(1,(M$5-$G23+1)/($H23-$G23+1))) -> 0 | N23: =MAX(0,MIN(1,(N$5-$G23+1)/($H23-$G23+1))) -> 0 | O23: =MAX(0,MIN(1,(O$5-$G23+1)/($H23-$G23+1))) -> 0 | P23: =MAX(0,MIN(1,(P$5-$G23+1)/($H23-$G23+1))) -> 0 | Q23: =MAX(0,MIN(1,(Q$5-$G23+1)/($H23-$G23+1))) -> 0 | R23: =MAX(0,MIN(1,(R$5-$G23+1)/($H23-$G23+1))) -> 0 | S23: =MAX(0,MIN(1,(S$5-$G23+1)/($H23-$G23+1))) -> 0.33333333 | ... AK23: =MAX(0,MIN(1,(AK$5-$G23+1)/($H23-$G23+1))) -> 1
A24: 19 | B24: NIVEL 4 | C24: Concreto | D24: =INDEX('LISTA DE COMPRAS'!$B$30:$E$35,MATCH(B24,'LISTA DE COMPRAS'!$A$30:$A$35,0),MATCH(C24,'LISTA DE COMPRAS'!$B$29:$E$29,0)) -> 11424.5 | E24: =IF($D$30>0,D24/$D$30,0) -> 0.06684754 | F24: 2 | G24: =MAX(H22,H23)+1 -> 46364 | H24: =G24+F24-1 -> 46365 | I24: =MAX(0,MIN(1,(PARÁMETROS!$B$7-G24+1)/(H24-G24+1))) -> 0 | J24: =_xlfn.MAXIFS('AVANCE REAL'!$E$6:$E$405,'AVANCE REAL'!$C$6:$C$405,B24,'AVANCE REAL'!$D$6:$D$405,C24,'AVANCE REAL'!$A$6:$A$405,"<="&PARÁMETROS!$B$7) -> 0 | L24: =MAX(0,MIN(1,(L$5-$G24+1)/($H24-$G24+1))) -> 0 | M24: =MAX(0,MIN(1,(M$5-$G24+1)/($H24-$G24+1))) -> 0 | N24: =MAX(0,MIN(1,(N$5-$G24+1)/($H24-$G24+1))) -> 0 | O24: =MAX(0,MIN(1,(O$5-$G24+1)/($H24-$G24+1))) -> 0 | P24: =MAX(0,MIN(1,(P$5-$G24+1)/($H24-$G24+1))) -> 0 | Q24: =MAX(0,MIN(1,(Q$5-$G24+1)/($H24-$G24+1))) -> 0 | R24: =MAX(0,MIN(1,(R$5-$G24+1)/($H24-$G24+1))) -> 0 | S24: =MAX(0,MIN(1,(S$5-$G24+1)/($H24-$G24+1))) -> 0 | ... AK24: =MAX(0,MIN(1,(AK$5-$G24+1)/($H24-$G24+1))) -> 1
A25: 20 | B25: NIVEL 4 | C25: Curado | D25: =INDEX('LISTA DE COMPRAS'!$B$30:$E$35,MATCH(B25,'LISTA DE COMPRAS'!$A$30:$A$35,0),MATCH(C25,'LISTA DE COMPRAS'!$B$29:$E$29,0)) -> 480 | E25: =IF($D$30>0,D25/$D$30,0) -> 0.0028085973 | F25: 7 | G25: =H24+1 -> 46366 | H25: =G25+F25-1 -> 46372 | I25: =MAX(0,MIN(1,(PARÁMETROS!$B$7-G25+1)/(H25-G25+1))) -> 0 | J25: =_xlfn.MAXIFS('AVANCE REAL'!$E$6:$E$405,'AVANCE REAL'!$C$6:$C$405,B25,'AVANCE REAL'!$D$6:$D$405,C25,'AVANCE REAL'!$A$6:$A$405,"<="&PARÁMETROS!$B$7) -> 0 | L25: =MAX(0,MIN(1,(L$5-$G25+1)/($H25-$G25+1))) -> 0 | M25: =MAX(0,MIN(1,(M$5-$G25+1)/($H25-$G25+1))) -> 0 | N25: =MAX(0,MIN(1,(N$5-$G25+1)/($H25-$G25+1))) -> 0 | O25: =MAX(0,MIN(1,(O$5-$G25+1)/($H25-$G25+1))) -> 0 | P25: =MAX(0,MIN(1,(P$5-$G25+1)/($H25-$G25+1))) -> 0 | Q25: =MAX(0,MIN(1,(Q$5-$G25+1)/($H25-$G25+1))) -> 0 | R25: =MAX(0,MIN(1,(R$5-$G25+1)/($H25-$G25+1))) -> 0 | S25: =MAX(0,MIN(1,(S$5-$G25+1)/($H25-$G25+1))) -> 0 | ... AK25: =MAX(0,MIN(1,(AK$5-$G25+1)/($H25-$G25+1))) -> 1
A26: 21 | B26: NIVEL 5 | C26: Acero | D26: =INDEX('LISTA DE COMPRAS'!$B$30:$E$35,MATCH(B26,'LISTA DE COMPRAS'!$A$30:$A$35,0),MATCH(C26,'LISTA DE COMPRAS'!$B$29:$E$29,0)) -> 15551.64 | E26: =IF($D$30>0,D26/$D$30,0) -> 0.090996445 | F26: 12 | G26: =H24+1 -> 46366 | H26: =G26+F26-1 -> 46377 | I26: =MAX(0,MIN(1,(PARÁMETROS!$B$7-G26+1)/(H26-G26+1))) -> 0 | J26: =_xlfn.MAXIFS('AVANCE REAL'!$E$6:$E$405,'AVANCE REAL'!$C$6:$C$405,B26,'AVANCE REAL'!$D$6:$D$405,C26,'AVANCE REAL'!$A$6:$A$405,"<="&PARÁMETROS!$B$7) -> 0 | L26: =MAX(0,MIN(1,(L$5-$G26+1)/($H26-$G26+1))) -> 0 | M26: =MAX(0,MIN(1,(M$5-$G26+1)/($H26-$G26+1))) -> 0 | N26: =MAX(0,MIN(1,(N$5-$G26+1)/($H26-$G26+1))) -> 0 | O26: =MAX(0,MIN(1,(O$5-$G26+1)/($H26-$G26+1))) -> 0 | P26: =MAX(0,MIN(1,(P$5-$G26+1)/($H26-$G26+1))) -> 0 | Q26: =MAX(0,MIN(1,(Q$5-$G26+1)/($H26-$G26+1))) -> 0 | R26: =MAX(0,MIN(1,(R$5-$G26+1)/($H26-$G26+1))) -> 0 | S26: =MAX(0,MIN(1,(S$5-$G26+1)/($H26-$G26+1))) -> 0 | ... AK26: =MAX(0,MIN(1,(AK$5-$G26+1)/($H26-$G26+1))) -> 1
A27: 22 | B27: NIVEL 5 | C27: Encofrado | D27: =INDEX('LISTA DE COMPRAS'!$B$30:$E$35,MATCH(B27,'LISTA DE COMPRAS'!$A$30:$A$35,0),MATCH(C27,'LISTA DE COMPRAS'!$B$29:$E$29,0)) -> 3686.8 | E27: =IF($D$30>0,D27/$D$30,0) -> 0.021572367 | F27: 12 | G27: =G26+PARÁMETROS!$B$21 -> 46368 | H27: =G27+F27-1 -> 46379 | I27: =MAX(0,MIN(1,(PARÁMETROS!$B$7-G27+1)/(H27-G27+1))) -> 0 | J27: =_xlfn.MAXIFS('AVANCE REAL'!$E$6:$E$405,'AVANCE REAL'!$C$6:$C$405,B27,'AVANCE REAL'!$D$6:$D$405,C27,'AVANCE REAL'!$A$6:$A$405,"<="&PARÁMETROS!$B$7) -> 0 | L27: =MAX(0,MIN(1,(L$5-$G27+1)/($H27-$G27+1))) -> 0 | M27: =MAX(0,MIN(1,(M$5-$G27+1)/($H27-$G27+1))) -> 0 | N27: =MAX(0,MIN(1,(N$5-$G27+1)/($H27-$G27+1))) -> 0 | O27: =MAX(0,MIN(1,(O$5-$G27+1)/($H27-$G27+1))) -> 0 | P27: =MAX(0,MIN(1,(P$5-$G27+1)/($H27-$G27+1))) -> 0 | Q27: =MAX(0,MIN(1,(Q$5-$G27+1)/($H27-$G27+1))) -> 0 | R27: =MAX(0,MIN(1,(R$5-$G27+1)/($H27-$G27+1))) -> 0 | S27: =MAX(0,MIN(1,(S$5-$G27+1)/($H27-$G27+1))) -> 0 | ... AK27: =MAX(0,MIN(1,(AK$5-$G27+1)/($H27-$G27+1))) -> 1
A28: 23 | B28: NIVEL 5 | C28: Concreto | D28: =INDEX('LISTA DE COMPRAS'!$B$30:$E$35,MATCH(B28,'LISTA DE COMPRAS'!$A$30:$A$35,0),MATCH(C28,'LISTA DE COMPRAS'!$B$29:$E$29,0)) -> 11424.5 | E28: =IF($D$30>0,D28/$D$30,0) -> 0.06684754 | F28: 2 | G28: =MAX(H26,H27)+1 -> 46380 | H28: =G28+F28-1 -> 46381 | I28: =MAX(0,MIN(1,(PARÁMETROS!$B$7-G28+1)/(H28-G28+1))) -> 0 | J28: =_xlfn.MAXIFS('AVANCE REAL'!$E$6:$E$405,'AVANCE REAL'!$C$6:$C$405,B28,'AVANCE REAL'!$D$6:$D$405,C28,'AVANCE REAL'!$A$6:$A$405,"<="&PARÁMETROS!$B$7) -> 0 | L28: =MAX(0,MIN(1,(L$5-$G28+1)/($H28-$G28+1))) -> 0 | M28: =MAX(0,MIN(1,(M$5-$G28+1)/($H28-$G28+1))) -> 0 | N28: =MAX(0,MIN(1,(N$5-$G28+1)/($H28-$G28+1))) -> 0 | O28: =MAX(0,MIN(1,(O$5-$G28+1)/($H28-$G28+1))) -> 0 | P28: =MAX(0,MIN(1,(P$5-$G28+1)/($H28-$G28+1))) -> 0 | Q28: =MAX(0,MIN(1,(Q$5-$G28+1)/($H28-$G28+1))) -> 0 | R28: =MAX(0,MIN(1,(R$5-$G28+1)/($H28-$G28+1))) -> 0 | S28: =MAX(0,MIN(1,(S$5-$G28+1)/($H28-$G28+1))) -> 0 | ... AK28: =MAX(0,MIN(1,(AK$5-$G28+1)/($H28-$G28+1))) -> 1
A29: 24 | B29: NIVEL 5 | C29: Curado | D29: =INDEX('LISTA DE COMPRAS'!$B$30:$E$35,MATCH(B29,'LISTA DE COMPRAS'!$A$30:$A$35,0),MATCH(C29,'LISTA DE COMPRAS'!$B$29:$E$29,0)) -> 480 | E29: =IF($D$30>0,D29/$D$30,0) -> 0.0028085973 | F29: 7 | G29: =H28+1 -> 46382 | H29: =G29+F29-1 -> 46388 | I29: =MAX(0,MIN(1,(PARÁMETROS!$B$7-G29+1)/(H29-G29+1))) -> 0 | J29: =_xlfn.MAXIFS('AVANCE REAL'!$E$6:$E$405,'AVANCE REAL'!$C$6:$C$405,B29,'AVANCE REAL'!$D$6:$D$405,C29,'AVANCE REAL'!$A$6:$A$405,"<="&PARÁMETROS!$B$7) -> 0 | L29: =MAX(0,MIN(1,(L$5-$G29+1)/($H29-$G29+1))) -> 0 | M29: =MAX(0,MIN(1,(M$5-$G29+1)/($H29-$G29+1))) -> 0 | N29: =MAX(0,MIN(1,(N$5-$G29+1)/($H29-$G29+1))) -> 0 | O29: =MAX(0,MIN(1,(O$5-$G29+1)/($H29-$G29+1))) -> 0 | P29: =MAX(0,MIN(1,(P$5-$G29+1)/($H29-$G29+1))) -> 0 | Q29: =MAX(0,MIN(1,(Q$5-$G29+1)/($H29-$G29+1))) -> 0 | R29: =MAX(0,MIN(1,(R$5-$G29+1)/($H29-$G29+1))) -> 0 | S29: =MAX(0,MIN(1,(S$5-$G29+1)/($H29-$G29+1))) -> 0 | ... AK29: =MAX(0,MIN(1,(AK$5-$G29+1)/($H29-$G29+1))) -> 1
C30: TOTAL | D30: =SUM(D6:D29) -> 170903.82 | E30: =SUM(E6:E29) -> 1 | G30: =MIN(G6:G29) -> 46300 | H30: =MAX(H6:H29) -> 46388 | I30: =SUMPRODUCT($E$6:$E$29,I6:I29) -> 0.0081957501 | J30: =SUMPRODUCT($E$6:$E$29,J6:J29) -> 0
L32: Fracción ejecutada por semana (según AVANCE REAL, hasta la fecha de corte)
B33: =B6 -> CIMENTACIÓN | C33: =C6 -> Acero | L33: =_xlfn.MAXIFS('AVANCE REAL'!$E$6:$E$405,'AVANCE REAL'!$C$6:$C$405,$B33,'AVANCE REAL'!$D$6:$D$405,$C33,'AVANCE REAL'!$A$6:$A$405,"<="&MIN(L$5,PARÁMETROS!$B$7)) -> 0 | M33: =_xlfn.MAXIFS('AVANCE REAL'!$E$6:$E$405,'AVANCE REAL'!$C$6:$C$405,$B33,'AVANCE REAL'!$D$6:$D$405,$C33,'AVANCE REAL'!$A$6:$A$405,"<="&MIN(M$5,PARÁMETROS!$B$7)) -> 0 | N33: =_xlfn.MAXIFS('AVANCE REAL'!$E$6:$E$405,'AVANCE REAL'!$C$6:$C$405,$B33,'AVANCE REAL'!$D$6:$D$405,$C33,'AVANCE REAL'!$A$6:$A$405,"<="&MIN(N$5,PARÁMETROS!$B$7)) -> 0 | O33: =_xlfn.MAXIFS('AVANCE REAL'!$E$6:$E$405,'AVANCE REAL'!$C$6:$C$405,$B33,'AVANCE REAL'!$D$6:$D$405,$C33,'AVANCE REAL'!$A$6:$A$405,"<="&MIN(O$5,PARÁMETROS!$B$7)) -> 0 | P33: =_xlfn.MAXIFS('AVANCE REAL'!$E$6:$E$405,'AVANCE REAL'!$C$6:$C$405,$B33,'AVANCE REAL'!$D$6:$D$405,$C33,'AVANCE REAL'!$A$6:$A$405,"<="&MIN(P$5,PARÁMETROS!$B$7)) -> 0 | Q33: =_xlfn.MAXIFS('AVANCE REAL'!$E$6:$E$405,'AVANCE REAL'!$C$6:$C$405,$B33,'AVANCE REAL'!$D$6:$D$405,$C33,'AVANCE REAL'!$A$6:$A$405,"<="&MIN(Q$5,PARÁMETROS!$B$7)) -> 0 | R33: =_xlfn.MAXIFS('AVANCE REAL'!$E$6:$E$405,'AVANCE REAL'!$C$6:$C$405,$B33,'AVANCE REAL'!$D$6:$D$405,$C33,'AVANCE REAL'!$A$6:$A$405,"<="&MIN(R$5,PARÁMETROS!$B$7)) -> 0 | S33: =_xlfn.MAXIFS('AVANCE REAL'!$E$6:$E$405,'AVANCE REAL'!$C$6:$C$405,$B33,'AVANCE REAL'!$D$6:$D$405,$C33,'AVANCE REAL'!$A$6:$A$405,"<="&MIN(S$5,PARÁMETROS!$B$7)) -> 0 | ... AK33: =_xlfn.MAXIFS('AVANCE REAL'!$E$6:$E$405,'AVANCE REAL'!$C$6:$C$405,$B33,'AVANCE REAL'!$D$6:$D$405,$C33,'AVANCE REAL'!$A$6:$A$405,"<="&MIN(AK$5,PARÁMETROS!$B$7)) -> 0
B34: =B7 -> CIMENTACIÓN | C34: =C7 -> Encofrado | L34: =_xlfn.MAXIFS('AVANCE REAL'!$E$6:$E$405,'AVANCE REAL'!$C$6:$C$405,$B34,'AVANCE REAL'!$D$6:$D$405,$C34,'AVANCE REAL'!$A$6:$A$405,"<="&MIN(L$5,PARÁMETROS!$B$7)) -> 0 | M34: =_xlfn.MAXIFS('AVANCE REAL'!$E$6:$E$405,'AVANCE REAL'!$C$6:$C$405,$B34,'AVANCE REAL'!$D$6:$D$405,$C34,'AVANCE REAL'!$A$6:$A$405,"<="&MIN(M$5,PARÁMETROS!$B$7)) -> 0 | N34: =_xlfn.MAXIFS('AVANCE REAL'!$E$6:$E$405,'AVANCE REAL'!$C$6:$C$405,$B34,'AVANCE REAL'!$D$6:$D$405,$C34,'AVANCE REAL'!$A$6:$A$405,"<="&MIN(N$5,PARÁMETROS!$B$7)) -> 0 | O34: =_xlfn.MAXIFS('AVANCE REAL'!$E$6:$E$405,'AVANCE REAL'!$C$6:$C$405,$B34,'AVANCE REAL'!$D$6:$D$405,$C34,'AVANCE REAL'!$A$6:$A$405,"<="&MIN(O$5,PARÁMETROS!$B$7)) -> 0 | P34: =_xlfn.MAXIFS('AVANCE REAL'!$E$6:$E$405,'AVANCE REAL'!$C$6:$C$405,$B34,'AVANCE REAL'!$D$6:$D$405,$C34,'AVANCE REAL'!$A$6:$A$405,"<="&MIN(P$5,PARÁMETROS!$B$7)) -> 0 | Q34: =_xlfn.MAXIFS('AVANCE REAL'!$E$6:$E$405,'AVANCE REAL'!$C$6:$C$405,$B34,'AVANCE REAL'!$D$6:$D$405,$C34,'AVANCE REAL'!$A$6:$A$405,"<="&MIN(Q$5,PARÁMETROS!$B$7)) -> 0 | R34: =_xlfn.MAXIFS('AVANCE REAL'!$E$6:$E$405,'AVANCE REAL'!$C$6:$C$405,$B34,'AVANCE REAL'!$D$6:$D$405,$C34,'AVANCE REAL'!$A$6:$A$405,"<="&MIN(R$5,PARÁMETROS!$B$7)) -> 0 | S34: =_xlfn.MAXIFS('AVANCE REAL'!$E$6:$E$405,'AVANCE REAL'!$C$6:$C$405,$B34,'AVANCE REAL'!$D$6:$D$405,$C34,'AVANCE REAL'!$A$6:$A$405,"<="&MIN(S$5,PARÁMETROS!$B$7)) -> 0 | ... AK34: =_xlfn.MAXIFS('AVANCE REAL'!$E$6:$E$405,'AVANCE REAL'!$C$6:$C$405,$B34,'AVANCE REAL'!$D$6:$D$405,$C34,'AVANCE REAL'!$A$6:$A$405,"<="&MIN(AK$5,PARÁMETROS!$B$7)) -> 0
B35: =B8 -> CIMENTACIÓN | C35: =C8 -> Concreto | L35: =_xlfn.MAXIFS('AVANCE REAL'!$E$6:$E$405,'AVANCE REAL'!$C$6:$C$405,$B35,'AVANCE REAL'!$D$6:$D$405,$C35,'AVANCE REAL'!$A$6:$A$405,"<="&MIN(L$5,PARÁMETROS!$B$7)) -> 0 | M35: =_xlfn.MAXIFS('AVANCE REAL'!$E$6:$E$405,'AVANCE REAL'!$C$6:$C$405,$B35,'AVANCE REAL'!$D$6:$D$405,$C35,'AVANCE REAL'!$A$6:$A$405,"<="&MIN(M$5,PARÁMETROS!$B$7)) -> 0 | N35: =_xlfn.MAXIFS('AVANCE REAL'!$E$6:$E$405,'AVANCE REAL'!$C$6:$C$405,$B35,'AVANCE REAL'!$D$6:$D$405,$C35,'AVANCE REAL'!$A$6:$A$405,"<="&MIN(N$5,PARÁMETROS!$B$7)) -> 0 | O35: =_xlfn.MAXIFS('AVANCE REAL'!$E$6:$E$405,'AVANCE REAL'!$C$6:$C$405,$B35,'AVANCE REAL'!$D$6:$D$405,$C35,'AVANCE REAL'!$A$6:$A$405,"<="&MIN(O$5,PARÁMETROS!$B$7)) -> 0 | P35: =_xlfn.MAXIFS('AVANCE REAL'!$E$6:$E$405,'AVANCE REAL'!$C$6:$C$405,$B35,'AVANCE REAL'!$D$6:$D$405,$C35,'AVANCE REAL'!$A$6:$A$405,"<="&MIN(P$5,PARÁMETROS!$B$7)) -> 0 | Q35: =_xlfn.MAXIFS('AVANCE REAL'!$E$6:$E$405,'AVANCE REAL'!$C$6:$C$405,$B35,'AVANCE REAL'!$D$6:$D$405,$C35,'AVANCE REAL'!$A$6:$A$405,"<="&MIN(Q$5,PARÁMETROS!$B$7)) -> 0 | R35: =_xlfn.MAXIFS('AVANCE REAL'!$E$6:$E$405,'AVANCE REAL'!$C$6:$C$405,$B35,'AVANCE REAL'!$D$6:$D$405,$C35,'AVANCE REAL'!$A$6:$A$405,"<="&MIN(R$5,PARÁMETROS!$B$7)) -> 0 | S35: =_xlfn.MAXIFS('AVANCE REAL'!$E$6:$E$405,'AVANCE REAL'!$C$6:$C$405,$B35,'AVANCE REAL'!$D$6:$D$405,$C35,'AVANCE REAL'!$A$6:$A$405,"<="&MIN(S$5,PARÁMETROS!$B$7)) -> 0 | ... AK35: =_xlfn.MAXIFS('AVANCE REAL'!$E$6:$E$405,'AVANCE REAL'!$C$6:$C$405,$B35,'AVANCE REAL'!$D$6:$D$405,$C35,'AVANCE REAL'!$A$6:$A$405,"<="&MIN(AK$5,PARÁMETROS!$B$7)) -> 0
B36: =B9 -> CIMENTACIÓN | C36: =C9 -> Curado | L36: =_xlfn.MAXIFS('AVANCE REAL'!$E$6:$E$405,'AVANCE REAL'!$C$6:$C$405,$B36,'AVANCE REAL'!$D$6:$D$405,$C36,'AVANCE REAL'!$A$6:$A$405,"<="&MIN(L$5,PARÁMETROS!$B$7)) -> 0 | M36: =_xlfn.MAXIFS('AVANCE REAL'!$E$6:$E$405,'AVANCE REAL'!$C$6:$C$405,$B36,'AVANCE REAL'!$D$6:$D$405,$C36,'AVANCE REAL'!$A$6:$A$405,"<="&MIN(M$5,PARÁMETROS!$B$7)) -> 0 | N36: =_xlfn.MAXIFS('AVANCE REAL'!$E$6:$E$405,'AVANCE REAL'!$C$6:$C$405,$B36,'AVANCE REAL'!$D$6:$D$405,$C36,'AVANCE REAL'!$A$6:$A$405,"<="&MIN(N$5,PARÁMETROS!$B$7)) -> 0 | O36: =_xlfn.MAXIFS('AVANCE REAL'!$E$6:$E$405,'AVANCE REAL'!$C$6:$C$405,$B36,'AVANCE REAL'!$D$6:$D$405,$C36,'AVANCE REAL'!$A$6:$A$405,"<="&MIN(O$5,PARÁMETROS!$B$7)) -> 0 | P36: =_xlfn.MAXIFS('AVANCE REAL'!$E$6:$E$405,'AVANCE REAL'!$C$6:$C$405,$B36,'AVANCE REAL'!$D$6:$D$405,$C36,'AVANCE REAL'!$A$6:$A$405,"<="&MIN(P$5,PARÁMETROS!$B$7)) -> 0 | Q36: =_xlfn.MAXIFS('AVANCE REAL'!$E$6:$E$405,'AVANCE REAL'!$C$6:$C$405,$B36,'AVANCE REAL'!$D$6:$D$405,$C36,'AVANCE REAL'!$A$6:$A$405,"<="&MIN(Q$5,PARÁMETROS!$B$7)) -> 0 | R36: =_xlfn.MAXIFS('AVANCE REAL'!$E$6:$E$405,'AVANCE REAL'!$C$6:$C$405,$B36,'AVANCE REAL'!$D$6:$D$405,$C36,'AVANCE REAL'!$A$6:$A$405,"<="&MIN(R$5,PARÁMETROS!$B$7)) -> 0 | S36: =_xlfn.MAXIFS('AVANCE REAL'!$E$6:$E$405,'AVANCE REAL'!$C$6:$C$405,$B36,'AVANCE REAL'!$D$6:$D$405,$C36,'AVANCE REAL'!$A$6:$A$405,"<="&MIN(S$5,PARÁMETROS!$B$7)) -> 0 | ... AK36: =_xlfn.MAXIFS('AVANCE REAL'!$E$6:$E$405,'AVANCE REAL'!$C$6:$C$405,$B36,'AVANCE REAL'!$D$6:$D$405,$C36,'AVANCE REAL'!$A$6:$A$405,"<="&MIN(AK$5,PARÁMETROS!$B$7)) -> 0
B37: =B10 -> NIVEL 1 | C37: =C10 -> Acero | L37: =_xlfn.MAXIFS('AVANCE REAL'!$E$6:$E$405,'AVANCE REAL'!$C$6:$C$405,$B37,'AVANCE REAL'!$D$6:$D$405,$C37,'AVANCE REAL'!$A$6:$A$405,"<="&MIN(L$5,PARÁMETROS!$B$7)) -> 0 | M37: =_xlfn.MAXIFS('AVANCE REAL'!$E$6:$E$405,'AVANCE REAL'!$C$6:$C$405,$B37,'AVANCE REAL'!$D$6:$D$405,$C37,'AVANCE REAL'!$A$6:$A$405,"<="&MIN(M$5,PARÁMETROS!$B$7)) -> 0 | N37: =_xlfn.MAXIFS('AVANCE REAL'!$E$6:$E$405,'AVANCE REAL'!$C$6:$C$405,$B37,'AVANCE REAL'!$D$6:$D$405,$C37,'AVANCE REAL'!$A$6:$A$405,"<="&MIN(N$5,PARÁMETROS!$B$7)) -> 0 | O37: =_xlfn.MAXIFS('AVANCE REAL'!$E$6:$E$405,'AVANCE REAL'!$C$6:$C$405,$B37,'AVANCE REAL'!$D$6:$D$405,$C37,'AVANCE REAL'!$A$6:$A$405,"<="&MIN(O$5,PARÁMETROS!$B$7)) -> 0 | P37: =_xlfn.MAXIFS('AVANCE REAL'!$E$6:$E$405,'AVANCE REAL'!$C$6:$C$405,$B37,'AVANCE REAL'!$D$6:$D$405,$C37,'AVANCE REAL'!$A$6:$A$405,"<="&MIN(P$5,PARÁMETROS!$B$7)) -> 0 | Q37: =_xlfn.MAXIFS('AVANCE REAL'!$E$6:$E$405,'AVANCE REAL'!$C$6:$C$405,$B37,'AVANCE REAL'!$D$6:$D$405,$C37,'AVANCE REAL'!$A$6:$A$405,"<="&MIN(Q$5,PARÁMETROS!$B$7)) -> 0 | R37: =_xlfn.MAXIFS('AVANCE REAL'!$E$6:$E$405,'AVANCE REAL'!$C$6:$C$405,$B37,'AVANCE REAL'!$D$6:$D$405,$C37,'AVANCE REAL'!$A$6:$A$405,"<="&MIN(R$5,PARÁMETROS!$B$7)) -> 0 | S37: =_xlfn.MAXIFS('AVANCE REAL'!$E$6:$E$405,'AVANCE REAL'!$C$6:$C$405,$B37,'AVANCE REAL'!$D$6:$D$405,$C37,'AVANCE REAL'!$A$6:$A$405,"<="&MIN(S$5,PARÁMETROS!$B$7)) -> 0 | ... AK37: =_xlfn.MAXIFS('AVANCE REAL'!$E$6:$E$405,'AVANCE REAL'!$C$6:$C$405,$B37,'AVANCE REAL'!$D$6:$D$405,$C37,'AVANCE REAL'!$A$6:$A$405,"<="&MIN(AK$5,PARÁMETROS!$B$7)) -> 0
B38: =B11 -> NIVEL 1 | C38: =C11 -> Encofrado | L38: =_xlfn.MAXIFS('AVANCE REAL'!$E$6:$E$405,'AVANCE REAL'!$C$6:$C$405,$B38,'AVANCE REAL'!$D$6:$D$405,$C38,'AVANCE REAL'!$A$6:$A$405,"<="&MIN(L$5,PARÁMETROS!$B$7)) -> 0 | M38: =_xlfn.MAXIFS('AVANCE REAL'!$E$6:$E$405,'AVANCE REAL'!$C$6:$C$405,$B38,'AVANCE REAL'!$D$6:$D$405,$C38,'AVANCE REAL'!$A$6:$A$405,"<="&MIN(M$5,PARÁMETROS!$B$7)) -> 0 | N38: =_xlfn.MAXIFS('AVANCE REAL'!$E$6:$E$405,'AVANCE REAL'!$C$6:$C$405,$B38,'AVANCE REAL'!$D$6:$D$405,$C38,'AVANCE REAL'!$A$6:$A$405,"<="&MIN(N$5,PARÁMETROS!$B$7)) -> 0 | O38: =_xlfn.MAXIFS('AVANCE REAL'!$E$6:$E$405,'AVANCE REAL'!$C$6:$C$405,$B38,'AVANCE REAL'!$D$6:$D$405,$C38,'AVANCE REAL'!$A$6:$A$405,"<="&MIN(O$5,PARÁMETROS!$B$7)) -> 0 | P38: =_xlfn.MAXIFS('AVANCE REAL'!$E$6:$E$405,'AVANCE REAL'!$C$6:$C$405,$B38,'AVANCE REAL'!$D$6:$D$405,$C38,'AVANCE REAL'!$A$6:$A$405,"<="&MIN(P$5,PARÁMETROS!$B$7)) -> 0 | Q38: =_xlfn.MAXIFS('AVANCE REAL'!$E$6:$E$405,'AVANCE REAL'!$C$6:$C$405,$B38,'AVANCE REAL'!$D$6:$D$405,$C38,'AVANCE REAL'!$A$6:$A$405,"<="&MIN(Q$5,PARÁMETROS!$B$7)) -> 0 | R38: =_xlfn.MAXIFS('AVANCE REAL'!$E$6:$E$405,'AVANCE REAL'!$C$6:$C$405,$B38,'AVANCE REAL'!$D$6:$D$405,$C38,'AVANCE REAL'!$A$6:$A$405,"<="&MIN(R$5,PARÁMETROS!$B$7)) -> 0 | S38: =_xlfn.MAXIFS('AVANCE REAL'!$E$6:$E$405,'AVANCE REAL'!$C$6:$C$405,$B38,'AVANCE REAL'!$D$6:$D$405,$C38,'AVANCE REAL'!$A$6:$A$405,"<="&MIN(S$5,PARÁMETROS!$B$7)) -> 0 | ... AK38: =_xlfn.MAXIFS('AVANCE REAL'!$E$6:$E$405,'AVANCE REAL'!$C$6:$C$405,$B38,'AVANCE REAL'!$D$6:$D$405,$C38,'AVANCE REAL'!$A$6:$A$405,"<="&MIN(AK$5,PARÁMETROS!$B$7)) -> 0
B39: =B12 -> NIVEL 1 | C39: =C12 -> Concreto | L39: =_xlfn.MAXIFS('AVANCE REAL'!$E$6:$E$405,'AVANCE REAL'!$C$6:$C$405,$B39,'AVANCE REAL'!$D$6:$D$405,$C39,'AVANCE REAL'!$A$6:$A$405,"<="&MIN(L$5,PARÁMETROS!$B$7)) -> 0 | M39: =_xlfn.MAXIFS('AVANCE REAL'!$E$6:$E$405,'AVANCE REAL'!$C$6:$C$405,$B39,'AVANCE REAL'!$D$6:$D$405,$C39,'AVANCE REAL'!$A$6:$A$405,"<="&MIN(M$5,PARÁMETROS!$B$7)) -> 0 | N39: =_xlfn.MAXIFS('AVANCE REAL'!$E$6:$E$405,'AVANCE REAL'!$C$6:$C$405,$B39,'AVANCE REAL'!$D$6:$D$405,$C39,'AVANCE REAL'!$A$6:$A$405,"<="&MIN(N$5,PARÁMETROS!$B$7)) -> 0 | O39: =_xlfn.MAXIFS('AVANCE REAL'!$E$6:$E$405,'AVANCE REAL'!$C$6:$C$405,$B39,'AVANCE REAL'!$D$6:$D$405,$C39,'AVANCE REAL'!$A$6:$A$405,"<="&MIN(O$5,PARÁMETROS!$B$7)) -> 0 | P39: =_xlfn.MAXIFS('AVANCE REAL'!$E$6:$E$405,'AVANCE REAL'!$C$6:$C$405,$B39,'AVANCE REAL'!$D$6:$D$405,$C39,'AVANCE REAL'!$A$6:$A$405,"<="&MIN(P$5,PARÁMETROS!$B$7)) -> 0 | Q39: =_xlfn.MAXIFS('AVANCE REAL'!$E$6:$E$405,'AVANCE REAL'!$C$6:$C$405,$B39,'AVANCE REAL'!$D$6:$D$405,$C39,'AVANCE REAL'!$A$6:$A$405,"<="&MIN(Q$5,PARÁMETROS!$B$7)) -> 0 | R39: =_xlfn.MAXIFS('AVANCE REAL'!$E$6:$E$405,'AVANCE REAL'!$C$6:$C$405,$B39,'AVANCE REAL'!$D$6:$D$405,$C39,'AVANCE REAL'!$A$6:$A$405,"<="&MIN(R$5,PARÁMETROS!$B$7)) -> 0 | S39: =_xlfn.MAXIFS('AVANCE REAL'!$E$6:$E$405,'AVANCE REAL'!$C$6:$C$405,$B39,'AVANCE REAL'!$D$6:$D$405,$C39,'AVANCE REAL'!$A$6:$A$405,"<="&MIN(S$5,PARÁMETROS!$B$7)) -> 0 | ... AK39: =_xlfn.MAXIFS('AVANCE REAL'!$E$6:$E$405,'AVANCE REAL'!$C$6:$C$405,$B39,'AVANCE REAL'!$D$6:$D$405,$C39,'AVANCE REAL'!$A$6:$A$405,"<="&MIN(AK$5,PARÁMETROS!$B$7)) -> 0
B40: =B13 -> NIVEL 1 | C40: =C13 -> Curado | L40: =_xlfn.MAXIFS('AVANCE REAL'!$E$6:$E$405,'AVANCE REAL'!$C$6:$C$405,$B40,'AVANCE REAL'!$D$6:$D$405,$C40,'AVANCE REAL'!$A$6:$A$405,"<="&MIN(L$5,PARÁMETROS!$B$7)) -> 0 | M40: =_xlfn.MAXIFS('AVANCE REAL'!$E$6:$E$405,'AVANCE REAL'!$C$6:$C$405,$B40,'AVANCE REAL'!$D$6:$D$405,$C40,'AVANCE REAL'!$A$6:$A$405,"<="&MIN(M$5,PARÁMETROS!$B$7)) -> 0 | N40: =_xlfn.MAXIFS('AVANCE REAL'!$E$6:$E$405,'AVANCE REAL'!$C$6:$C$405,$B40,'AVANCE REAL'!$D$6:$D$405,$C40,'AVANCE REAL'!$A$6:$A$405,"<="&MIN(N$5,PARÁMETROS!$B$7)) -> 0 | O40: =_xlfn.MAXIFS('AVANCE REAL'!$E$6:$E$405,'AVANCE REAL'!$C$6:$C$405,$B40,'AVANCE REAL'!$D$6:$D$405,$C40,'AVANCE REAL'!$A$6:$A$405,"<="&MIN(O$5,PARÁMETROS!$B$7)) -> 0 | P40: =_xlfn.MAXIFS('AVANCE REAL'!$E$6:$E$405,'AVANCE REAL'!$C$6:$C$405,$B40,'AVANCE REAL'!$D$6:$D$405,$C40,'AVANCE REAL'!$A$6:$A$405,"<="&MIN(P$5,PARÁMETROS!$B$7)) -> 0 | Q40: =_xlfn.MAXIFS('AVANCE REAL'!$E$6:$E$405,'AVANCE REAL'!$C$6:$C$405,$B40,'AVANCE REAL'!$D$6:$D$405,$C40,'AVANCE REAL'!$A$6:$A$405,"<="&MIN(Q$5,PARÁMETROS!$B$7)) -> 0 | R40: =_xlfn.MAXIFS('AVANCE REAL'!$E$6:$E$405,'AVANCE REAL'!$C$6:$C$405,$B40,'AVANCE REAL'!$D$6:$D$405,$C40,'AVANCE REAL'!$A$6:$A$405,"<="&MIN(R$5,PARÁMETROS!$B$7)) -> 0 | S40: =_xlfn.MAXIFS('AVANCE REAL'!$E$6:$E$405,'AVANCE REAL'!$C$6:$C$405,$B40,'AVANCE REAL'!$D$6:$D$405,$C40,'AVANCE REAL'!$A$6:$A$405,"<="&MIN(S$5,PARÁMETROS!$B$7)) -> 0 | ... AK40: =_xlfn.MAXIFS('AVANCE REAL'!$E$6:$E$405,'AVANCE REAL'!$C$6:$C$405,$B40,'AVANCE REAL'!$D$6:$D$405,$C40,'AVANCE REAL'!$A$6:$A$405,"<="&MIN(AK$5,PARÁMETROS!$B$7)) -> 0
B41: =B14 -> NIVEL 2 | C41: =C14 -> Acero | L41: =_xlfn.MAXIFS('AVANCE REAL'!$E$6:$E$405,'AVANCE REAL'!$C$6:$C$405,$B41,'AVANCE REAL'!$D$6:$D$405,$C41,'AVANCE REAL'!$A$6:$A$405,"<="&MIN(L$5,PARÁMETROS!$B$7)) -> 0 | M41: =_xlfn.MAXIFS('AVANCE REAL'!$E$6:$E$405,'AVANCE REAL'!$C$6:$C$405,$B41,'AVANCE REAL'!$D$6:$D$405,$C41,'AVANCE REAL'!$A$6:$A$405,"<="&MIN(M$5,PARÁMETROS!$B$7)) -> 0 | N41: =_xlfn.MAXIFS('AVANCE REAL'!$E$6:$E$405,'AVANCE REAL'!$C$6:$C$405,$B41,'AVANCE REAL'!$D$6:$D$405,$C41,'AVANCE REAL'!$A$6:$A$405,"<="&MIN(N$5,PARÁMETROS!$B$7)) -> 0 | O41: =_xlfn.MAXIFS('AVANCE REAL'!$E$6:$E$405,'AVANCE REAL'!$C$6:$C$405,$B41,'AVANCE REAL'!$D$6:$D$405,$C41,'AVANCE REAL'!$A$6:$A$405,"<="&MIN(O$5,PARÁMETROS!$B$7)) -> 0 | P41: =_xlfn.MAXIFS('AVANCE REAL'!$E$6:$E$405,'AVANCE REAL'!$C$6:$C$405,$B41,'AVANCE REAL'!$D$6:$D$405,$C41,'AVANCE REAL'!$A$6:$A$405,"<="&MIN(P$5,PARÁMETROS!$B$7)) -> 0 | Q41: =_xlfn.MAXIFS('AVANCE REAL'!$E$6:$E$405,'AVANCE REAL'!$C$6:$C$405,$B41,'AVANCE REAL'!$D$6:$D$405,$C41,'AVANCE REAL'!$A$6:$A$405,"<="&MIN(Q$5,PARÁMETROS!$B$7)) -> 0 | R41: =_xlfn.MAXIFS('AVANCE REAL'!$E$6:$E$405,'AVANCE REAL'!$C$6:$C$405,$B41,'AVANCE REAL'!$D$6:$D$405,$C41,'AVANCE REAL'!$A$6:$A$405,"<="&MIN(R$5,PARÁMETROS!$B$7)) -> 0 | S41: =_xlfn.MAXIFS('AVANCE REAL'!$E$6:$E$405,'AVANCE REAL'!$C$6:$C$405,$B41,'AVANCE REAL'!$D$6:$D$405,$C41,'AVANCE REAL'!$A$6:$A$405,"<="&MIN(S$5,PARÁMETROS!$B$7)) -> 0 | ... AK41: =_xlfn.MAXIFS('AVANCE REAL'!$E$6:$E$405,'AVANCE REAL'!$C$6:$C$405,$B41,'AVANCE REAL'!$D$6:$D$405,$C41,'AVANCE REAL'!$A$6:$A$405,"<="&MIN(AK$5,PARÁMETROS!$B$7)) -> 0
B42: =B15 -> NIVEL 2 | C42: =C15 -> Encofrado | L42: =_xlfn.MAXIFS('AVANCE REAL'!$E$6:$E$405,'AVANCE REAL'!$C$6:$C$405,$B42,'AVANCE REAL'!$D$6:$D$405,$C42,'AVANCE REAL'!$A$6:$A$405,"<="&MIN(L$5,PARÁMETROS!$B$7)) -> 0 | M42: =_xlfn.MAXIFS('AVANCE REAL'!$E$6:$E$405,'AVANCE REAL'!$C$6:$C$405,$B42,'AVANCE REAL'!$D$6:$D$405,$C42,'AVANCE REAL'!$A$6:$A$405,"<="&MIN(M$5,PARÁMETROS!$B$7)) -> 0 | N42: =_xlfn.MAXIFS('AVANCE REAL'!$E$6:$E$405,'AVANCE REAL'!$C$6:$C$405,$B42,'AVANCE REAL'!$D$6:$D$405,$C42,'AVANCE REAL'!$A$6:$A$405,"<="&MIN(N$5,PARÁMETROS!$B$7)) -> 0 | O42: =_xlfn.MAXIFS('AVANCE REAL'!$E$6:$E$405,'AVANCE REAL'!$C$6:$C$405,$B42,'AVANCE REAL'!$D$6:$D$405,$C42,'AVANCE REAL'!$A$6:$A$405,"<="&MIN(O$5,PARÁMETROS!$B$7)) -> 0 | P42: =_xlfn.MAXIFS('AVANCE REAL'!$E$6:$E$405,'AVANCE REAL'!$C$6:$C$405,$B42,'AVANCE REAL'!$D$6:$D$405,$C42,'AVANCE REAL'!$A$6:$A$405,"<="&MIN(P$5,PARÁMETROS!$B$7)) -> 0 | Q42: =_xlfn.MAXIFS('AVANCE REAL'!$E$6:$E$405,'AVANCE REAL'!$C$6:$C$405,$B42,'AVANCE REAL'!$D$6:$D$405,$C42,'AVANCE REAL'!$A$6:$A$405,"<="&MIN(Q$5,PARÁMETROS!$B$7)) -> 0 | R42: =_xlfn.MAXIFS('AVANCE REAL'!$E$6:$E$405,'AVANCE REAL'!$C$6:$C$405,$B42,'AVANCE REAL'!$D$6:$D$405,$C42,'AVANCE REAL'!$A$6:$A$405,"<="&MIN(R$5,PARÁMETROS!$B$7)) -> 0 | S42: =_xlfn.MAXIFS('AVANCE REAL'!$E$6:$E$405,'AVANCE REAL'!$C$6:$C$405,$B42,'AVANCE REAL'!$D$6:$D$405,$C42,'AVANCE REAL'!$A$6:$A$405,"<="&MIN(S$5,PARÁMETROS!$B$7)) -> 0 | ... AK42: =_xlfn.MAXIFS('AVANCE REAL'!$E$6:$E$405,'AVANCE REAL'!$C$6:$C$405,$B42,'AVANCE REAL'!$D$6:$D$405,$C42,'AVANCE REAL'!$A$6:$A$405,"<="&MIN(AK$5,PARÁMETROS!$B$7)) -> 0
B43: =B16 -> NIVEL 2 | C43: =C16 -> Concreto | L43: =_xlfn.MAXIFS('AVANCE REAL'!$E$6:$E$405,'AVANCE REAL'!$C$6:$C$405,$B43,'AVANCE REAL'!$D$6:$D$405,$C43,'AVANCE REAL'!$A$6:$A$405,"<="&MIN(L$5,PARÁMETROS!$B$7)) -> 0 | M43: =_xlfn.MAXIFS('AVANCE REAL'!$E$6:$E$405,'AVANCE REAL'!$C$6:$C$405,$B43,'AVANCE REAL'!$D$6:$D$405,$C43,'AVANCE REAL'!$A$6:$A$405,"<="&MIN(M$5,PARÁMETROS!$B$7)) -> 0 | N43: =_xlfn.MAXIFS('AVANCE REAL'!$E$6:$E$405,'AVANCE REAL'!$C$6:$C$405,$B43,'AVANCE REAL'!$D$6:$D$405,$C43,'AVANCE REAL'!$A$6:$A$405,"<="&MIN(N$5,PARÁMETROS!$B$7)) -> 0 | O43: =_xlfn.MAXIFS('AVANCE REAL'!$E$6:$E$405,'AVANCE REAL'!$C$6:$C$405,$B43,'AVANCE REAL'!$D$6:$D$405,$C43,'AVANCE REAL'!$A$6:$A$405,"<="&MIN(O$5,PARÁMETROS!$B$7)) -> 0 | P43: =_xlfn.MAXIFS('AVANCE REAL'!$E$6:$E$405,'AVANCE REAL'!$C$6:$C$405,$B43,'AVANCE REAL'!$D$6:$D$405,$C43,'AVANCE REAL'!$A$6:$A$405,"<="&MIN(P$5,PARÁMETROS!$B$7)) -> 0 | Q43: =_xlfn.MAXIFS('AVANCE REAL'!$E$6:$E$405,'AVANCE REAL'!$C$6:$C$405,$B43,'AVANCE REAL'!$D$6:$D$405,$C43,'AVANCE REAL'!$A$6:$A$405,"<="&MIN(Q$5,PARÁMETROS!$B$7)) -> 0 | R43: =_xlfn.MAXIFS('AVANCE REAL'!$E$6:$E$405,'AVANCE REAL'!$C$6:$C$405,$B43,'AVANCE REAL'!$D$6:$D$405,$C43,'AVANCE REAL'!$A$6:$A$405,"<="&MIN(R$5,PARÁMETROS!$B$7)) -> 0 | S43: =_xlfn.MAXIFS('AVANCE REAL'!$E$6:$E$405,'AVANCE REAL'!$C$6:$C$405,$B43,'AVANCE REAL'!$D$6:$D$405,$C43,'AVANCE REAL'!$A$6:$A$405,"<="&MIN(S$5,PARÁMETROS!$B$7)) -> 0 | ... AK43: =_xlfn.MAXIFS('AVANCE REAL'!$E$6:$E$405,'AVANCE REAL'!$C$6:$C$405,$B43,'AVANCE REAL'!$D$6:$D$405,$C43,'AVANCE REAL'!$A$6:$A$405,"<="&MIN(AK$5,PARÁMETROS!$B$7)) -> 0
B44: =B17 -> NIVEL 2 | C44: =C17 -> Curado | L44: =_xlfn.MAXIFS('AVANCE REAL'!$E$6:$E$405,'AVANCE REAL'!$C$6:$C$405,$B44,'AVANCE REAL'!$D$6:$D$405,$C44,'AVANCE REAL'!$A$6:$A$405,"<="&MIN(L$5,PARÁMETROS!$B$7)) -> 0 | M44: =_xlfn.MAXIFS('AVANCE REAL'!$E$6:$E$405,'AVANCE REAL'!$C$6:$C$405,$B44,'AVANCE REAL'!$D$6:$D$405,$C44,'AVANCE REAL'!$A$6:$A$405,"<="&MIN(M$5,PARÁMETROS!$B$7)) -> 0 | N44: =_xlfn.MAXIFS('AVANCE REAL'!$E$6:$E$405,'AVANCE REAL'!$C$6:$C$405,$B44,'AVANCE REAL'!$D$6:$D$405,$C44,'AVANCE REAL'!$A$6:$A$405,"<="&MIN(N$5,PARÁMETROS!$B$7)) -> 0 | O44: =_xlfn.MAXIFS('AVANCE REAL'!$E$6:$E$405,'AVANCE REAL'!$C$6:$C$405,$B44,'AVANCE REAL'!$D$6:$D$405,$C44,'AVANCE REAL'!$A$6:$A$405,"<="&MIN(O$5,PARÁMETROS!$B$7)) -> 0 | P44: =_xlfn.MAXIFS('AVANCE REAL'!$E$6:$E$405,'AVANCE REAL'!$C$6:$C$405,$B44,'AVANCE REAL'!$D$6:$D$405,$C44,'AVANCE REAL'!$A$6:$A$405,"<="&MIN(P$5,PARÁMETROS!$B$7)) -> 0 | Q44: =_xlfn.MAXIFS('AVANCE REAL'!$E$6:$E$405,'AVANCE REAL'!$C$6:$C$405,$B44,'AVANCE REAL'!$D$6:$D$405,$C44,'AVANCE REAL'!$A$6:$A$405,"<="&MIN(Q$5,PARÁMETROS!$B$7)) -> 0 | R44: =_xlfn.MAXIFS('AVANCE REAL'!$E$6:$E$405,'AVANCE REAL'!$C$6:$C$405,$B44,'AVANCE REAL'!$D$6:$D$405,$C44,'AVANCE REAL'!$A$6:$A$405,"<="&MIN(R$5,PARÁMETROS!$B$7)) -> 0 | S44: =_xlfn.MAXIFS('AVANCE REAL'!$E$6:$E$405,'AVANCE REAL'!$C$6:$C$405,$B44,'AVANCE REAL'!$D$6:$D$405,$C44,'AVANCE REAL'!$A$6:$A$405,"<="&MIN(S$5,PARÁMETROS!$B$7)) -> 0 | ... AK44: =_xlfn.MAXIFS('AVANCE REAL'!$E$6:$E$405,'AVANCE REAL'!$C$6:$C$405,$B44,'AVANCE REAL'!$D$6:$D$405,$C44,'AVANCE REAL'!$A$6:$A$405,"<="&MIN(AK$5,PARÁMETROS!$B$7)) -> 0
... B56: =B29 -> NIVEL 5 | C56: =C29 -> Curado | L56: =_xlfn.MAXIFS('AVANCE REAL'!$E$6:$E$405,'AVANCE REAL'!$C$6:$C$405,$B56,'AVANCE REAL'!$D$6:$D$405,$C56,'AVANCE REAL'!$A$6:$A$405,"<="&MIN(L$5,PARÁMETROS!$B$7)) -> 0 | M56: =_xlfn.MAXIFS('AVANCE REAL'!$E$6:$E$405,'AVANCE REAL'!$C$6:$C$405,$B56,'AVANCE REAL'!$D$6:$D$405,$C56,'AVANCE REAL'!$A$6:$A$405,"<="&MIN(M$5,PARÁMETROS!$B$7)) -> 0 | N56: =_xlfn.MAXIFS('AVANCE REAL'!$E$6:$E$405,'AVANCE REAL'!$C$6:$C$405,$B56,'AVANCE REAL'!$D$6:$D$405,$C56,'AVANCE REAL'!$A$6:$A$405,"<="&MIN(N$5,PARÁMETROS!$B$7)) -> 0 | O56: =_xlfn.MAXIFS('AVANCE REAL'!$E$6:$E$405,'AVANCE REAL'!$C$6:$C$405,$B56,'AVANCE REAL'!$D$6:$D$405,$C56,'AVANCE REAL'!$A$6:$A$405,"<="&MIN(O$5,PARÁMETROS!$B$7)) -> 0 | P56: =_xlfn.MAXIFS('AVANCE REAL'!$E$6:$E$405,'AVANCE REAL'!$C$6:$C$405,$B56,'AVANCE REAL'!$D$6:$D$405,$C56,'AVANCE REAL'!$A$6:$A$405,"<="&MIN(P$5,PARÁMETROS!$B$7)) -> 0 | Q56: =_xlfn.MAXIFS('AVANCE REAL'!$E$6:$E$405,'AVANCE REAL'!$C$6:$C$405,$B56,'AVANCE REAL'!$D$6:$D$405,$C56,'AVANCE REAL'!$A$6:$A$405,"<="&MIN(Q$5,PARÁMETROS!$B$7)) -> 0 | R56: =_xlfn.MAXIFS('AVANCE REAL'!$E$6:$E$405,'AVANCE REAL'!$C$6:$C$405,$B56,'AVANCE REAL'!$D$6:$D$405,$C56,'AVANCE REAL'!$A$6:$A$405,"<="&MIN(R$5,PARÁMETROS!$B$7)) -> 0 | S56: =_xlfn.MAXIFS('AVANCE REAL'!$E$6:$E$405,'AVANCE REAL'!$C$6:$C$405,$B56,'AVANCE REAL'!$D$6:$D$405,$C56,'AVANCE REAL'!$A$6:$A$405,"<="&MIN(S$5,PARÁMETROS!$B$7)) -> 0 | ... AK56: =_xlfn.MAXIFS('AVANCE REAL'!$E$6:$E$405,'AVANCE REAL'!$C$6:$C$405,$B56,'AVANCE REAL'!$D$6:$D$405,$C56,'AVANCE REAL'!$A$6:$A$405,"<="&MIN(AK$5,PARÁMETROS!$B$7)) -> 0

Sheet AVANCE REAL
A1: AVANCE REAL - REGISTRO SEMANAL (única hoja que se llena en obra)
A2: Llenar solo las celdas amarillas. Tabla A: % ejecutado ACUMULADO de cada partida. Tabla B: materiales recibidos y usados.
A3: Ejemplo de llenado (no se suma): 12/10/2026 | CIMENTACIÓN | Acero | 40 % · 12/10/2026 | Cemento Portland IP 42.5 kg | recibido 200 | usado 150
A5: Fecha | B5: Semana N° | C5: Nivel | D5: Partida | E5: % ejecutado acumulado | F5: Observaciones | H5: Fecha | I5: Insumo | J5: Unidad | K5: Cantidad recibida | L5: Cantidad usada | M5: Guía / proveedor | N5: Observaciones
B6: =IF(A6="","",INT((A6-PARÁMETROS!$B$6)/7)+1) | J6: =IF(I6="","",INDEX(PARÁMETROS!$B$70:$B$89,MATCH(I6,PARÁMETROS!$A$70:$A$89,0)))
B7: =IF(A7="","",INT((A7-PARÁMETROS!$B$6)/7)+1) | J7: =IF(I7="","",INDEX(PARÁMETROS!$B$70:$B$89,MATCH(I7,PARÁMETROS!$A$70:$A$89,0)))
B8: =IF(A8="","",INT((A8-PARÁMETROS!$B$6)/7)+1) | J8: =IF(I8="","",INDEX(PARÁMETROS!$B$70:$B$89,MATCH(I8,PARÁMETROS!$A$70:$A$89,0)))
B9: =IF(A9="","",INT((A9-PARÁMETROS!$B$6)/7)+1) | J9: =IF(I9="","",INDEX(PARÁMETROS!$B$70:$B$89,MATCH(I9,PARÁMETROS!$A$70:$A$89,0)))
B10: =IF(A10="","",INT((A10-PARÁMETROS!$B$6)/7)+1) | J10: =IF(I10="","",INDEX(PARÁMETROS!$B$70:$B$89,MATCH(I10,PARÁMETROS!$A$70:$A$89,0)))
B11: =IF(A11="","",INT((A11-PARÁMETROS!$B$6)/7)+1) | J11: =IF(I11="","",INDEX(PARÁMETROS!$B$70:$B$89,MATCH(I11,PARÁMETROS!$A$70:$A$89,0)))
B12: =IF(A12="","",INT((A12-PARÁMETROS!$B$6)/7)+1) | J12: =IF(I12="","",INDEX(PARÁMETROS!$B$70:$B$89,MATCH(I12,PARÁMETROS!$A$70:$A$89,0)))
B13: =IF(A13="","",INT((A13-PARÁMETROS!$B$6)/7)+1) | J13: =IF(I13="","",INDEX(PARÁMETROS!$B$70:$B$89,MATCH(I13,PARÁMETROS!$A$70:$A$89,0)))
B14: =IF(A14="","",INT((A14-PARÁMETROS!$B$6)/7)+1) | J14: =IF(I14="","",INDEX(PARÁMETROS!$B$70:$B$89,MATCH(I14,PARÁMETROS!$A$70:$A$89,0)))
